Workbook

Sheet Roofs 1
H1: Exhibit B
V2: Explanatory Notes:
H3: RESERVE EXPENDITURES | P3: RefYr | U3: 1) | V3: 0.03 | W3: is the estimated future Inflation Rate for estimating Future Replacement Costs.
H4: for | P4: 2023 | U4: 2) | V4: Fiscal Year is beginning January 1 and ending December 31.
H5: ='Funding Plan'!G9 -> Association
B6: Line Item | D6: Estimated | J6: Estimated Year Last Replaced | L6: Life Analysis, Years | P6: Estimated Year of 1st Replacement | R6: 2024 Unit Cost | T6: 2024 Cost of Replacement | V6: Total Future Cost of Replacement | X6: 1 | Z6: 2 | AB6: 3 | AD6: 4 | AF6: 5 | AH6: 6 | AJ6: 7 | AL6: 8 | AN6: 9 | AP6: 10 | AR6: 11 | AT6: 12 | AV6: 13 | AX6: 14 | AZ6: 15
D7: Quantity | F7: Units | H7: Reserve Component Inventory | L7: Useful | N7: Remaining | X7: 2024 | Z7: =X7+1 -> 2025 | AA7: =Y7+1 -> 1 | AB7: =Z7+1 -> 2026 | AC7: =AA7+1 -> 2 | AD7: =AB7+1 -> 2027 | AE7: =AC7+1 -> 3 | AF7: =AD7+1 -> 2028 | AG7: =AE7+1 -> 4 | ... AZ7: =AX7+1 -> 2038
H9: Roofs
B11: 1 | D11: 1 | F11: x | H11: x | J11: 1 | K11: 23 | L11: 1 | N11: =P11-O11 -> -1999 | O11: =P4 -> 2023 | P11: =J11+K11 -> 24 | R11: 1 | T11: =D11*R11 -> 1 | V11: =SUM(X11:AZ11)+SUM(J61:AL61) -> 0 | X11: =IF(X$6=$N11,FV($V$3,$N11-1,,-$T11,0),0) -> 0 | Z11: =IF(Z$6=$N11,FV($V$3,$N11-1,,-$T11,0),0) -> 0 | AB11: =IF(AB$6=$N11,FV($V$3,$N11-1,,-$T11,0),0) -> 0 | AD11: =IF(AD$6=$N11,FV($V$3,$N11-1,,-$T11,0),0) -> 0 | AF11: =IF(AF$6=$N11,FV($V$3,$N11-1,,-$T11,0),0) -> 0 | AH11: =IF(AH$6=$N11,FV($V$3,$N11-1,,-$T11,0),0) -> 0 | AJ11: =IF(AJ$6=$N11,FV($V$3,$N11-1,,-$T11,0),0) -> 0 | AL11: =IF(AL$6=$N11,FV($V$3,$N11-1,,-$T11,0),0) -> 0 | AN11: =IF(AN$6=$N11,FV($V$3,$N11-1,,-$T11,0),0) -> 0 | AP11: =IF(AP$6=$N11,FV($V$3,$N11-1,,-$T11,0),0) -> 0 | AR11: =IF(AR$6=$N11,FV($V$3,$N11-1,,-$T11,0),0) -> 0 | AT11: =IF(AT$6=$N11,FV($V$3,$N11-1,,-$T11,0),0) -> 0 | AV11: =IF(AV$6=$N11,FV($V$3,$N11-1,,-$T11,0),0) -> 0 | AX11: =IF(AX$6=$N11,FV($V$3,$N11-1,,-$T11,0),0) -> 0 | AZ11: =IF(AZ$6=$N11,FV($V$3,$N11-1,,-$T11,0),0) -> 0
B12: =+B11+1 -> 2 | D12: 1 | F12: =F11 -> x | H12: x | J12: 1 | K12: 23 | L12: =L11 -> 1 | N12: =P12-O12 -> -1999 | O12: =O11 -> 2023 | P12: =J12+K12 -> 24 | R12: =R11 -> 1 | T12: =D12*R12 -> 1 | V12: =SUM(X12:AZ12)+SUM(J62:AL62) -> 0 | X12: =IF(X$6=$N12,FV($V$3,$N12-1,,-$T12,0),0) -> 0 | Z12: =IF(Z$6=$N12,FV($V$3,$N12-1,,-$T12,0),0) -> 0 | AB12: =IF(AB$6=$N12,FV($V$3,$N12-1,,-$T12,0),0) -> 0 | AD12: =IF(AD$6=$N12,FV($V$3,$N12-1,,-$T12,0),0) -> 0 | AF12: =IF(AF$6=$N12,FV($V$3,$N12-1,,-$T12,0),0) -> 0 | AH12: =IF(AH$6=$N12,FV($V$3,$N12-1,,-$T12,0),0) -> 0 | AJ12: =IF(AJ$6=$N12,FV($V$3,$N12-1,,-$T12,0),0) -> 0 | AL12: =IF(AL$6=$N12,FV($V$3,$N12-1,,-$T12,0),0) -> 0 | AN12: =IF(AN$6=$N12,FV($V$3,$N12-1,,-$T12,0),0) -> 0 | AP12: =IF(AP$6=$N12,FV($V$3,$N12-1,,-$T12,0),0) -> 0 | AR12: =IF(AR$6=$N12,FV($V$3,$N12-1,,-$T12,0),0) -> 0 | AT12: =IF(AT$6=$N12,FV($V$3,$N12-1,,-$T12,0),0) -> 0 | AV12: =IF(AV$6=$N12,FV($V$3,$N12-1,,-$T12,0),0) -> 0 | AX12: =IF(AX$6=$N12,FV($V$3,$N12-1,,-$T12,0),0) -> 0 | AZ12: =IF(AZ$6=$N12,FV($V$3,$N12-1,,-$T12,0),0) -> 0
B13: =+B12+1 -> 3 | D13: 1 | F13: =F12 -> x | H13: x | J13: 1 | K13: 23 | L13: =L12 -> 1 | N13: =P13-O13 -> -1999 | O13: =O12 -> 2023 | P13: =J13+K13 -> 24 | R13: =R12 -> 1 | T13: =D13*R13 -> 1 | V13: =SUM(X13:AZ13)+SUM(J63:AL63) -> 0 | X13: =IF(X$6=$N13,FV($V$3,$N13-1,,-$T13,0),0) -> 0 | Z13: =IF(Z$6=$N13,FV($V$3,$N13-1,,-$T13,0),0) -> 0 | AB13: =IF(AB$6=$N13,FV($V$3,$N13-1,,-$T13,0),0) -> 0 | AD13: =IF(AD$6=$N13,FV($V$3,$N13-1,,-$T13,0),0) -> 0 | AF13: =IF(AF$6=$N13,FV($V$3,$N13-1,,-$T13,0),0) -> 0 | AH13: =IF(AH$6=$N13,FV($V$3,$N13-1,,-$T13,0),0) -> 0 | AJ13: =IF(AJ$6=$N13,FV($V$3,$N13-1,,-$T13,0),0) -> 0 | AL13: =IF(AL$6=$N13,FV($V$3,$N13-1,,-$T13,0),0) -> 0 | AN13: =IF(AN$6=$N13,FV($V$3,$N13-1,,-$T13,0),0) -> 0 | AP13: =IF(AP$6=$N13,FV($V$3,$N13-1,,-$T13,0),0) -> 0 | AR13: =IF(AR$6=$N13,FV($V$3,$N13-1,,-$T13,0),0) -> 0 | AT13: =IF(AT$6=$N13,FV($V$3,$N13-1,,-$T13,0),0) -> 0 | AV13: =IF(AV$6=$N13,FV($V$3,$N13-1,,-$T13,0),0) -> 0 | AX13: =IF(AX$6=$N13,FV($V$3,$N13-1,,-$T13,0),0) -> 0 | AZ13: =IF(AZ$6=$N13,FV($V$3,$N13-1,,-$T13,0),0) -> 0
B14: =+B13+1 -> 4 | D14: 1 | F14: =F13 -> x | H14: x | J14: 1 | K14: 23 | L14: =L13 -> 1 | N14: =P14-O14 -> -1999 | O14: =O13 -> 2023 | P14: =J14+K14 -> 24 | R14: =R13 -> 1 | T14: =D14*R14 -> 1 | V14: =SUM(X14:AZ14)+SUM(J64:AL64) -> 0 | X14: =IF(X$6=$N14,FV($V$3,$N14-1,,-$T14,0),0) -> 0 | Z14: =IF(Z$6=$N14,FV($V$3,$N14-1,,-$T14,0),0) -> 0 | AB14: =IF(AB$6=$N14,FV($V$3,$N14-1,,-$T14,0),0) -> 0 | AD14: =IF(AD$6=$N14,FV($V$3,$N14-1,,-$T14,0),0) -> 0 | AF14: =IF(AF$6=$N14,FV($V$3,$N14-1,,-$T14,0),0) -> 0 | AH14: =IF(AH$6=$N14,FV($V$3,$N14-1,,-$T14,0),0) -> 0 | AJ14: =IF(AJ$6=$N14,FV($V$3,$N14-1,,-$T14,0),0) -> 0 | AL14: =IF(AL$6=$N14,FV($V$3,$N14-1,,-$T14,0),0) -> 0 | AN14: =IF(AN$6=$N14,FV($V$3,$N14-1,,-$T14,0),0) -> 0 | AP14: =IF(AP$6=$N14,FV($V$3,$N14-1,,-$T14,0),0) -> 0 | AR14: =IF(AR$6=$N14,FV($V$3,$N14-1,,-$T14,0),0) -> 0 | AT14: =IF(AT$6=$N14,FV($V$3,$N14-1,,-$T14,0),0) -> 0 | AV14: =IF(AV$6=$N14,FV($V$3,$N14-1,,-$T14,0),0) -> 0 | AX14: =IF(AX$6=$N14,FV($V$3,$N14-1,,-$T14,0),0) -> 0 | AZ14: =IF(AZ$6=$N14,FV($V$3,$N14-1,,-$T14,0),0) -> 0
B15: =+B14+1 -> 5 | D15: 1 | F15: =F14 -> x | H15: x | J15: 1 | K15: 23 | L15: =L14 -> 1 | N15: =P15-O15 -> -1999 | O15: =O14 -> 2023 | P15: =J15+K15 -> 24 | R15: =R14 -> 1 | T15: =D15*R15 -> 1 | V15: =SUM(X15:AZ15)+SUM(J65:AL65) -> 0 | X15: =IF(X$6=$N15,FV($V$3,$N15-1,,-$T15,0),0) -> 0 | Z15: =IF(Z$6=$N15,FV($V$3,$N15-1,,-$T15,0),0) -> 0 | AB15: =IF(AB$6=$N15,FV($V$3,$N15-1,,-$T15,0),0) -> 0 | AD15: =IF(AD$6=$N15,FV($V$3,$N15-1,,-$T15,0),0) -> 0 | AF15: =IF(AF$6=$N15,FV($V$3,$N15-1,,-$T15,0),0) -> 0 | AH15: =IF(AH$6=$N15,FV($V$3,$N15-1,,-$T15,0),0) -> 0 | AJ15: =IF(AJ$6=$N15,FV($V$3,$N15-1,,-$T15,0),0) -> 0 | AL15: =IF(AL$6=$N15,FV($V$3,$N15-1,,-$T15,0),0) -> 0 | AN15: =IF(AN$6=$N15,FV($V$3,$N15-1,,-$T15,0),0) -> 0 | AP15: =IF(AP$6=$N15,FV($V$3,$N15-1,,-$T15,0),0) -> 0 | AR15: =IF(AR$6=$N15,FV($V$3,$N15-1,,-$T15,0),0) -> 0 | AT15: =IF(AT$6=$N15,FV($V$3,$N15-1,,-$T15,0),0) -> 0 | AV15: =IF(AV$6=$N15,FV($V$3,$N15-1,,-$T15,0),0) -> 0 | AX15: =IF(AX$6=$N15,FV($V$3,$N15-1,,-$T15,0),0) -> 0 | AZ15: =IF(AZ$6=$N15,FV($V$3,$N15-1,,-$T15,0),0) -> 0
B16: =+B15+1 -> 6 | D16: 1 | F16: =F15 -> x | H16: x | J16: 1 | K16: 23 | L16: =L15 -> 1 | N16: =P16-O16 -> -1999 | O16: =O15 -> 2023 | P16: =J16+K16 -> 24 | R16: =R15 -> 1 | T16: =D16*R16 -> 1 | V16: =SUM(X16:AZ16)+SUM(J66:AL66) -> 0 | X16: =IF(X$6=$N16,FV($V$3,$N16-1,,-$T16,0),0) -> 0 | Z16: =IF(Z$6=$N16,FV($V$3,$N16-1,,-$T16,0),0) -> 0 | AB16: =IF(AB$6=$N16,FV($V$3,$N16-1,,-$T16,0),0) -> 0 | AD16: =IF(AD$6=$N16,FV($V$3,$N16-1,,-$T16,0),0) -> 0 | AF16: =IF(AF$6=$N16,FV($V$3,$N16-1,,-$T16,0),0) -> 0 | AH16: =IF(AH$6=$N16,FV($V$3,$N16-1,,-$T16,0),0) -> 0 | AJ16: =IF(AJ$6=$N16,FV($V$3,$N16-1,,-$T16,0),0) -> 0 | AL16: =IF(AL$6=$N16,FV($V$3,$N16-1,,-$T16,0),0) -> 0 | AN16: =IF(AN$6=$N16,FV($V$3,$N16-1,,-$T16,0),0) -> 0 | AP16: =IF(AP$6=$N16,FV($V$3,$N16-1,,-$T16,0),0) -> 0 | AR16: =IF(AR$6=$N16,FV($V$3,$N16-1,,-$T16,0),0) -> 0 | AT16: =IF(AT$6=$N16,FV($V$3,$N16-1,,-$T16,0),0) -> 0 | AV16: =IF(AV$6=$N16,FV($V$3,$N16-1,,-$T16,0),0) -> 0 | AX16: =IF(AX$6=$N16,FV($V$3,$N16-1,,-$T16,0),0) -> 0 | AZ16: =IF(AZ$6=$N16,FV($V$3,$N16-1,,-$T16,0),0) -> 0
B17: =+B16+1 -> 7 | D17: 1 | F17: =F16 -> x | H17: x | J17: 1 | K17: 23 | L17: =L16 -> 1 | N17: =P17-O17 -> -1999 | O17: =O16 -> 2023 | P17: =J17+K17 -> 24 | R17: =R16 -> 1 | T17: =D17*R17 -> 1 | V17: =SUM(X17:AZ17)+SUM(J67:AL67) -> 0 | X17: =IF(X$6=$N17,FV($V$3,$N17-1,,-$T17,0),0) -> 0 | Z17: =IF(Z$6=$N17,FV($V$3,$N17-1,,-$T17,0),0) -> 0 | AB17: =IF(AB$6=$N17,FV($V$3,$N17-1,,-$T17,0),0) -> 0 | AD17: =IF(AD$6=$N17,FV($V$3,$N17-1,,-$T17,0),0) -> 0 | AF17: =IF(AF$6=$N17,FV($V$3,$N17-1,,-$T17,0),0) -> 0 | AH17: =IF(AH$6=$N17,FV($V$3,$N17-1,,-$T17,0),0) -> 0 | AJ17: =IF(AJ$6=$N17,FV($V$3,$N17-1,,-$T17,0),0) -> 0 | AL17: =IF(AL$6=$N17,FV($V$3,$N17-1,,-$T17,0),0) -> 0 | AN17: =IF(AN$6=$N17,FV($V$3,$N17-1,,-$T17,0),0) -> 0 | AP17: =IF(AP$6=$N17,FV($V$3,$N17-1,,-$T17,0),0) -> 0 | AR17: =IF(AR$6=$N17,FV($V$3,$N17-1,,-$T17,0),0) -> 0 | AT17: =IF(AT$6=$N17,FV($V$3,$N17-1,,-$T17,0),0) -> 0 | AV17: =IF(AV$6=$N17,FV($V$3,$N17-1,,-$T17,0),0) -> 0 | AX17: =IF(AX$6=$N17,FV($V$3,$N17-1,,-$T17,0),0) -> 0 | AZ17: =IF(AZ$6=$N17,FV($V$3,$N17-1,,-$T17,0),0) -> 0
B18: =+B17+1 -> 8 | D18: 1 | F18: =F17 -> x | H18: x | J18: 1 | K18: 23 | L18: =L17 -> 1 | N18: =P18-O18 -> -1999 | O18: =O17 -> 2023 | P18: =J18+K18 -> 24 | R18: =R17 -> 1 | T18: =D18*R18 -> 1 | V18: =SUM(X18:AZ18)+SUM(J68:AL68) -> 0 | X18: =IF(X$6=$N18,FV($V$3,$N18-1,,-$T18,0),0) -> 0 | Z18: =IF(Z$6=$N18,FV($V$3,$N18-1,,-$T18,0),0) -> 0 | AB18: =IF(AB$6=$N18,FV($V$3,$N18-1,,-$T18,0),0) -> 0 | AD18: =IF(AD$6=$N18,FV($V$3,$N18-1,,-$T18,0),0) -> 0 | AF18: =IF(AF$6=$N18,FV($V$3,$N18-1,,-$T18,0),0) -> 0 | AH18: =IF(AH$6=$N18,FV($V$3,$N18-1,,-$T18,0),0) -> 0 | AJ18: =IF(AJ$6=$N18,FV($V$3,$N18-1,,-$T18,0),0) -> 0 | AL18: =IF(AL$6=$N18,FV($V$3,$N18-1,,-$T18,0),0) -> 0 | AN18: =IF(AN$6=$N18,FV($V$3,$N18-1,,-$T18,0),0) -> 0 | AP18: =IF(AP$6=$N18,FV($V$3,$N18-1,,-$T18,0),0) -> 0 | AR18: =IF(AR$6=$N18,FV($V$3,$N18-1,,-$T18,0),0) -> 0 | AT18: =IF(AT$6=$N18,FV($V$3,$N18-1,,-$T18,0),0) -> 0 | AV18: =IF(AV$6=$N18,FV($V$3,$N18-1,,-$T18,0),0) -> 0 | AX18: =IF(AX$6=$N18,FV($V$3,$N18-1,,-$T18,0),0) -> 0 | AZ18: =IF(AZ$6=$N18,FV($V$3,$N18-1,,-$T18,0),0) -> 0
B19: =+B18+1 -> 9 | D19: 1 | F19: =F18 -> x | H19: x | J19: 1 | K19: 23 | L19: =L18 -> 1 | N19: =P19-O19 -> -1999 | O19: =O18 -> 2023 | P19: =J19+K19 -> 24 | R19: =R18 -> 1 | T19: =D19*R19 -> 1 | V19: =SUM(X19:AZ19)+SUM(J69:AL69) -> 0 | X19: =IF(X$6=$N19,FV($V$3,$N19-1,,-$T19,0),0) -> 0 | Z19: =IF(Z$6=$N19,FV($V$3,$N19-1,,-$T19,0),0) -> 0 | AB19: =IF(AB$6=$N19,FV($V$3,$N19-1,,-$T19,0),0) -> 0 | AD19: =IF(AD$6=$N19,FV($V$3,$N19-1,,-$T19,0),0) -> 0 | AF19: =IF(AF$6=$N19,FV($V$3,$N19-1,,-$T19,0),0) -> 0 | AH19: =IF(AH$6=$N19,FV($V$3,$N19-1,,-$T19,0),0) -> 0 | AJ19: =IF(AJ$6=$N19,FV($V$3,$N19-1,,-$T19,0),0) -> 0 | AL19: =IF(AL$6=$N19,FV($V$3,$N19-1,,-$T19,0),0) -> 0 | AN19: =IF(AN$6=$N19,FV($V$3,$N19-1,,-$T19,0),0) -> 0 | AP19: =IF(AP$6=$N19,FV($V$3,$N19-1,,-$T19,0),0) -> 0 | AR19: =IF(AR$6=$N19,FV($V$3,$N19-1,,-$T19,0),0) -> 0 | AT19: =IF(AT$6=$N19,FV($V$3,$N19-1,,-$T19,0),0) -> 0 | AV19: =IF(AV$6=$N19,FV($V$3,$N19-1,,-$T19,0),0) -> 0 | AX19: =IF(AX$6=$N19,FV($V$3,$N19-1,,-$T19,0),0) -> 0 | AZ19: =IF(AZ$6=$N19,FV($V$3,$N19-1,,-$T19,0),0) -> 0
B20: =+B19+1 -> 10 | D20: 1 | F20: =F19 -> x | H20: x | J20: 1 | K20: 23 | L20: =L19 -> 1 | N20: =P20-O20 -> -1999 | O20: =O19 -> 2023 | P20: =J20+K20 -> 24 | R20: =R19 -> 1 | T20: =D20*R20 -> 1 | V20: =SUM(X20:AZ20)+SUM(J70:AL70) -> 0 | X20: =IF(X$6=$N20,FV($V$3,$N20-1,,-$T20,0),0) -> 0 | Z20: =IF(Z$6=$N20,FV($V$3,$N20-1,,-$T20,0),0) -> 0 | AB20: =IF(AB$6=$N20,FV($V$3,$N20-1,,-$T20,0),0) -> 0 | AD20: =IF(AD$6=$N20,FV($V$3,$N20-1,,-$T20,0),0) -> 0 | AF20: =IF(AF$6=$N20,FV($V$3,$N20-1,,-$T20,0),0) -> 0 | AH20: =IF(AH$6=$N20,FV($V$3,$N20-1,,-$T20,0),0) -> 0 | AJ20: =IF(AJ$6=$N20,FV($V$3,$N20-1,,-$T20,0),0) -> 0 | AL20: =IF(AL$6=$N20,FV($V$3,$N20-1,,-$T20,0),0) -> 0 | AN20: =IF(AN$6=$N20,FV($V$3,$N20-1,,-$T20,0),0) -> 0 | AP20: =IF(AP$6=$N20,FV($V$3,$N20-1,,-$T20,0),0) -> 0 | AR20: =IF(AR$6=$N20,FV($V$3,$N20-1,,-$T20,0),0) -> 0 | AT20: =IF(AT$6=$N20,FV($V$3,$N20-1,,-$T20,0),0) -> 0 | AV20: =IF(AV$6=$N20,FV($V$3,$N20-1,,-$T20,0),0) -> 0 | AX20: =IF(AX$6=$N20,FV($V$3,$N20-1,,-$T20,0),0) -> 0 | AZ20: =IF(AZ$6=$N20,FV($V$3,$N20-1,,-$T20,0),0) -> 0
B21: =+B20+1 -> 11 | D21: 1 | F21: =F20 -> x | H21: x | J21: 1 | K21: 23 | L21: =L20 -> 1 | N21: =P21-O21 -> -1999 | O21: =O20 -> 2023 | P21: =J21+K21 -> 24 | R21: =R20 -> 1 | T21: =D21*R21 -> 1 | V21: =SUM(X21:AZ21)+SUM(J71:AL71) -> 0 | X21: =IF(X$6=$N21,FV($V$3,$N21-1,,-$T21,0),0) -> 0 | Z21: =IF(Z$6=$N21,FV($V$3,$N21-1,,-$T21,0),0) -> 0 | AB21: =IF(AB$6=$N21,FV($V$3,$N21-1,,-$T21,0),0) -> 0 | AD21: =IF(AD$6=$N21,FV($V$3,$N21-1,,-$T21,0),0) -> 0 | AF21: =IF(AF$6=$N21,FV($V$3,$N21-1,,-$T21,0),0) -> 0 | AH21: =IF(AH$6=$N21,FV($V$3,$N21-1,,-$T21,0),0) -> 0 | AJ21: =IF(AJ$6=$N21,FV($V$3,$N21-1,,-$T21,0),0) -> 0 | AL21: =IF(AL$6=$N21,FV($V$3,$N21-1,,-$T21,0),0) -> 0 | AN21: =IF(AN$6=$N21,FV($V$3,$N21-1,,-$T21,0),0) -> 0 | AP21: =IF(AP$6=$N21,FV($V$3,$N21-1,,-$T21,0),0) -> 0 | AR21: =IF(AR$6=$N21,FV($V$3,$N21-1,,-$T21,0),0) -> 0 | AT21: =IF(AT$6=$N21,FV($V$3,$N21-1,,-$T21,0),0) -> 0 | AV21: =IF(AV$6=$N21,FV($V$3,$N21-1,,-$T21,0),0) -> 0 | AX21: =IF(AX$6=$N21,FV($V$3,$N21-1,,-$T21,0),0) -> 0 | AZ21: =IF(AZ$6=$N21,FV($V$3,$N21-1,,-$T21,0),0) -> 0
B22: =+B21+1 -> 12 | D22: 1 | F22: =F21 -> x | H22: x | J22: 1 | K22: 23 | L22: =L21 -> 1 | N22: =P22-O22 -> -1999 | O22: =O21 -> 2023 | P22: =J22+K22 -> 24 | R22: =R21 -> 1 | T22: =D22*R22 -> 1 | V22: =SUM(X22:AZ22)+SUM(J72:AL72) -> 0 | X22: =IF(X$6=$N22,FV($V$3,$N22-1,,-$T22,0),0) -> 0 | Z22: =IF(Z$6=$N22,FV($V$3,$N22-1,,-$T22,0),0) -> 0 | AB22: =IF(AB$6=$N22,FV($V$3,$N22-1,,-$T22,0),0) -> 0 | AD22: =IF(AD$6=$N22,FV($V$3,$N22-1,,-$T22,0),0) -> 0 | AF22: =IF(AF$6=$N22,FV($V$3,$N22-1,,-$T22,0),0) -> 0 | AH22: =IF(AH$6=$N22,FV($V$3,$N22-1,,-$T22,0),0) -> 0 | AJ22: =IF(AJ$6=$N22,FV($V$3,$N22-1,,-$T22,0),0) -> 0 | AL22: =IF(AL$6=$N22,FV($V$3,$N22-1,,-$T22,0),0) -> 0 | AN22: =IF(AN$6=$N22,FV($V$3,$N22-1,,-$T22,0),0) -> 0 | AP22: =IF(AP$6=$N22,FV($V$3,$N22-1,,-$T22,0),0) -> 0 | AR22: =IF(AR$6=$N22,FV($V$3,$N22-1,,-$T22,0),0) -> 0 | AT22: =IF(AT$6=$N22,FV($V$3,$N22-1,,-$T22,0),0) -> 0 | AV22: =IF(AV$6=$N22,FV($V$3,$N22-1,,-$T22,0),0) -> 0 | AX22: =IF(AX$6=$N22,FV($V$3,$N22-1,,-$T22,0),0) -> 0 | AZ22: =IF(AZ$6=$N22,FV($V$3,$N22-1,,-$T22,0),0) -> 0
B23: =+B22+1 -> 13 | D23: 1 | F23: =F22 -> x | H23: x | J23: 1 | K23: 23 | L23: =L22 -> 1 | N23: =P23-O23 -> -1999 | O23: =O22 -> 2023 | P23: =J23+K23 -> 24 | R23: =R22 -> 1 | T23: =D23*R23 -> 1 | V23: =SUM(X23:AZ23)+SUM(J73:AL73) -> 0 | X23: =IF(X$6=$N23,FV($V$3,$N23-1,,-$T23,0),0) -> 0 | Z23: =IF(Z$6=$N23,FV($V$3,$N23-1,,-$T23,0),0) -> 0 | AB23: =IF(AB$6=$N23,FV($V$3,$N23-1,,-$T23,0),0) -> 0 | AD23: =IF(AD$6=$N23,FV($V$3,$N23-1,,-$T23,0),0) -> 0 | AF23: =IF(AF$6=$N23,FV($V$3,$N23-1,,-$T23,0),0) -> 0 | AH23: =IF(AH$6=$N23,FV($V$3,$N23-1,,-$T23,0),0) -> 0 | AJ23: =IF(AJ$6=$N23,FV($V$3,$N23-1,,-$T23,0),0) -> 0 | AL23: =IF(AL$6=$N23,FV($V$3,$N23-1,,-$T23,0),0) -> 0 | AN23: =IF(AN$6=$N23,FV($V$3,$N23-1,,-$T23,0),0) -> 0 | AP23: =IF(AP$6=$N23,FV($V$3,$N23-1,,-$T23,0),0) -> 0 | AR23: =IF(AR$6=$N23,FV($V$3,$N23-1,,-$T23,0),0) -> 0 | AT23: =IF(AT$6=$N23,FV($V$3,$N23-1,,-$T23,0),0) -> 0 | AV23: =IF(AV$6=$N23,FV($V$3,$N23-1,,-$T23,0),0) -> 0 | AX23: =IF(AX$6=$N23,FV($V$3,$N23-1,,-$T23,0),0) -> 0 | AZ23: =IF(AZ$6=$N23,FV($V$3,$N23-1,,-$T23,0),0) -> 0
... B50: =+B49+1 -> 40 | D50: 1 | F50: =F49 -> x | H50: x | J50: 1 | K50: 23 | L50: =L49 -> 1 | N50: =P50-O50 -> -1999 | O50: =O49 -> 2023 | P50: =J50+K50 -> 24 | R50: =R49 -> 1 | T50: =D50*R50 -> 1 | V50: =SUM(X50:AZ50)+SUM(J100:AL100) -> 0 | X50: =IF(X$6=$N50,FV($V$3,$N50-1,,-$T50,0),0) -> 0 | Z50: =IF(Z$6=$N50,FV($V$3,$N50-1,,-$T50,0),0) -> 0 | AB50: =IF(AB$6=$N50,FV($V$3,$N50-1,,-$T50,0),0) -> 0 | AD50: =IF(AD$6=$N50,FV($V$3,$N50-1,,-$T50,0),0) -> 0 | AF50: =IF(AF$6=$N50,FV($V$3,$N50-1,,-$T50,0),0) -> 0 | AH50: =IF(AH$6=$N50,FV($V$3,$N50-1,,-$T50,0),0) -> 0 | AJ50: =IF(AJ$6=$N50,FV($V$3,$N50-1,,-$T50,0),0) -> 0 | AL50: =IF(AL$6=$N50,FV($V$3,$N50-1,,-$T50,0),0) -> 0 | AN50: =IF(AN$6=$N50,FV($V$3,$N50-1,,-$T50,0),0) -> 0 | AP50: =IF(AP$6=$N50,FV($V$3,$N50-1,,-$T50,0),0) -> 0 | AR50: =IF(AR$6=$N50,FV($V$3,$N50-1,,-$T50,0),0) -> 0 | AT50: =IF(AT$6=$N50,FV($V$3,$N50-1,,-$T50,0),0) -> 0 | AV50: =IF(AV$6=$N50,FV($V$3,$N50-1,,-$T50,0),0) -> 0 | AX50: =IF(AX$6=$N50,FV($V$3,$N50-1,,-$T50,0),0) -> 0 | AZ50: =IF(AZ$6=$N50,FV($V$3,$N50-1,,-$T50,0),0) -> 0
H52: Anticipated Expenditures, By Year | T52: =SUM(T11:T50) -> 40 | V52: =SUM(V11:V50) -> 0 | X52: =SUM(X11:X50) -> 0 | Z52: =SUM(Z11:Z50) -> 0 | AB52: =SUM(AB11:AB50) -> 0 | AD52: =SUM(AD11:AD50) -> 0 | AF52: =SUM(AF11:AF50) -> 0 | AH52: =SUM(AH11:AH50) -> 0 | AJ52: =SUM(AJ11:AJ50) -> 0 | AL52: =SUM(AL11:AL50) -> 0 | AN52: =SUM(AN11:AN50) -> 0 | AP52: =SUM(AP11:AP50) -> 0 | AR52: =SUM(AR11:AR50) -> 0 | AT52: =SUM(AT11:AT50) -> 0 | AV52: =SUM(AV11:AV50) -> 0 | AX52: =SUM(AX11:AX50) -> 0 | AZ52: =SUM(AZ11:AZ50) -> 0
B56: Line Item | J56: 16 | L56: 17 | N56: 18 | P56: 19 | R56: 20 | T56: =+R56+1 -> 21 | V56: =+T56+1 -> 22 | X56: =+V56+1 -> 23 | Z56: =+X56+1 -> 24 | AB56: =+Z56+1 -> 25 | AD56: =+AB56+1 -> 26 | AF56: =+AD56+1 -> 27 | AH56: =+AF56+1 -> 28 | AJ56: =+AH56+1 -> 29 | AL56: =+AJ56+1 -> 30
D57: Quantity | F57: Units | H57: Reserve Component Inventory | J57: =AZ7+1 -> 2039 | K57: =BA7+1 -> 1 | L57: =J57+1 -> 2040 | M57: =K57+1 -> 2 | N57: =L57+1 -> 2041 | O57: =M57+1 -> 3 | P57: =N57+1 -> 2042 | Q57: =O57+1 -> 4 | R57: =P57+1 -> 2043 | T57: =+R57+1 -> 2044 | U57: =S57+1 -> 1 | V57: =T57+1 -> 2045 | W57: =U57+1 -> 2 | X57: =V57+1 -> 2046 | Y57: =W57+1 -> 3 | Z57: =X57+1 -> 2047 | AA57: =Y57+1 -> 4 | AB57: =Z57+1 -> 2048 | AD57: =AB57+1 -> 2049 | AF57: =AD57+1 -> 2050 | AH57: =AF57+1 -> 2051 | AJ57: =AH57+1 -> 2052 | AL57: =AJ57+1 -> 2053
H59: =+H9 -> Roofs
B61: =+B11 -> 1 | D61: =+D11 -> 1 | F61: =+F11 -> x | H61: =+H11 -> x | J61: =IF(J$56=$N11,FV($V$3,$N11-1,,-$T11,0),0) -> 0 | L61: =IF(L$56=$N11,FV($V$3,$N11-1,,-$T11,0),0) -> 0 | N61: =IF(N$56=$N11,FV($V$3,$N11-1,,-$T11,0),0) -> 0 | P61: =IF(P$56=$N11,FV($V$3,$N11-1,,-$T11,0),0) -> 0 | R61: =IF(R$56=$N11,FV($V$3,$N11-1,,-$T11,0),0) -> 0 | T61: =IF(T$56=$N11,FV($V$3,$N11-1,,-$T11,0),0) -> 0 | V61: =IF(V$56=$N11,FV($V$3,$N11-1,,-$T11,0),0) -> 0 | X61: =IF(X$56=$N11,FV($V$3,$N11-1,,-$T11,0),0) -> 0 | Z61: =IF(Z$56=$N11,FV($V$3,$N11-1,,-$T11,0),0) -> 0 | AB61: =IF(AB$56=$N11,FV($V$3,$N11-1,,-$T11,0),0) -> 0 | AD61: =IF(AD$56=$N11,FV($V$3,$N11-1,,-$T11,0),0) -> 0 | AF61: =IF(AF$56=$N11,FV($V$3,$N11-1,,-$T11,0),0) -> 0 | AH61: =IF(AH$56=$N11,FV($V$3,$N11-1,,-$T11,0),0) -> 0 | AJ61: =IF(AJ$56=$N11,FV($V$3,$N11-1,,-$T11,0),0) -> 0 | AL61: =IF(AL$56=$N11,FV($V$3,$N11-1,,-$T11,0),0) -> 0
B62: =+B12 -> 2 | D62: =+D12 -> 1 | F62: =+F12 -> x | H62: =+H12 -> x | J62: =IF(J$56=$N12,FV($V$3,$N12-1,,-$T12,0),0) -> 0 | L62: =IF(L$56=$N12,FV($V$3,$N12-1,,-$T12,0),0) -> 0 | N62: =IF(N$56=$N12,FV($V$3,$N12-1,,-$T12,0),0) -> 0 | P62: =IF(P$56=$N12,FV($V$3,$N12-1,,-$T12,0),0) -> 0 | R62: =IF(R$56=$N12,FV($V$3,$N12-1,,-$T12,0),0) -> 0 | T62: =IF(T$56=$N12,FV($V$3,$N12-1,,-$T12,0),0) -> 0 | V62: =IF(V$56=$N12,FV($V$3,$N12-1,,-$T12,0),0) -> 0 | X62: =IF(X$56=$N12,FV($V$3,$N12-1,,-$T12,0),0) -> 0 | Z62: =IF(Z$56=$N12,FV($V$3,$N12-1,,-$T12,0),0) -> 0 | AB62: =IF(AB$56=$N12,FV($V$3,$N12-1,,-$T12,0),0) -> 0 | AD62: =IF(AD$56=$N12,FV($V$3,$N12-1,,-$T12,0),0) -> 0 | AF62: =IF(AF$56=$N12,FV($V$3,$N12-1,,-$T12,0),0) -> 0 | AH62: =IF(AH$56=$N12,FV($V$3,$N12-1,,-$T12,0),0) -> 0 | AJ62: =IF(AJ$56=$N12,FV($V$3,$N12-1,,-$T12,0),0) -> 0 | AL62: =IF(AL$56=$N12,FV($V$3,$N12-1,,-$T12,0),0) -> 0
B63: =+B13 -> 3 | D63: =+D13 -> 1 | F63: =+F13 -> x | H63: =+H13 -> x | J63: =IF(J$56=$N13,FV($V$3,$N13-1,,-$T13,0),0) -> 0 | L63: =IF(L$56=$N13,FV($V$3,$N13-1,,-$T13,0),0) -> 0 | N63: =IF(N$56=$N13,FV($V$3,$N13-1,,-$T13,0),0) -> 0 | P63: =IF(P$56=$N13,FV($V$3,$N13-1,,-$T13,0),0) -> 0 | R63: =IF(R$56=$N13,FV($V$3,$N13-1,,-$T13,0),0) -> 0 | T63: =IF(T$56=$N13,FV($V$3,$N13-1,,-$T13,0),0) -> 0 | V63: =IF(V$56=$N13,FV($V$3,$N13-1,,-$T13,0),0) -> 0 | X63: =IF(X$56=$N13,FV($V$3,$N13-1,,-$T13,0),0) -> 0 | Z63: =IF(Z$56=$N13,FV($V$3,$N13-1,,-$T13,0),0) -> 0 | AB63: =IF(AB$56=$N13,FV($V$3,$N13-1,,-$T13,0),0) -> 0 | AD63: =IF(AD$56=$N13,FV($V$3,$N13-1,,-$T13,0),0) -> 0 | AF63: =IF(AF$56=$N13,FV($V$3,$N13-1,,-$T13,0),0) -> 0 | AH63: =IF(AH$56=$N13,FV($V$3,$N13-1,,-$T13,0),0) -> 0 | AJ63: =IF(AJ$56=$N13,FV($V$3,$N13-1,,-$T13,0),0) -> 0 | AL63: =IF(AL$56=$N13,FV($V$3,$N13-1,,-$T13,0),0) -> 0
B64: =+B14 -> 4 | D64: =+D14 -> 1 | F64: =+F14 -> x | H64: =+H14 -> x | J64: =IF(J$56=$N14,FV($V$3,$N14-1,,-$T14,0),0) -> 0 | L64: =IF(L$56=$N14,FV($V$3,$N14-1,,-$T14,0),0) -> 0 | N64: =IF(N$56=$N14,FV($V$3,$N14-1,,-$T14,0),0) -> 0 | P64: =IF(P$56=$N14,FV($V$3,$N14-1,,-$T14,0),0) -> 0 | R64: =IF(R$56=$N14,FV($V$3,$N14-1,,-$T14,0),0) -> 0 | T64: =IF(T$56=$N14,FV($V$3,$N14-1,,-$T14,0),0) -> 0 | V64: =IF(V$56=$N14,FV($V$3,$N14-1,,-$T14,0),0) -> 0 | X64: =IF(X$56=$N14,FV($V$3,$N14-1,,-$T14,0),0) -> 0 | Z64: =IF(Z$56=$N14,FV($V$3,$N14-1,,-$T14,0),0) -> 0 | AB64: =IF(AB$56=$N14,FV($V$3,$N14-1,,-$T14,0),0) -> 0 | AD64: =IF(AD$56=$N14,FV($V$3,$N14-1,,-$T14,0),0) -> 0 | AF64: =IF(AF$56=$N14,FV($V$3,$N14-1,,-$T14,0),0) -> 0 | AH64: =IF(AH$56=$N14,FV($V$3,$N14-1,,-$T14,0),0) -> 0 | AJ64: =IF(AJ$56=$N14,FV($V$3,$N14-1,,-$T14,0),0) -> 0 | AL64: =IF(AL$56=$N14,FV($V$3,$N14-1,,-$T14,0),0) -> 0
B65: =+B15 -> 5 | D65: =+D15 -> 1 | F65: =+F15 -> x | H65: =+H15 -> x | J65: =IF(J$56=$N15,FV($V$3,$N15-1,,-$T15,0),0) -> 0 | L65: =IF(L$56=$N15,FV($V$3,$N15-1,,-$T15,0),0) -> 0 | N65: =IF(N$56=$N15,FV($V$3,$N15-1,,-$T15,0),0) -> 0 | P65: =IF(P$56=$N15,FV($V$3,$N15-1,,-$T15,0),0) -> 0 | R65: =IF(R$56=$N15,FV($V$3,$N15-1,,-$T15,0),0) -> 0 | T65: =IF(T$56=$N15,FV($V$3,$N15-1,,-$T15,0),0) -> 0 | V65: =IF(V$56=$N15,FV($V$3,$N15-1,,-$T15,0),0) -> 0 | X65: =IF(X$56=$N15,FV($V$3,$N15-1,,-$T15,0),0) -> 0 | Z65: =IF(Z$56=$N15,FV($V$3,$N15-1,,-$T15,0),0) -> 0 | AB65: =IF(AB$56=$N15,FV($V$3,$N15-1,,-$T15,0),0) -> 0 | AD65: =IF(AD$56=$N15,FV($V$3,$N15-1,,-$T15,0),0) -> 0 | AF65: =IF(AF$56=$N15,FV($V$3,$N15-1,,-$T15,0),0) -> 0 | AH65: =IF(AH$56=$N15,FV($V$3,$N15-1,,-$T15,0),0) -> 0 | AJ65: =IF(AJ$56=$N15,FV($V$3,$N15-1,,-$T15,0),0) -> 0 | AL65: =IF(AL$56=$N15,FV($V$3,$N15-1,,-$T15,0),0) -> 0
B66: =+B16 -> 6 | D66: =+D16 -> 1 | F66: =+F16 -> x | H66: =+H16 -> x | J66: =IF(J$56=$N16,FV($V$3,$N16-1,,-$T16,0),0) -> 0 | L66: =IF(L$56=$N16,FV($V$3,$N16-1,,-$T16,0),0) -> 0 | N66: =IF(N$56=$N16,FV($V$3,$N16-1,,-$T16,0),0) -> 0 | P66: =IF(P$56=$N16,FV($V$3,$N16-1,,-$T16,0),0) -> 0 | R66: =IF(R$56=$N16,FV($V$3,$N16-1,,-$T16,0),0) -> 0 | T66: =IF(T$56=$N16,FV($V$3,$N16-1,,-$T16,0),0) -> 0 | V66: =IF(V$56=$N16,FV($V$3,$N16-1,,-$T16,0),0) -> 0 | X66: =IF(X$56=$N16,FV($V$3,$N16-1,,-$T16,0),0) -> 0 | Z66: =IF(Z$56=$N16,FV($V$3,$N16-1,,-$T16,0),0) -> 0 | AB66: =IF(AB$56=$N16,FV($V$3,$N16-1,,-$T16,0),0) -> 0 | AD66: =IF(AD$56=$N16,FV($V$3,$N16-1,,-$T16,0),0) -> 0 | AF66: =IF(AF$56=$N16,FV($V$3,$N16-1,,-$T16,0),0) -> 0 | AH66: =IF(AH$56=$N16,FV($V$3,$N16-1,,-$T16,0),0) -> 0 | AJ66: =IF(AJ$56=$N16,FV($V$3,$N16-1,,-$T16,0),0) -> 0 | AL66: =IF(AL$56=$N16,FV($V$3,$N16-1,,-$T16,0),0) -> 0
B67: =+B17 -> 7 | D67: =+D17 -> 1 | F67: =+F17 -> x | H67: =+H17 -> x | J67: =IF(J$56=$N17,FV($V$3,$N17-1,,-$T17,0),0) -> 0 | L67: =IF(L$56=$N17,FV($V$3,$N17-1,,-$T17,0),0) -> 0 | N67: =IF(N$56=$N17,FV($V$3,$N17-1,,-$T17,0),0) -> 0 | P67: =IF(P$56=$N17,FV($V$3,$N17-1,,-$T17,0),0) -> 0 | R67: =IF(R$56=$N17,FV($V$3,$N17-1,,-$T17,0),0) -> 0 | T67: =IF(T$56=$N17,FV($V$3,$N17-1,,-$T17,0),0) -> 0 | V67: =IF(V$56=$N17,FV($V$3,$N17-1,,-$T17,0),0) -> 0 | X67: =IF(X$56=$N17,FV($V$3,$N17-1,,-$T17,0),0) -> 0 | Z67: =IF(Z$56=$N17,FV($V$3,$N17-1,,-$T17,0),0) -> 0 | AB67: =IF(AB$56=$N17,FV($V$3,$N17-1,,-$T17,0),0) -> 0 | AD67: =IF(AD$56=$N17,FV($V$3,$N17-1,,-$T17,0),0) -> 0 | AF67: =IF(AF$56=$N17,FV($V$3,$N17-1,,-$T17,0),0) -> 0 | AH67: =IF(AH$56=$N17,FV($V$3,$N17-1,,-$T17,0),0) -> 0 | AJ67: =IF(AJ$56=$N17,FV($V$3,$N17-1,,-$T17,0),0) -> 0 | AL67: =IF(AL$56=$N17,FV($V$3,$N17-1,,-$T17,0),0) -> 0
B68: =+B18 -> 8 | D68: =+D18 -> 1 | F68: =+F18 -> x | H68: =+H18 -> x | J68: =IF(J$56=$N18,FV($V$3,$N18-1,,-$T18,0),0) -> 0 | L68: =IF(L$56=$N18,FV($V$3,$N18-1,,-$T18,0),0) -> 0 | N68: =IF(N$56=$N18,FV($V$3,$N18-1,,-$T18,0),0) -> 0 | P68: =IF(P$56=$N18,FV($V$3,$N18-1,,-$T18,0),0) -> 0 | R68: =IF(R$56=$N18,FV($V$3,$N18-1,,-$T18,0),0) -> 0 | T68: =IF(T$56=$N18,FV($V$3,$N18-1,,-$T18,0),0) -> 0 | V68: =IF(V$56=$N18,FV($V$3,$N18-1,,-$T18,0),0) -> 0 | X68: =IF(X$56=$N18,FV($V$3,$N18-1,,-$T18,0),0) -> 0 | Z68: =IF(Z$56=$N18,FV($V$3,$N18-1,,-$T18,0),0) -> 0 | AB68: =IF(AB$56=$N18,FV($V$3,$N18-1,,-$T18,0),0) -> 0 | AD68: =IF(AD$56=$N18,FV($V$3,$N18-1,,-$T18,0),0) -> 0 | AF68: =IF(AF$56=$N18,FV($V$3,$N18-1,,-$T18,0),0) -> 0 | AH68: =IF(AH$56=$N18,FV($V$3,$N18-1,,-$T18,0),0) -> 0 | AJ68: =IF(AJ$56=$N18,FV($V$3,$N18-1,,-$T18,0),0) -> 0 | AL68: =IF(AL$56=$N18,FV($V$3,$N18-1,,-$T18,0),0) -> 0
B69: =+B19 -> 9 | D69: =+D19 -> 1 | F69: =+F19 -> x | H69: =+H19 -> x | J69: =IF(J$56=$N19,FV($V$3,$N19-1,,-$T19,0),0) -> 0 | L69: =IF(L$56=$N19,FV($V$3,$N19-1,,-$T19,0),0) -> 0 | N69: =IF(N$56=$N19,FV($V$3,$N19-1,,-$T19,0),0) -> 0 | P69: =IF(P$56=$N19,FV($V$3,$N19-1,,-$T19,0),0) -> 0 | R69: =IF(R$56=$N19,FV($V$3,$N19-1,,-$T19,0),0) -> 0 | T69: =IF(T$56=$N19,FV($V$3,$N19-1,,-$T19,0),0) -> 0 | V69: =IF(V$56=$N19,FV($V$3,$N19-1,,-$T19,0),0) -> 0 | X69: =IF(X$56=$N19,FV($V$3,$N19-1,,-$T19,0),0) -> 0 | Z69: =IF(Z$56=$N19,FV($V$3,$N19-1,,-$T19,0),0) -> 0 | AB69: =IF(AB$56=$N19,FV($V$3,$N19-1,,-$T19,0),0) -> 0 | AD69: =IF(AD$56=$N19,FV($V$3,$N19-1,,-$T19,0),0) -> 0 | AF69: =IF(AF$56=$N19,FV($V$3,$N19-1,,-$T19,0),0) -> 0 | AH69: =IF(AH$56=$N19,FV($V$3,$N19-1,,-$T19,0),0) -> 0 | AJ69: =IF(AJ$56=$N19,FV($V$3,$N19-1,,-$T19,0),0) -> 0 | AL69: =IF(AL$56=$N19,FV($V$3,$N19-1,,-$T19,0),0) -> 0
B70: =+B20 -> 10 | D70: =+D20 -> 1 | F70: =+F20 -> x | H70: =+H20 -> x | J70: =IF(J$56=$N20,FV($V$3,$N20-1,,-$T20,0),0) -> 0 | L70: =IF(L$56=$N20,FV($V$3,$N20-1,,-$T20,0),0) -> 0 | N70: =IF(N$56=$N20,FV($V$3,$N20-1,,-$T20,0),0) -> 0 | P70: =IF(P$56=$N20,FV($V$3,$N20-1,,-$T20,0),0) -> 0 | R70: =IF(R$56=$N20,FV($V$3,$N20-1,,-$T20,0),0) -> 0 | T70: =IF(T$56=$N20,FV($V$3,$N20-1,,-$T20,0),0) -> 0 | V70: =IF(V$56=$N20,FV($V$3,$N20-1,,-$T20,0),0) -> 0 | X70: =IF(X$56=$N20,FV($V$3,$N20-1,,-$T20,0),0) -> 0 | Z70: =IF(Z$56=$N20,FV($V$3,$N20-1,,-$T20,0),0) -> 0 | AB70: =IF(AB$56=$N20,FV($V$3,$N20-1,,-$T20,0),0) -> 0 | AD70: =IF(AD$56=$N20,FV($V$3,$N20-1,,-$T20,0),0) -> 0 | AF70: =IF(AF$56=$N20,FV($V$3,$N20-1,,-$T20,0),0) -> 0 | AH70: =IF(AH$56=$N20,FV($V$3,$N20-1,,-$T20,0),0) -> 0 | AJ70: =IF(AJ$56=$N20,FV($V$3,$N20-1,,-$T20,0),0) -> 0 | AL70: =IF(AL$56=$N20,FV($V$3,$N20-1,,-$T20,0),0) -> 0
B71: =+B21 -> 11 | D71: =+D21 -> 1 | F71: =+F21 -> x | H71: =+H21 -> x | J71: =IF(J$56=$N21,FV($V$3,$N21-1,,-$T21,0),0) -> 0 | L71: =IF(L$56=$N21,FV($V$3,$N21-1,,-$T21,0),0) -> 0 | N71: =IF(N$56=$N21,FV($V$3,$N21-1,,-$T21,0),0) -> 0 | P71: =IF(P$56=$N21,FV($V$3,$N21-1,,-$T21,0),0) -> 0 | R71: =IF(R$56=$N21,FV($V$3,$N21-1,,-$T21,0),0) -> 0 | T71: =IF(T$56=$N21,FV($V$3,$N21-1,,-$T21,0),0) -> 0 | V71: =IF(V$56=$N21,FV($V$3,$N21-1,,-$T21,0),0) -> 0 | X71: =IF(X$56=$N21,FV($V$3,$N21-1,,-$T21,0),0) -> 0 | Z71: =IF(Z$56=$N21,FV($V$3,$N21-1,,-$T21,0),0) -> 0 | AB71: =IF(AB$56=$N21,FV($V$3,$N21-1,,-$T21,0),0) -> 0 | AD71: =IF(AD$56=$N21,FV($V$3,$N21-1,,-$T21,0),0) -> 0 | AF71: =IF(AF$56=$N21,FV($V$3,$N21-1,,-$T21,0),0) -> 0 | AH71: =IF(AH$56=$N21,FV($V$3,$N21-1,,-$T21,0),0) -> 0 | AJ71: =IF(AJ$56=$N21,FV($V$3,$N21-1,,-$T21,0),0) -> 0 | AL71: =IF(AL$56=$N21,FV($V$3,$N21-1,,-$T21,0),0) -> 0
B72: =+B22 -> 12 | D72: =+D22 -> 1 | F72: =+F22 -> x | H72: =+H22 -> x | J72: =IF(J$56=$N22,FV($V$3,$N22-1,,-$T22,0),0) -> 0 | L72: =IF(L$56=$N22,FV($V$3,$N22-1,,-$T22,0),0) -> 0 | N72: =IF(N$56=$N22,FV($V$3,$N22-1,,-$T22,0),0) -> 0 | P72: =IF(P$56=$N22,FV($V$3,$N22-1,,-$T22,0),0) -> 0 | R72: =IF(R$56=$N22,FV($V$3,$N22-1,,-$T22,0),0) -> 0 | T72: =IF(T$56=$N22,FV($V$3,$N22-1,,-$T22,0),0) -> 0 | V72: =IF(V$56=$N22,FV($V$3,$N22-1,,-$T22,0),0) -> 0 | X72: =IF(X$56=$N22,FV($V$3,$N22-1,,-$T22,0),0) -> 0 | Z72: =IF(Z$56=$N22,FV($V$3,$N22-1,,-$T22,0),0) -> 0 | AB72: =IF(AB$56=$N22,FV($V$3,$N22-1,,-$T22,0),0) -> 0 | AD72: =IF(AD$56=$N22,FV($V$3,$N22-1,,-$T22,0),0) -> 0 | AF72: =IF(AF$56=$N22,FV($V$3,$N22-1,,-$T22,0),0) -> 0 | AH72: =IF(AH$56=$N22,FV($V$3,$N22-1,,-$T22,0),0) -> 0 | AJ72: =IF(AJ$56=$N22,FV($V$3,$N22-1,,-$T22,0),0) -> 0 | AL72: =IF(AL$56=$N22,FV($V$3,$N22-1,,-$T22,0),0) -> 0
... B100: =+B50 -> 40 | D100: =+D50 -> 1 | F100: =+F50 -> x | H100: =+H50 -> x | J100: =IF(J$56=$N50,FV($V$3,$N50-1,,-$T50,0),0) -> 0 | L100: =IF(L$56=$N50,FV($V$3,$N50-1,,-$T50,0),0) -> 0 | N100: =IF(N$56=$N50,FV($V$3,$N50-1,,-$T50,0),0) -> 0 | P100: =IF(P$56=$N50,FV($V$3,$N50-1,,-$T50,0),0) -> 0 | R100: =IF(R$56=$N50,FV($V$3,$N50-1,,-$T50,0),0) -> 0 | T100: =IF(T$56=$N50,FV($V$3,$N50-1,,-$T50,0),0) -> 0 | V100: =IF(V$56=$N50,FV($V$3,$N50-1,,-$T50,0),0) -> 0 | X100: =IF(X$56=$N50,FV($V$3,$N50-1,,-$T50,0),0) -> 0 | Z100: =IF(Z$56=$N50,FV($V$3,$N50-1,,-$T50,0),0) -> 0 | AB100: =IF(AB$56=$N50,FV($V$3,$N50-1,,-$T50,0),0) -> 0 | AD100: =IF(AD$56=$N50,FV($V$3,$N50-1,,-$T50,0),0) -> 0 | AF100: =IF(AF$56=$N50,FV($V$3,$N50-1,,-$T50,0),0) -> 0 | AH100: =IF(AH$56=$N50,FV($V$3,$N50-1,,-$T50,0),0) -> 0 | AJ100: =IF(AJ$56=$N50,FV($V$3,$N50-1,,-$T50,0),0) -> 0 | AL100: =IF(AL$56=$N50,FV($V$3,$N50-1,,-$T50,0),0) -> 0
H102: =+H52 -> Anticipated Expenditures, By Year | J102: =SUM(J61:J100) -> 0 | L102: =SUM(L61:L100) -> 0 | N102: =SUM(N61:N100) -> 0 | P102: =SUM(P61:P100) -> 0 | R102: =SUM(R61:R100) -> 0 | T102: =SUM(T61:T100) -> 0 | V102: =SUM(V61:V100) -> 0 | X102: =SUM(X61:X100) -> 0 | Z102: =SUM(Z61:Z100) -> 0 | AB102: =SUM(AB61:AB100) -> 0 | AD102: =SUM(AD61:AD100) -> 0 | AF102: =SUM(AF61:AF100) -> 0 | AH102: =SUM(AH61:AH100) -> 0 | AJ102: =SUM(AJ61:AJ100) -> 0 | AL102: =SUM(AL61:AL100) -> 0

Sheet Maintain (PRN) 1
G3: Exhibit B
G5: RESERVE EXPENDITURES | U5: Explanatory Notes:
G6: for | T6: 1) | U6: =+'Roofs 1'!V3 -> 0.03 | V6: is the estimated future Inflation Rate for estimating Future Replacement Costs.
G7: =+'Roofs 1'!H5 -> Association | T7: 2) | U7: Fiscal Year is beginning January 1 and ending December 31.
A9: Line Item | C9: Estimated | I9: Estimated Year Last Replaced | K9: Life Analysis, Years | O9: Estimated Year of 1st Replacement | Q9: =+'Roofs 1'!R6 -> 2024 Unit Cost | S9: =+'Roofs 1'!T6 -> 2024 Cost of Replacement | U9: Total Future Cost of Replacement | W9: 1 | Y9: 2 | AA9: 3 | AC9: 4 | AE9: 5 | AG9: 6 | AI9: 7 | AK9: 8 | AM9: 9 | AO9: 10 | AQ9: 11 | AS9: 12 | AU9: 13 | AW9: 14 | AY9: 15
C10: Quantity | E10: Units | G10: Reserve Component Inventory | K10: Useful | M10: Remaining | W10: =+'Roofs 1'!X7 -> 2024 | Y10: =W10+1 -> 2025 | Z10: =X10+1 -> 1 | AA10: =Y10+1 -> 2026 | AB10: =Z10+1 -> 2 | AC10: =AA10+1 -> 2027 | AD10: =AB10+1 -> 3 | AE10: =AC10+1 -> 2028 | AF10: =AD10+1 -> 4 | ... AY10: =AW10+1 -> 2038
G12: ELEMENTS
A14: ='Roofs 1'!B50+1 -> 41 | C14: 1 | E14: x | G14: x | I14: x | K14: x | M14: 1 | N14: ='Roofs 1'!P4 -> 2023 | O14: 1 | Q14: 1 | S14: =C14*Q14 -> 1 | U14: =SUM(W14:AY14)+SUM(I47:AK47) -> 47.575416 | W14: =S14 -> 1 | Y14: =FV($U$6,W$9,,-$S14,0) -> 1.03 | AA14: =FV($U$6,Y$9,,-$S14,0) -> 1.0609 | AC14: =FV($U$6,AA$9,,-$S14,0) -> 1.092727 | AE14: =FV($U$6,AC$9,,-$S14,0) -> 1.1255088 | AG14: =FV($U$6,AE$9,,-$S14,0) -> 1.1592741 | AI14: =FV($U$6,AG$9,,-$S14,0) -> 1.1940523 | AK14: =FV($U$6,AI$9,,-$S14,0) -> 1.2298739 | AM14: =FV($U$6,AK$9,,-$S14,0) -> 1.2667701 | AO14: =FV($U$6,AM$9,,-$S14,0) -> 1.3047732 | AQ14: =FV($U$6,AO$9,,-$S14,0) -> 1.3439164 | AS14: =FV($U$6,AQ$9,,-$S14,0) -> 1.3842339 | AU14: =FV($U$6,AS$9,,-$S14,0) -> 1.4257609 | AW14: =FV($U$6,AU$9,,-$S14,0) -> 1.4685337 | AY14: =FV($U$6,AW$9,,-$S14,0) -> 1.5125897
A15: =+A14+1 -> 42 | C15: 1 | E15: x | G15: x | I15: x | K15: x | M15: 1 | N15: =N14 -> 2023 | O15: 1 | Q15: 1 | S15: =C15*Q15 -> 1 | U15: =SUM(W15:AY15)+SUM(I48:AK48) -> 47.575416 | W15: =S15 -> 1 | Y15: =FV($U$6,W$9,,-$S15,0) -> 1.03 | AA15: =FV($U$6,Y$9,,-$S15,0) -> 1.0609 | AC15: =FV($U$6,AA$9,,-$S15,0) -> 1.092727 | AE15: =FV($U$6,AC$9,,-$S15,0) -> 1.1255088 | AG15: =FV($U$6,AE$9,,-$S15,0) -> 1.1592741 | AI15: =FV($U$6,AG$9,,-$S15,0) -> 1.1940523 | AK15: =FV($U$6,AI$9,,-$S15,0) -> 1.2298739 | AM15: =FV($U$6,AK$9,,-$S15,0) -> 1.2667701 | AO15: =FV($U$6,AM$9,,-$S15,0) -> 1.3047732 | AQ15: =FV($U$6,AO$9,,-$S15,0) -> 1.3439164 | AS15: =FV($U$6,AQ$9,,-$S15,0) -> 1.3842339 | AU15: =FV($U$6,AS$9,,-$S15,0) -> 1.4257609 | AW15: =FV($U$6,AU$9,,-$S15,0) -> 1.4685337 | AY15: =FV($U$6,AW$9,,-$S15,0) -> 1.5125897
A16: =+A15+1 -> 43 | C16: 1 | E16: x | G16: x | I16: x | K16: x | M16: 1 | N16: =N15 -> 2023 | O16: 1 | Q16: 1 | S16: =C16*Q16 -> 1 | U16: =SUM(W16:AY16)+SUM(I49:AK49) -> 47.575416 | W16: =S16 -> 1 | Y16: =FV($U$6,W$9,,-$S16,0) -> 1.03 | AA16: =FV($U$6,Y$9,,-$S16,0) -> 1.0609 | AC16: =FV($U$6,AA$9,,-$S16,0) -> 1.092727 | AE16: =FV($U$6,AC$9,,-$S16,0) -> 1.1255088 | AG16: =FV($U$6,AE$9,,-$S16,0) -> 1.1592741 | AI16: =FV($U$6,AG$9,,-$S16,0) -> 1.1940523 | AK16: =FV($U$6,AI$9,,-$S16,0) -> 1.2298739 | AM16: =FV($U$6,AK$9,,-$S16,0) -> 1.2667701 | AO16: =FV($U$6,AM$9,,-$S16,0) -> 1.3047732 | AQ16: =FV($U$6,AO$9,,-$S16,0) -> 1.3439164 | AS16: =FV($U$6,AQ$9,,-$S16,0) -> 1.3842339 | AU16: =FV($U$6,AS$9,,-$S16,0) -> 1.4257609 | AW16: =FV($U$6,AU$9,,-$S16,0) -> 1.4685337 | AY16: =FV($U$6,AW$9,,-$S16,0) -> 1.5125897
A17: =+A16+1 -> 44 | C17: 1 | E17: x | G17: x | I17: x | K17: x | M17: 1 | N17: =N16 -> 2023 | O17: 1 | Q17: 1 | S17: =C17*Q17 -> 1 | U17: =SUM(W17:AY17)+SUM(I50:AK50) -> 47.575416 | W17: =S17 -> 1 | Y17: =FV($U$6,W$9,,-$S17,0) -> 1.03 | AA17: =FV($U$6,Y$9,,-$S17,0) -> 1.0609 | AC17: =FV($U$6,AA$9,,-$S17,0) -> 1.092727 | AE17: =FV($U$6,AC$9,,-$S17,0) -> 1.1255088 | AG17: =FV($U$6,AE$9,,-$S17,0) -> 1.1592741 | AI17: =FV($U$6,AG$9,,-$S17,0) -> 1.1940523 | AK17: =FV($U$6,AI$9,,-$S17,0) -> 1.2298739 | AM17: =FV($U$6,AK$9,,-$S17,0) -> 1.2667701 | AO17: =FV($U$6,AM$9,,-$S17,0) -> 1.3047732 | AQ17: =FV($U$6,AO$9,,-$S17,0) -> 1.3439164 | AS17: =FV($U$6,AQ$9,,-$S17,0) -> 1.3842339 | AU17: =FV($U$6,AS$9,,-$S17,0) -> 1.4257609 | AW17: =FV($U$6,AU$9,,-$S17,0) -> 1.4685337 | AY17: =FV($U$6,AW$9,,-$S17,0) -> 1.5125897
A18: =+A17+1 -> 45 | C18: 1 | E18: x | G18: x | I18: x | K18: x | M18: 1 | N18: =N17 -> 2023 | O18: 1 | Q18: 1 | S18: =C18*Q18 -> 1 | U18: =SUM(W18:AY18)+SUM(I51:AK51) -> 47.575416 | W18: =S18 -> 1 | Y18: =FV($U$6,W$9,,-$S18,0) -> 1.03 | AA18: =FV($U$6,Y$9,,-$S18,0) -> 1.0609 | AC18: =FV($U$6,AA$9,,-$S18,0) -> 1.092727 | AE18: =FV($U$6,AC$9,,-$S18,0) -> 1.1255088 | AG18: =FV($U$6,AE$9,,-$S18,0) -> 1.1592741 | AI18: =FV($U$6,AG$9,,-$S18,0) -> 1.1940523 | AK18: =FV($U$6,AI$9,,-$S18,0) -> 1.2298739 | AM18: =FV($U$6,AK$9,,-$S18,0) -> 1.2667701 | AO18: =FV($U$6,AM$9,,-$S18,0) -> 1.3047732 | AQ18: =FV($U$6,AO$9,,-$S18,0) -> 1.3439164 | AS18: =FV($U$6,AQ$9,,-$S18,0) -> 1.3842339 | AU18: =FV($U$6,AS$9,,-$S18,0) -> 1.4257609 | AW18: =FV($U$6,AU$9,,-$S18,0) -> 1.4685337 | AY18: =FV($U$6,AW$9,,-$S18,0) -> 1.5125897
A19: =+A18+1 -> 46 | C19: 1 | E19: x | G19: x | I19: x | K19: x | M19: 1 | N19: =N18 -> 2023 | O19: 1 | Q19: 1 | S19: =C19*Q19 -> 1 | U19: =SUM(W19:AY19)+SUM(I52:AK52) -> 47.575416 | W19: =S19 -> 1 | Y19: =FV($U$6,W$9,,-$S19,0) -> 1.03 | AA19: =FV($U$6,Y$9,,-$S19,0) -> 1.0609 | AC19: =FV($U$6,AA$9,,-$S19,0) -> 1.092727 | AE19: =FV($U$6,AC$9,,-$S19,0) -> 1.1255088 | AG19: =FV($U$6,AE$9,,-$S19,0) -> 1.1592741 | AI19: =FV($U$6,AG$9,,-$S19,0) -> 1.1940523 | AK19: =FV($U$6,AI$9,,-$S19,0) -> 1.2298739 | AM19: =FV($U$6,AK$9,,-$S19,0) -> 1.2667701 | AO19: =FV($U$6,AM$9,,-$S19,0) -> 1.3047732 | AQ19: =FV($U$6,AO$9,,-$S19,0) -> 1.3439164 | AS19: =FV($U$6,AQ$9,,-$S19,0) -> 1.3842339 | AU19: =FV($U$6,AS$9,,-$S19,0) -> 1.4257609 | AW19: =FV($U$6,AU$9,,-$S19,0) -> 1.4685337 | AY19: =FV($U$6,AW$9,,-$S19,0) -> 1.5125897
A20: =+A19+1 -> 47 | C20: 1 | E20: x | G20: x | I20: x | K20: x | M20: 1 | N20: =N19 -> 2023 | O20: 1 | Q20: 1 | S20: =C20*Q20 -> 1 | U20: =SUM(W20:AY20)+SUM(I53:AK53) -> 47.575416 | W20: =S20 -> 1 | Y20: =FV($U$6,W$9,,-$S20,0) -> 1.03 | AA20: =FV($U$6,Y$9,,-$S20,0) -> 1.0609 | AC20: =FV($U$6,AA$9,,-$S20,0) -> 1.092727 | AE20: =FV($U$6,AC$9,,-$S20,0) -> 1.1255088 | AG20: =FV($U$6,AE$9,,-$S20,0) -> 1.1592741 | AI20: =FV($U$6,AG$9,,-$S20,0) -> 1.1940523 | AK20: =FV($U$6,AI$9,,-$S20,0) -> 1.2298739 | AM20: =FV($U$6,AK$9,,-$S20,0) -> 1.2667701 | AO20: =FV($U$6,AM$9,,-$S20,0) -> 1.3047732 | AQ20: =FV($U$6,AO$9,,-$S20,0) -> 1.3439164 | AS20: =FV($U$6,AQ$9,,-$S20,0) -> 1.3842339 | AU20: =FV($U$6,AS$9,,-$S20,0) -> 1.4257609 | AW20: =FV($U$6,AU$9,,-$S20,0) -> 1.4685337 | AY20: =FV($U$6,AW$9,,-$S20,0) -> 1.5125897
A21: =+A20+1 -> 48 | C21: 1 | E21: x | G21: x | I21: x | K21: x | M21: 1 | N21: =N20 -> 2023 | O21: 1 | Q21: 1 | S21: =C21*Q21 -> 1 | U21: =SUM(W21:AY21)+SUM(I54:AK54) -> 47.575416 | W21: =S21 -> 1 | Y21: =FV($U$6,W$9,,-$S21,0) -> 1.03 | AA21: =FV($U$6,Y$9,,-$S21,0) -> 1.0609 | AC21: =FV($U$6,AA$9,,-$S21,0) -> 1.092727 | AE21: =FV($U$6,AC$9,,-$S21,0) -> 1.1255088 | AG21: =FV($U$6,AE$9,,-$S21,0) -> 1.1592741 | AI21: =FV($U$6,AG$9,,-$S21,0) -> 1.1940523 | AK21: =FV($U$6,AI$9,,-$S21,0) -> 1.2298739 | AM21: =FV($U$6,AK$9,,-$S21,0) -> 1.2667701 | AO21: =FV($U$6,AM$9,,-$S21,0) -> 1.3047732 | AQ21: =FV($U$6,AO$9,,-$S21,0) -> 1.3439164 | AS21: =FV($U$6,AQ$9,,-$S21,0) -> 1.3842339 | AU21: =FV($U$6,AS$9,,-$S21,0) -> 1.4257609 | AW21: =FV($U$6,AU$9,,-$S21,0) -> 1.4685337 | AY21: =FV($U$6,AW$9,,-$S21,0) -> 1.5125897
A22: =+A21+1 -> 49 | C22: 1 | E22: x | G22: x | I22: x | K22: x | M22: 1 | N22: =N21 -> 2023 | O22: 1 | Q22: 1 | S22: =C22*Q22 -> 1 | U22: =SUM(W22:AY22)+SUM(I55:AK55) -> 47.575416 | W22: =S22 -> 1 | Y22: =FV($U$6,W$9,,-$S22,0) -> 1.03 | AA22: =FV($U$6,Y$9,,-$S22,0) -> 1.0609 | AC22: =FV($U$6,AA$9,,-$S22,0) -> 1.092727 | AE22: =FV($U$6,AC$9,,-$S22,0) -> 1.1255088 | AG22: =FV($U$6,AE$9,,-$S22,0) -> 1.1592741 | AI22: =FV($U$6,AG$9,,-$S22,0) -> 1.1940523 | AK22: =FV($U$6,AI$9,,-$S22,0) -> 1.2298739 | AM22: =FV($U$6,AK$9,,-$S22,0) -> 1.2667701 | AO22: =FV($U$6,AM$9,,-$S22,0) -> 1.3047732 | AQ22: =FV($U$6,AO$9,,-$S22,0) -> 1.3439164 | AS22: =FV($U$6,AQ$9,,-$S22,0) -> 1.3842339 | AU22: =FV($U$6,AS$9,,-$S22,0) -> 1.4257609 | AW22: =FV($U$6,AU$9,,-$S22,0) -> 1.4685337 | AY22: =FV($U$6,AW$9,,-$S22,0) -> 1.5125897
A23: =+A22+1 -> 50 | C23: 1 | E23: x | G23: x | I23: x | K23: x | M23: 1 | N23: =N22 -> 2023 | O23: 1 | Q23: 1 | S23: =C23*Q23 -> 1 | U23: =SUM(W23:AY23)+SUM(I56:AK56) -> 47.575416 | W23: =S23 -> 1 | Y23: =FV($U$6,W$9,,-$S23,0) -> 1.03 | AA23: =FV($U$6,Y$9,,-$S23,0) -> 1.0609 | AC23: =FV($U$6,AA$9,,-$S23,0) -> 1.092727 | AE23: =FV($U$6,AC$9,,-$S23,0) -> 1.1255088 | AG23: =FV($U$6,AE$9,,-$S23,0) -> 1.1592741 | AI23: =FV($U$6,AG$9,,-$S23,0) -> 1.1940523 | AK23: =FV($U$6,AI$9,,-$S23,0) -> 1.2298739 | AM23: =FV($U$6,AK$9,,-$S23,0) -> 1.2667701 | AO23: =FV($U$6,AM$9,,-$S23,0) -> 1.3047732 | AQ23: =FV($U$6,AO$9,,-$S23,0) -> 1.3439164 | AS23: =FV($U$6,AQ$9,,-$S23,0) -> 1.3842339 | AU23: =FV($U$6,AS$9,,-$S23,0) -> 1.4257609 | AW23: =FV($U$6,AU$9,,-$S23,0) -> 1.4685337 | AY23: =FV($U$6,AW$9,,-$S23,0) -> 1.5125897
A24: =+A23+1 -> 51 | C24: 1 | E24: x | G24: x | I24: x | K24: x | M24: 1 | N24: =N23 -> 2023 | O24: 1 | Q24: 1 | S24: =C24*Q24 -> 1 | U24: =SUM(W24:AY24)+SUM(I57:AK57) -> 47.575416 | W24: =S24 -> 1 | Y24: =FV($U$6,W$9,,-$S24,0) -> 1.03 | AA24: =FV($U$6,Y$9,,-$S24,0) -> 1.0609 | AC24: =FV($U$6,AA$9,,-$S24,0) -> 1.092727 | AE24: =FV($U$6,AC$9,,-$S24,0) -> 1.1255088 | AG24: =FV($U$6,AE$9,,-$S24,0) -> 1.1592741 | AI24: =FV($U$6,AG$9,,-$S24,0) -> 1.1940523 | AK24: =FV($U$6,AI$9,,-$S24,0) -> 1.2298739 | AM24: =FV($U$6,AK$9,,-$S24,0) -> 1.2667701 | AO24: =FV($U$6,AM$9,,-$S24,0) -> 1.3047732 | AQ24: =FV($U$6,AO$9,,-$S24,0) -> 1.3439164 | AS24: =FV($U$6,AQ$9,,-$S24,0) -> 1.3842339 | AU24: =FV($U$6,AS$9,,-$S24,0) -> 1.4257609 | AW24: =FV($U$6,AU$9,,-$S24,0) -> 1.4685337 | AY24: =FV($U$6,AW$9,,-$S24,0) -> 1.5125897
A25: =+A24+1 -> 52 | C25: 1 | E25: x | G25: x | I25: x | K25: x | M25: 1 | N25: =N24 -> 2023 | O25: 1 | Q25: 1 | S25: =C25*Q25 -> 1 | U25: =SUM(W25:AY25)+SUM(I58:AK58) -> 47.575416 | W25: =S25 -> 1 | Y25: =FV($U$6,W$9,,-$S25,0) -> 1.03 | AA25: =FV($U$6,Y$9,,-$S25,0) -> 1.0609 | AC25: =FV($U$6,AA$9,,-$S25,0) -> 1.092727 | AE25: =FV($U$6,AC$9,,-$S25,0) -> 1.1255088 | AG25: =FV($U$6,AE$9,,-$S25,0) -> 1.1592741 | AI25: =FV($U$6,AG$9,,-$S25,0) -> 1.1940523 | AK25: =FV($U$6,AI$9,,-$S25,0) -> 1.2298739 | AM25: =FV($U$6,AK$9,,-$S25,0) -> 1.2667701 | AO25: =FV($U$6,AM$9,,-$S25,0) -> 1.3047732 | AQ25: =FV($U$6,AO$9,,-$S25,0) -> 1.3439164 | AS25: =FV($U$6,AQ$9,,-$S25,0) -> 1.3842339 | AU25: =FV($U$6,AS$9,,-$S25,0) -> 1.4257609 | AW25: =FV($U$6,AU$9,,-$S25,0) -> 1.4685337 | AY25: =FV($U$6,AW$9,,-$S25,0) -> 1.5125897
A26: =+A25+1 -> 53 | C26: 1 | E26: x | G26: x | I26: x | K26: x | M26: 1 | N26: =N25 -> 2023 | O26: 1 | Q26: 1 | S26: =C26*Q26 -> 1 | U26: =SUM(W26:AY26)+SUM(I59:AK59) -> 47.575416 | W26: =S26 -> 1 | Y26: =FV($U$6,W$9,,-$S26,0) -> 1.03 | AA26: =FV($U$6,Y$9,,-$S26,0) -> 1.0609 | AC26: =FV($U$6,AA$9,,-$S26,0) -> 1.092727 | AE26: =FV($U$6,AC$9,,-$S26,0) -> 1.1255088 | AG26: =FV($U$6,AE$9,,-$S26,0) -> 1.1592741 | AI26: =FV($U$6,AG$9,,-$S26,0) -> 1.1940523 | AK26: =FV($U$6,AI$9,,-$S26,0) -> 1.2298739 | AM26: =FV($U$6,AK$9,,-$S26,0) -> 1.2667701 | AO26: =FV($U$6,AM$9,,-$S26,0) -> 1.3047732 | AQ26: =FV($U$6,AO$9,,-$S26,0) -> 1.3439164 | AS26: =FV($U$6,AQ$9,,-$S26,0) -> 1.3842339 | AU26: =FV($U$6,AS$9,,-$S26,0) -> 1.4257609 | AW26: =FV($U$6,AU$9,,-$S26,0) -> 1.4685337 | AY26: =FV($U$6,AW$9,,-$S26,0) -> 1.5125897
... A35: =+A34+1 -> 62 | C35: 1 | E35: x | G35: x | I35: x | K35: x | M35: 1 | N35: =N34 -> 2023 | O35: 1 | Q35: 1 | S35: =C35*Q35 -> 1 | U35: =SUM(W35:AY35)+SUM(I68:AK68) -> 47.575416 | W35: =S35 -> 1 | Y35: =FV($U$6,W$9,,-$S35,0) -> 1.03 | AA35: =FV($U$6,Y$9,,-$S35,0) -> 1.0609 | AC35: =FV($U$6,AA$9,,-$S35,0) -> 1.092727 | AE35: =FV($U$6,AC$9,,-$S35,0) -> 1.1255088 | AG35: =FV($U$6,AE$9,,-$S35,0) -> 1.1592741 | AI35: =FV($U$6,AG$9,,-$S35,0) -> 1.1940523 | AK35: =FV($U$6,AI$9,,-$S35,0) -> 1.2298739 | AM35: =FV($U$6,AK$9,,-$S35,0) -> 1.2667701 | AO35: =FV($U$6,AM$9,,-$S35,0) -> 1.3047732 | AQ35: =FV($U$6,AO$9,,-$S35,0) -> 1.3439164 | AS35: =FV($U$6,AQ$9,,-$S35,0) -> 1.3842339 | AU35: =FV($U$6,AS$9,,-$S35,0) -> 1.4257609 | AW35: =FV($U$6,AU$9,,-$S35,0) -> 1.4685337 | AY35: =FV($U$6,AW$9,,-$S35,0) -> 1.5125897
G38: Anticipated Expenditures, By Year | S38: =SUM(S14:S35) -> 22 | U38: =SUM(U14:U35) -> 1046.6591 | W38: =SUM(W14:W36) -> 22 | Y38: =SUM(Y14:Y36) -> 22.66 | AA38: =SUM(AA14:AA36) -> 23.3398 | AC38: =SUM(AC14:AC36) -> 24.039994 | AE38: =SUM(AE14:AE36) -> 24.761194 | AG38: =SUM(AG14:AG36) -> 25.50403 | AI38: =SUM(AI14:AI36) -> 26.269151 | AK38: =SUM(AK14:AK36) -> 27.057225 | AM38: =SUM(AM14:AM36) -> 27.868942 | AO38: =SUM(AO14:AO36) -> 28.70501 | AQ38: =SUM(AQ14:AQ36) -> 29.56616 | AS38: =SUM(AS14:AS36) -> 30.453145 | AU38: =SUM(AU14:AU36) -> 31.36674 | AW38: =SUM(AW14:AW36) -> 32.307742 | AY38: =SUM(AY14:AY36) -> 33.276974
A42: Line Item | I42: 16 | K42: 17 | M42: 18 | O42: 19 | Q42: 20 | S42: =+Q42+1 -> 21 | U42: =+S42+1 -> 22 | W42: =+U42+1 -> 23 | Y42: =+W42+1 -> 24 | AA42: =+Y42+1 -> 25 | AC42: =+AA42+1 -> 26 | AE42: =+AC42+1 -> 27 | AG42: =+AE42+1 -> 28 | AI42: =+AG42+1 -> 29 | AK42: =+AI42+1 -> 30
C43: Quantity | E43: Units | G43: Reserve Component Inventory | I43: =AY10+1 -> 2039 | J43: =AZ10+1 -> 1 | K43: =I43+1 -> 2040 | L43: =J43+1 -> 2 | M43: =K43+1 -> 2041 | N43: =L43+1 -> 3 | O43: =M43+1 -> 2042 | P43: =N43+1 -> 4 | Q43: =O43+1 -> 2043 | S43: =+Q43+1 -> 2044 | T43: =R43+1 -> 1 | U43: =S43+1 -> 2045 | V43: =T43+1 -> 2 | W43: =U43+1 -> 2046 | X43: =V43+1 -> 3 | Y43: =W43+1 -> 2047 | Z43: =X43+1 -> 4 | AA43: =Y43+1 -> 2048 | AC43: =AA43+1 -> 2049 | AE43: =AC43+1 -> 2050 | AG43: =AE43+1 -> 2051 | AI43: =AG43+1 -> 2052 | AK43: =AI43+1 -> 2053
G45: =+G12 -> ELEMENTS
A47: =+A14 -> 41 | C47: =+C14 -> 1 | E47: =+E14 -> x | G47: =+G14 -> x | I47: =FV($U$6,AY$9,,-$S14,0) -> 1.5579674 | K47: =FV($U$6,I$42,,-$S14,0) -> 1.6047064 | M47: =FV($U$6,K$42,,-$S14,0) -> 1.6528476 | O47: =FV($U$6,M$42,,-$S14,0) -> 1.7024331 | Q47: =FV($U$6,O$42,,-$S14,0) -> 1.7535061 | S47: =FV($U$6,Q$42,,-$S14,0) -> 1.8061112 | U47: =FV($U$6,S$42,,-$S14,0) -> 1.8602946 | W47: =FV($U$6,U$42,,-$S14,0) -> 1.9161034 | Y47: =FV($U$6,W$42,,-$S14,0) -> 1.9735865 | AA47: =FV($U$6,Y$42,,-$S14,0) -> 2.0327941 | AC47: =FV($U$6,AA$42,,-$S14,0) -> 2.0937779 | AE47: =FV($U$6,AC$42,,-$S14,0) -> 2.1565913 | AG47: =FV($U$6,AE$42,,-$S14,0) -> 2.221289 | AI47: =FV($U$6,AG$42,,-$S14,0) -> 2.2879277 | AK47: =FV($U$6,AI$42,,-$S14,0) -> 2.3565655
A48: =+A15 -> 42 | C48: =+C15 -> 1 | E48: =+E15 -> x | G48: =+G15 -> x | I48: =FV($U$6,AY$9,,-$S15,0) -> 1.5579674 | K48: =FV($U$6,I$42,,-$S15,0) -> 1.6047064 | M48: =FV($U$6,K$42,,-$S15,0) -> 1.6528476 | O48: =FV($U$6,M$42,,-$S15,0) -> 1.7024331 | Q48: =FV($U$6,O$42,,-$S15,0) -> 1.7535061 | S48: =FV($U$6,Q$42,,-$S15,0) -> 1.8061112 | U48: =FV($U$6,S$42,,-$S15,0) -> 1.8602946 | W48: =FV($U$6,U$42,,-$S15,0) -> 1.9161034 | Y48: =FV($U$6,W$42,,-$S15,0) -> 1.9735865 | AA48: =FV($U$6,Y$42,,-$S15,0) -> 2.0327941 | AC48: =FV($U$6,AA$42,,-$S15,0) -> 2.0937779 | AE48: =FV($U$6,AC$42,,-$S15,0) -> 2.1565913 | AG48: =FV($U$6,AE$42,,-$S15,0) -> 2.221289 | AI48: =FV($U$6,AG$42,,-$S15,0) -> 2.2879277 | AK48: =FV($U$6,AI$42,,-$S15,0) -> 2.3565655
A49: =+A16 -> 43 | C49: =+C16 -> 1 | E49: =+E16 -> x | G49: =+G16 -> x | I49: =FV($U$6,AY$9,,-$S16,0) -> 1.5579674 | K49: =FV($U$6,I$42,,-$S16,0) -> 1.6047064 | M49: =FV($U$6,K$42,,-$S16,0) -> 1.6528476 | O49: =FV($U$6,M$42,,-$S16,0) -> 1.7024331 | Q49: =FV($U$6,O$42,,-$S16,0) -> 1.7535061 | S49: =FV($U$6,Q$42,,-$S16,0) -> 1.8061112 | U49: =FV($U$6,S$42,,-$S16,0) -> 1.8602946 | W49: =FV($U$6,U$42,,-$S16,0) -> 1.9161034 | Y49: =FV($U$6,W$42,,-$S16,0) -> 1.9735865 | AA49: =FV($U$6,Y$42,,-$S16,0) -> 2.0327941 | AC49: =FV($U$6,AA$42,,-$S16,0) -> 2.0937779 | AE49: =FV($U$6,AC$42,,-$S16,0) -> 2.1565913 | AG49: =FV($U$6,AE$42,,-$S16,0) -> 2.221289 | AI49: =FV($U$6,AG$42,,-$S16,0) -> 2.2879277 | AK49: =FV($U$6,AI$42,,-$S16,0) -> 2.3565655
A50: =+A17 -> 44 | C50: =+C17 -> 1 | E50: =+E17 -> x | G50: =+G17 -> x | I50: =FV($U$6,AY$9,,-$S17,0) -> 1.5579674 | K50: =FV($U$6,I$42,,-$S17,0) -> 1.6047064 | M50: =FV($U$6,K$42,,-$S17,0) -> 1.6528476 | O50: =FV($U$6,M$42,,-$S17,0) -> 1.7024331 | Q50: =FV($U$6,O$42,,-$S17,0) -> 1.7535061 | S50: =FV($U$6,Q$42,,-$S17,0) -> 1.8061112 | U50: =FV($U$6,S$42,,-$S17,0) -> 1.8602946 | W50: =FV($U$6,U$42,,-$S17,0) -> 1.9161034 | Y50: =FV($U$6,W$42,,-$S17,0) -> 1.9735865 | AA50: =FV($U$6,Y$42,,-$S17,0) -> 2.0327941 | AC50: =FV($U$6,AA$42,,-$S17,0) -> 2.0937779 | AE50: =FV($U$6,AC$42,,-$S17,0) -> 2.1565913 | AG50: =FV($U$6,AE$42,,-$S17,0) -> 2.221289 | AI50: =FV($U$6,AG$42,,-$S17,0) -> 2.2879277 | AK50: =FV($U$6,AI$42,,-$S17,0) -> 2.3565655
A51: =+A18 -> 45 | C51: =+C18 -> 1 | E51: =+E18 -> x | G51: =+G18 -> x | I51: =FV($U$6,AY$9,,-$S18,0) -> 1.5579674 | K51: =FV($U$6,I$42,,-$S18,0) -> 1.6047064 | M51: =FV($U$6,K$42,,-$S18,0) -> 1.6528476 | O51: =FV($U$6,M$42,,-$S18,0) -> 1.7024331 | Q51: =FV($U$6,O$42,,-$S18,0) -> 1.7535061 | S51: =FV($U$6,Q$42,,-$S18,0) -> 1.8061112 | U51: =FV($U$6,S$42,,-$S18,0) -> 1.8602946 | W51: =FV($U$6,U$42,,-$S18,0) -> 1.9161034 | Y51: =FV($U$6,W$42,,-$S18,0) -> 1.9735865 | AA51: =FV($U$6,Y$42,,-$S18,0) -> 2.0327941 | AC51: =FV($U$6,AA$42,,-$S18,0) -> 2.0937779 | AE51: =FV($U$6,AC$42,,-$S18,0) -> 2.1565913 | AG51: =FV($U$6,AE$42,,-$S18,0) -> 2.221289 | AI51: =FV($U$6,AG$42,,-$S18,0) -> 2.2879277 | AK51: =FV($U$6,AI$42,,-$S18,0) -> 2.3565655
A52: =+A19 -> 46 | C52: =+C19 -> 1 | E52: =+E19 -> x | G52: =+G19 -> x | I52: =FV($U$6,AY$9,,-$S19,0) -> 1.5579674 | K52: =FV($U$6,I$42,,-$S19,0) -> 1.6047064 | M52: =FV($U$6,K$42,,-$S19,0) -> 1.6528476 | O52: =FV($U$6,M$42,,-$S19,0) -> 1.7024331 | Q52: =FV($U$6,O$42,,-$S19,0) -> 1.7535061 | S52: =FV($U$6,Q$42,,-$S19,0) -> 1.8061112 | U52: =FV($U$6,S$42,,-$S19,0) -> 1.8602946 | W52: =FV($U$6,U$42,,-$S19,0) -> 1.9161034 | Y52: =FV($U$6,W$42,,-$S19,0) -> 1.9735865 | AA52: =FV($U$6,Y$42,,-$S19,0) -> 2.0327941 | AC52: =FV($U$6,AA$42,,-$S19,0) -> 2.0937779 | AE52: =FV($U$6,AC$42,,-$S19,0) -> 2.1565913 | AG52: =FV($U$6,AE$42,,-$S19,0) -> 2.221289 | AI52: =FV($U$6,AG$42,,-$S19,0) -> 2.2879277 | AK52: =FV($U$6,AI$42,,-$S19,0) -> 2.3565655
A53: =+A20 -> 47 | C53: =+C20 -> 1 | E53: =+E20 -> x | G53: =+G20 -> x | I53: =FV($U$6,AY$9,,-$S20,0) -> 1.5579674 | K53: =FV($U$6,I$42,,-$S20,0) -> 1.6047064 | M53: =FV($U$6,K$42,,-$S20,0) -> 1.6528476 | O53: =FV($U$6,M$42,,-$S20,0) -> 1.7024331 | Q53: =FV($U$6,O$42,,-$S20,0) -> 1.7535061 | S53: =FV($U$6,Q$42,,-$S20,0) -> 1.8061112 | U53: =FV($U$6,S$42,,-$S20,0) -> 1.8602946 | W53: =FV($U$6,U$42,,-$S20,0) -> 1.9161034 | Y53: =FV($U$6,W$42,,-$S20,0) -> 1.9735865 | AA53: =FV($U$6,Y$42,,-$S20,0) -> 2.0327941 | AC53: =FV($U$6,AA$42,,-$S20,0) -> 2.0937779 | AE53: =FV($U$6,AC$42,,-$S20,0) -> 2.1565913 | AG53: =FV($U$6,AE$42,,-$S20,0) -> 2.221289 | AI53: =FV($U$6,AG$42,,-$S20,0) -> 2.2879277 | AK53: =FV($U$6,AI$42,,-$S20,0) -> 2.3565655
A54: =+A21 -> 48 | C54: =+C21 -> 1 | E54: =+E21 -> x | G54: =+G21 -> x | I54: =FV($U$6,AY$9,,-$S21,0) -> 1.5579674 | K54: =FV($U$6,I$42,,-$S21,0) -> 1.6047064 | M54: =FV($U$6,K$42,,-$S21,0) -> 1.6528476 | O54: =FV($U$6,M$42,,-$S21,0) -> 1.7024331 | Q54: =FV($U$6,O$42,,-$S21,0) -> 1.7535061 | S54: =FV($U$6,Q$42,,-$S21,0) -> 1.8061112 | U54: =FV($U$6,S$42,,-$S21,0) -> 1.8602946 | W54: =FV($U$6,U$42,,-$S21,0) -> 1.9161034 | Y54: =FV($U$6,W$42,,-$S21,0) -> 1.9735865 | AA54: =FV($U$6,Y$42,,-$S21,0) -> 2.0327941 | AC54: =FV($U$6,AA$42,,-$S21,0) -> 2.0937779 | AE54: =FV($U$6,AC$42,,-$S21,0) -> 2.1565913 | AG54: =FV($U$6,AE$42,,-$S21,0) -> 2.221289 | AI54: =FV($U$6,AG$42,,-$S21,0) -> 2.2879277 | AK54: =FV($U$6,AI$42,,-$S21,0) -> 2.3565655
A55: =+A22 -> 49 | C55: =+C22 -> 1 | E55: =+E22 -> x | G55: =+G22 -> x | I55: =FV($U$6,AY$9,,-$S22,0) -> 1.5579674 | K55: =FV($U$6,I$42,,-$S22,0) -> 1.6047064 | M55: =FV($U$6,K$42,,-$S22,0) -> 1.6528476 | O55: =FV($U$6,M$42,,-$S22,0) -> 1.7024331 | Q55: =FV($U$6,O$42,,-$S22,0) -> 1.7535061 | S55: =FV($U$6,Q$42,,-$S22,0) -> 1.8061112 | U55: =FV($U$6,S$42,,-$S22,0) -> 1.8602946 | W55: =FV($U$6,U$42,,-$S22,0) -> 1.9161034 | Y55: =FV($U$6,W$42,,-$S22,0) -> 1.9735865 | AA55: =FV($U$6,Y$42,,-$S22,0) -> 2.0327941 | AC55: =FV($U$6,AA$42,,-$S22,0) -> 2.0937779 | AE55: =FV($U$6,AC$42,,-$S22,0) -> 2.1565913 | AG55: =FV($U$6,AE$42,,-$S22,0) -> 2.221289 | AI55: =FV($U$6,AG$42,,-$S22,0) -> 2.2879277 | AK55: =FV($U$6,AI$42,,-$S22,0) -> 2.3565655
A56: =+A23 -> 50 | C56: =+C23 -> 1 | E56: =+E23 -> x | G56: =+G23 -> x | I56: =FV($U$6,AY$9,,-$S23,0) -> 1.5579674 | K56: =FV($U$6,I$42,,-$S23,0) -> 1.6047064 | M56: =FV($U$6,K$42,,-$S23,0) -> 1.6528476 | O56: =FV($U$6,M$42,,-$S23,0) -> 1.7024331 | Q56: =FV($U$6,O$42,,-$S23,0) -> 1.7535061 | S56: =FV($U$6,Q$42,,-$S23,0) -> 1.8061112 | U56: =FV($U$6,S$42,,-$S23,0) -> 1.8602946 | W56: =FV($U$6,U$42,,-$S23,0) -> 1.9161034 | Y56: =FV($U$6,W$42,,-$S23,0) -> 1.9735865 | AA56: =FV($U$6,Y$42,,-$S23,0) -> 2.0327941 | AC56: =FV($U$6,AA$42,,-$S23,0) -> 2.0937779 | AE56: =FV($U$6,AC$42,,-$S23,0) -> 2.1565913 | AG56: =FV($U$6,AE$42,,-$S23,0) -> 2.221289 | AI56: =FV($U$6,AG$42,,-$S23,0) -> 2.2879277 | AK56: =FV($U$6,AI$42,,-$S23,0) -> 2.3565655
A57: =+A24 -> 51 | C57: =+C24 -> 1 | E57: =+E24 -> x | G57: =+G24 -> x | I57: =FV($U$6,AY$9,,-$S24,0) -> 1.5579674 | K57: =FV($U$6,I$42,,-$S24,0) -> 1.6047064 | M57: =FV($U$6,K$42,,-$S24,0) -> 1.6528476 | O57: =FV($U$6,M$42,,-$S24,0) -> 1.7024331 | Q57: =FV($U$6,O$42,,-$S24,0) -> 1.7535061 | S57: =FV($U$6,Q$42,,-$S24,0) -> 1.8061112 | U57: =FV($U$6,S$42,,-$S24,0) -> 1.8602946 | W57: =FV($U$6,U$42,,-$S24,0) -> 1.9161034 | Y57: =FV($U$6,W$42,,-$S24,0) -> 1.9735865 | AA57: =FV($U$6,Y$42,,-$S24,0) -> 2.0327941 | AC57: =FV($U$6,AA$42,,-$S24,0) -> 2.0937779 | AE57: =FV($U$6,AC$42,,-$S24,0) -> 2.1565913 | AG57: =FV($U$6,AE$42,,-$S24,0) -> 2.221289 | AI57: =FV($U$6,AG$42,,-$S24,0) -> 2.2879277 | AK57: =FV($U$6,AI$42,,-$S24,0) -> 2.3565655
A58: =+A25 -> 52 | C58: =+C25 -> 1 | E58: =+E25 -> x | G58: =+G25 -> x | I58: =FV($U$6,AY$9,,-$S25,0) -> 1.5579674 | K58: =FV($U$6,I$42,,-$S25,0) -> 1.6047064 | M58: =FV($U$6,K$42,,-$S25,0) -> 1.6528476 | O58: =FV($U$6,M$42,,-$S25,0) -> 1.7024331 | Q58: =FV($U$6,O$42,,-$S25,0) -> 1.7535061 | S58: =FV($U$6,Q$42,,-$S25,0) -> 1.8061112 | U58: =FV($U$6,S$42,,-$S25,0) -> 1.8602946 | W58: =FV($U$6,U$42,,-$S25,0) -> 1.9161034 | Y58: =FV($U$6,W$42,,-$S25,0) -> 1.9735865 | AA58: =FV($U$6,Y$42,,-$S25,0) -> 2.0327941 | AC58: =FV($U$6,AA$42,,-$S25,0) -> 2.0937779 | AE58: =FV($U$6,AC$42,,-$S25,0) -> 2.1565913 | AG58: =FV($U$6,AE$42,,-$S25,0) -> 2.221289 | AI58: =FV($U$6,AG$42,,-$S25,0) -> 2.2879277 | AK58: =FV($U$6,AI$42,,-$S25,0) -> 2.3565655
... A68: =+A35 -> 62 | C68: =+C35 -> 1 | E68: =+E35 -> x | G68: =+G35 -> x | I68: =FV($U$6,AY$9,,-$S35,0) -> 1.5579674 | K68: =FV($U$6,I$42,,-$S35,0) -> 1.6047064 | M68: =FV($U$6,K$42,,-$S35,0) -> 1.6528476 | O68: =FV($U$6,M$42,,-$S35,0) -> 1.7024331 | Q68: =FV($U$6,O$42,,-$S35,0) -> 1.7535061 | S68: =FV($U$6,Q$42,,-$S35,0) -> 1.8061112 | U68: =FV($U$6,S$42,,-$S35,0) -> 1.8602946 | W68: =FV($U$6,U$42,,-$S35,0) -> 1.9161034 | Y68: =FV($U$6,W$42,,-$S35,0) -> 1.9735865 | AA68: =FV($U$6,Y$42,,-$S35,0) -> 2.0327941 | AC68: =FV($U$6,AA$42,,-$S35,0) -> 2.0937779 | AE68: =FV($U$6,AC$42,,-$S35,0) -> 2.1565913 | AG68: =FV($U$6,AE$42,,-$S35,0) -> 2.221289 | AI68: =FV($U$6,AG$42,,-$S35,0) -> 2.2879277 | AK68: =FV($U$6,AI$42,,-$S35,0) -> 2.3565655
G71: =+G38 -> Anticipated Expenditures, By Year | I71: =SUM(I47:I69) -> 34.275283 | K71: =SUM(K47:K69) -> 35.303542 | M71: =SUM(M47:M69) -> 36.362648 | O71: =SUM(O47:O69) -> 37.453527 | Q71: =SUM(Q47:Q69) -> 38.577133 | S71: =SUM(S47:S69) -> 39.734447 | U71: =SUM(U47:U69) -> 40.926481 | W71: =SUM(W47:W69) -> 42.154275 | Y71: =SUM(Y47:Y69) -> 43.418903 | AA71: =SUM(AA47:AA69) -> 44.72147 | AC71: =SUM(AC47:AC69) -> 46.063114 | AE71: =SUM(AE47:AE69) -> 47.445008 | AG71: =SUM(AG47:AG69) -> 48.868358 | AI71: =SUM(AI47:AI69) -> 50.334409 | AK71: =SUM(AK47:AK69) -> 51.844441

Sheet Maintain (PRN) 2
G3: Exhibit B
G5: RESERVE EXPENDITURES | U5: Explanatory Notes:
G6: for | T6: 1) | U6: =+'Roofs 1'!V3 -> 0.03 | V6: is the estimated future Inflation Rate for estimating Future Replacement Costs.
G7: =+'Roofs 1'!H5 -> Association | T7: 2) | U7: Fiscal Year is beginning January 1 and ending December 31.
A9: Line Item | C9: Estimated | I9: Estimated Year Last Replaced | K9: Life Analysis, Years | O9: Estimated Year of 1st Replacement | Q9: =+'Roofs 1'!R6 -> 2024 Unit Cost | S9: =+'Roofs 1'!T6 -> 2024 Cost of Replacement | U9: Total Future Cost of Replacement | W9: 1 | Y9: 2 | AA9: 3 | AC9: 4 | AE9: 5 | AG9: 6 | AI9: 7 | AK9: 8 | AM9: 9 | AO9: 10 | AQ9: 11 | AS9: 12 | AU9: 13 | AW9: 14 | AY9: 15
C10: Quantity | E10: Units | G10: Reserve Component Inventory | K10: Useful | M10: Remaining | W10: =+'Roofs 1'!X7 -> 2024 | Y10: =W10+1 -> 2025 | Z10: =X10+1 -> 1 | AA10: =Y10+1 -> 2026 | AB10: =Z10+1 -> 2 | AC10: =AA10+1 -> 2027 | AD10: =AB10+1 -> 3 | AE10: =AC10+1 -> 2028 | AF10: =AD10+1 -> 4 | ... AY10: =AW10+1 -> 2038
G12: ELEMENTS
A14: ='Roofs 1'!B50+1 -> 41 | C14: 1 | E14: x | G14: x | I14: x | K14: x | M14: 1 | N14: ='Roofs 1'!P4 -> 2023 | O14: 1 | Q14: 1 | S14: =C14*Q14 -> 1 | U14: =SUM(W14:AY14)+SUM(I47:AK47) -> 47.575416 | W14: =S14 -> 1 | Y14: =FV($U$6,W$9,,-$S14,0) -> 1.03 | AA14: =FV($U$6,Y$9,,-$S14,0) -> 1.0609 | AC14: =FV($U$6,AA$9,,-$S14,0) -> 1.092727 | AE14: =FV($U$6,AC$9,,-$S14,0) -> 1.1255088 | AG14: =FV($U$6,AE$9,,-$S14,0) -> 1.1592741 | AI14: =FV($U$6,AG$9,,-$S14,0) -> 1.1940523 | AK14: =FV($U$6,AI$9,,-$S14,0) -> 1.2298739 | AM14: =FV($U$6,AK$9,,-$S14,0) -> 1.2667701 | AO14: =FV($U$6,AM$9,,-$S14,0) -> 1.3047732 | AQ14: =FV($U$6,AO$9,,-$S14,0) -> 1.3439164 | AS14: =FV($U$6,AQ$9,,-$S14,0) -> 1.3842339 | AU14: =FV($U$6,AS$9,,-$S14,0) -> 1.4257609 | AW14: =FV($U$6,AU$9,,-$S14,0) -> 1.4685337 | AY14: =FV($U$6,AW$9,,-$S14,0) -> 1.5125897
A15: =+A14+1 -> 42 | C15: 1 | E15: x | G15: x | I15: x | K15: x | M15: 1 | N15: =N14 -> 2023 | O15: 1 | Q15: 1 | S15: =C15*Q15 -> 1 | U15: =SUM(W15:AY15)+SUM(I48:AK48) -> 47.575416 | W15: =S15 -> 1 | Y15: =FV($U$6,W$9,,-$S15,0) -> 1.03 | AA15: =FV($U$6,Y$9,,-$S15,0) -> 1.0609 | AC15: =FV($U$6,AA$9,,-$S15,0) -> 1.092727 | AE15: =FV($U$6,AC$9,,-$S15,0) -> 1.1255088 | AG15: =FV($U$6,AE$9,,-$S15,0) -> 1.1592741 | AI15: =FV($U$6,AG$9,,-$S15,0) -> 1.1940523 | AK15: =FV($U$6,AI$9,,-$S15,0) -> 1.2298739 | AM15: =FV($U$6,AK$9,,-$S15,0) -> 1.2667701 | AO15: =FV($U$6,AM$9,,-$S15,0) -> 1.3047732 | AQ15: =FV($U$6,AO$9,,-$S15,0) -> 1.3439164 | AS15: =FV($U$6,AQ$9,,-$S15,0) -> 1.3842339 | AU15: =FV($U$6,AS$9,,-$S15,0) -> 1.4257609 | AW15: =FV($U$6,AU$9,,-$S15,0) -> 1.4685337 | AY15: =FV($U$6,AW$9,,-$S15,0) -> 1.5125897
A16: =+A15+1 -> 43 | C16: 1 | E16: x | G16: x | I16: x | K16: x | M16: 1 | N16: =N15 -> 2023 | O16: 1 | Q16: 1 | S16: =C16*Q16 -> 1 | U16: =SUM(W16:AY16)+SUM(I49:AK49) -> 47.575416 | W16: =S16 -> 1 | Y16: =FV($U$6,W$9,,-$S16,0) -> 1.03 | AA16: =FV($U$6,Y$9,,-$S16,0) -> 1.0609 | AC16: =FV($U$6,AA$9,,-$S16,0) -> 1.092727 | AE16: =FV($U$6,AC$9,,-$S16,0) -> 1.1255088 | AG16: =FV($U$6,AE$9,,-$S16,0) -> 1.1592741 | AI16: =FV($U$6,AG$9,,-$S16,0) -> 1.1940523 | AK16: =FV($U$6,AI$9,,-$S16,0) -> 1.2298739 | AM16: =FV($U$6,AK$9,,-$S16,0) -> 1.2667701 | AO16: =FV($U$6,AM$9,,-$S16,0) -> 1.3047732 | AQ16: =FV($U$6,AO$9,,-$S16,0) -> 1.3439164 | AS16: =FV($U$6,AQ$9,,-$S16,0) -> 1.3842339 | AU16: =FV($U$6,AS$9,,-$S16,0) -> 1.4257609 | AW16: =FV($U$6,AU$9,,-$S16,0) -> 1.4685337 | AY16: =FV($U$6,AW$9,,-$S16,0) -> 1.5125897
A17: =+A16+1 -> 44 | C17: 1 | E17: x | G17: x | I17: x | K17: x | M17: 1 | N17: =N16 -> 2023 | O17: 1 | Q17: 1 | S17: =C17*Q17 -> 1 | U17: =SUM(W17:AY17)+SUM(I50:AK50) -> 47.575416 | W17: =S17 -> 1 | Y17: =FV($U$6,W$9,,-$S17,0) -> 1.03 | AA17: =FV($U$6,Y$9,,-$S17,0) -> 1.0609 | AC17: =FV($U$6,AA$9,,-$S17,0) -> 1.092727 | AE17: =FV($U$6,AC$9,,-$S17,0) -> 1.1255088 | AG17: =FV($U$6,AE$9,,-$S17,0) -> 1.1592741 | AI17: =FV($U$6,AG$9,,-$S17,0) -> 1.1940523 | AK17: =FV($U$6,AI$9,,-$S17,0) -> 1.2298739 | AM17: =FV($U$6,AK$9,,-$S17,0) -> 1.2667701 | AO17: =FV($U$6,AM$9,,-$S17,0) -> 1.3047732 | AQ17: =FV($U$6,AO$9,,-$S17,0) -> 1.3439164 | AS17: =FV($U$6,AQ$9,,-$S17,0) -> 1.3842339 | AU17: =FV($U$6,AS$9,,-$S17,0) -> 1.4257609 | AW17: =FV($U$6,AU$9,,-$S17,0) -> 1.4685337 | AY17: =FV($U$6,AW$9,,-$S17,0) -> 1.5125897
A18: =+A17+1 -> 45 | C18: 1 | E18: x | G18: x | I18: x | K18: x | M18: 1 | N18: =N17 -> 2023 | O18: 1 | Q18: 1 | S18: =C18*Q18 -> 1 | U18: =SUM(W18:AY18)+SUM(I51:AK51) -> 47.575416 | W18: =S18 -> 1 | Y18: =FV($U$6,W$9,,-$S18,0) -> 1.03 | AA18: =FV($U$6,Y$9,,-$S18,0) -> 1.0609 | AC18: =FV($U$6,AA$9,,-$S18,0) -> 1.092727 | AE18: =FV($U$6,AC$9,,-$S18,0) -> 1.1255088 | AG18: =FV($U$6,AE$9,,-$S18,0) -> 1.1592741 | AI18: =FV($U$6,AG$9,,-$S18,0) -> 1.1940523 | AK18: =FV($U$6,AI$9,,-$S18,0) -> 1.2298739 | AM18: =FV($U$6,AK$9,,-$S18,0) -> 1.2667701 | AO18: =FV($U$6,AM$9,,-$S18,0) -> 1.3047732 | AQ18: =FV($U$6,AO$9,,-$S18,0) -> 1.3439164 | AS18: =FV($U$6,AQ$9,,-$S18,0) -> 1.3842339 | AU18: =FV($U$6,AS$9,,-$S18,0) -> 1.4257609 | AW18: =FV($U$6,AU$9,,-$S18,0) -> 1.4685337 | AY18: =FV($U$6,AW$9,,-$S18,0) -> 1.5125897
A19: =+A18+1 -> 46 | C19: 1 | E19: x | G19: x | I19: x | K19: x | M19: 1 | N19: =N18 -> 2023 | O19: 1 | Q19: 1 | S19: =C19*Q19 -> 1 | U19: =SUM(W19:AY19)+SUM(I52:AK52) -> 47.575416 | W19: =S19 -> 1 | Y19: =FV($U$6,W$9,,-$S19,0) -> 1.03 | AA19: =FV($U$6,Y$9,,-$S19,0) -> 1.0609 | AC19: =FV($U$6,AA$9,,-$S19,0) -> 1.092727 | AE19: =FV($U$6,AC$9,,-$S19,0) -> 1.1255088 | AG19: =FV($U$6,AE$9,,-$S19,0) -> 1.1592741 | AI19: =FV($U$6,AG$9,,-$S19,0) -> 1.1940523 | AK19: =FV($U$6,AI$9,,-$S19,0) -> 1.2298739 | AM19: =FV($U$6,AK$9,,-$S19,0) -> 1.2667701 | AO19: =FV($U$6,AM$9,,-$S19,0) -> 1.3047732 | AQ19: =FV($U$6,AO$9,,-$S19,0) -> 1.3439164 | AS19: =FV($U$6,AQ$9,,-$S19,0) -> 1.3842339 | AU19: =FV($U$6,AS$9,,-$S19,0) -> 1.4257609 | AW19: =FV($U$6,AU$9,,-$S19,0) -> 1.4685337 | AY19: =FV($U$6,AW$9,,-$S19,0) -> 1.5125897
A20: =+A19+1 -> 47 | C20: 1 | E20: x | G20: x | I20: x | K20: x | M20: 1 | N20: =N19 -> 2023 | O20: 1 | Q20: 1 | S20: =C20*Q20 -> 1 | U20: =SUM(W20:AY20)+SUM(I53:AK53) -> 47.575416 | W20: =S20 -> 1 | Y20: =FV($U$6,W$9,,-$S20,0) -> 1.03 | AA20: =FV($U$6,Y$9,,-$S20,0) -> 1.0609 | AC20: =FV($U$6,AA$9,,-$S20,0) -> 1.092727 | AE20: =FV($U$6,AC$9,,-$S20,0) -> 1.1255088 | AG20: =FV($U$6,AE$9,,-$S20,0) -> 1.1592741 | AI20: =FV($U$6,AG$9,,-$S20,0) -> 1.1940523 | AK20: =FV($U$6,AI$9,,-$S20,0) -> 1.2298739 | AM20: =FV($U$6,AK$9,,-$S20,0) -> 1.2667701 | AO20: =FV($U$6,AM$9,,-$S20,0) -> 1.3047732 | AQ20: =FV($U$6,AO$9,,-$S20,0) -> 1.3439164 | AS20: =FV($U$6,AQ$9,,-$S20,0) -> 1.3842339 | AU20: =FV($U$6,AS$9,,-$S20,0) -> 1.4257609 | AW20: =FV($U$6,AU$9,,-$S20,0) -> 1.4685337 | AY20: =FV($U$6,AW$9,,-$S20,0) -> 1.5125897
A21: =+A20+1 -> 48 | C21: 1 | E21: x | G21: x | I21: x | K21: x | M21: 1 | N21: =N20 -> 2023 | O21: 1 | Q21: 1 | S21: =C21*Q21 -> 1 | U21: =SUM(W21:AY21)+SUM(I54:AK54) -> 47.575416 | W21: =S21 -> 1 | Y21: =FV($U$6,W$9,,-$S21,0) -> 1.03 | AA21: =FV($U$6,Y$9,,-$S21,0) -> 1.0609 | AC21: =FV($U$6,AA$9,,-$S21,0) -> 1.092727 | AE21: =FV($U$6,AC$9,,-$S21,0) -> 1.1255088 | AG21: =FV($U$6,AE$9,,-$S21,0) -> 1.1592741 | AI21: =FV($U$6,AG$9,,-$S21,0) -> 1.1940523 | AK21: =FV($U$6,AI$9,,-$S21,0) -> 1.2298739 | AM21: =FV($U$6,AK$9,,-$S21,0) -> 1.2667701 | AO21: =FV($U$6,AM$9,,-$S21,0) -> 1.3047732 | AQ21: =FV($U$6,AO$9,,-$S21,0) -> 1.3439164 | AS21: =FV($U$6,AQ$9,,-$S21,0) -> 1.3842339 | AU21: =FV($U$6,AS$9,,-$S21,0) -> 1.4257609 | AW21: =FV($U$6,AU$9,,-$S21,0) -> 1.4685337 | AY21: =FV($U$6,AW$9,,-$S21,0) -> 1.5125897
A22: =+A21+1 -> 49 | C22: 1 | E22: x | G22: x | I22: x | K22: x | M22: 1 | N22: =N21 -> 2023 | O22: 1 | Q22: 1 | S22: =C22*Q22 -> 1 | U22: =SUM(W22:AY22)+SUM(I55:AK55) -> 47.575416 | W22: =S22 -> 1 | Y22: =FV($U$6,W$9,,-$S22,0) -> 1.03 | AA22: =FV($U$6,Y$9,,-$S22,0) -> 1.0609 | AC22: =FV($U$6,AA$9,,-$S22,0) -> 1.092727 | AE22: =FV($U$6,AC$9,,-$S22,0) -> 1.1255088 | AG22: =FV($U$6,AE$9,,-$S22,0) -> 1.1592741 | AI22: =FV($U$6,AG$9,,-$S22,0) -> 1.1940523 | AK22: =FV($U$6,AI$9,,-$S22,0) -> 1.2298739 | AM22: =FV($U$6,AK$9,,-$S22,0) -> 1.2667701 | AO22: =FV($U$6,AM$9,,-$S22,0) -> 1.3047732 | AQ22: =FV($U$6,AO$9,,-$S22,0) -> 1.3439164 | AS22: =FV($U$6,AQ$9,,-$S22,0) -> 1.3842339 | AU22: =FV($U$6,AS$9,,-$S22,0) -> 1.4257609 | AW22: =FV($U$6,AU$9,,-$S22,0) -> 1.4685337 | AY22: =FV($U$6,AW$9,,-$S22,0) -> 1.5125897
A23: =+A22+1 -> 50 | C23: 1 | E23: x | G23: x | I23: x | K23: x | M23: 1 | N23: =N22 -> 2023 | O23: 1 | Q23: 1 | S23: =C23*Q23 -> 1 | U23: =SUM(W23:AY23)+SUM(I56:AK56) -> 47.575416 | W23: =S23 -> 1 | Y23: =FV($U$6,W$9,,-$S23,0) -> 1.03 | AA23: =FV($U$6,Y$9,,-$S23,0) -> 1.0609 | AC23: =FV($U$6,AA$9,,-$S23,0) -> 1.092727 | AE23: =FV($U$6,AC$9,,-$S23,0) -> 1.1255088 | AG23: =FV($U$6,AE$9,,-$S23,0) -> 1.1592741 | AI23: =FV($U$6,AG$9,,-$S23,0) -> 1.1940523 | AK23: =FV($U$6,AI$9,,-$S23,0) -> 1.2298739 | AM23: =FV($U$6,AK$9,,-$S23,0) -> 1.2667701 | AO23: =FV($U$6,AM$9,,-$S23,0) -> 1.3047732 | AQ23: =FV($U$6,AO$9,,-$S23,0) -> 1.3439164 | AS23: =FV($U$6,AQ$9,,-$S23,0) -> 1.3842339 | AU23: =FV($U$6,AS$9,,-$S23,0) -> 1.4257609 | AW23: =FV($U$6,AU$9,,-$S23,0) -> 1.4685337 | AY23: =FV($U$6,AW$9,,-$S23,0) -> 1.5125897
A24: =+A23+1 -> 51 | C24: 1 | E24: x | G24: x | I24: x | K24: x | M24: 1 | N24: =N23 -> 2023 | O24: 1 | Q24: 1 | S24: =C24*Q24 -> 1 | U24: =SUM(W24:AY24)+SUM(I57:AK57) -> 47.575416 | W24: =S24 -> 1 | Y24: =FV($U$6,W$9,,-$S24,0) -> 1.03 | AA24: =FV($U$6,Y$9,,-$S24,0) -> 1.0609 | AC24: =FV($U$6,AA$9,,-$S24,0) -> 1.092727 | AE24: =FV($U$6,AC$9,,-$S24,0) -> 1.1255088 | AG24: =FV($U$6,AE$9,,-$S24,0) -> 1.1592741 | AI24: =FV($U$6,AG$9,,-$S24,0) -> 1.1940523 | AK24: =FV($U$6,AI$9,,-$S24,0) -> 1.2298739 | AM24: =FV($U$6,AK$9,,-$S24,0) -> 1.2667701 | AO24: =FV($U$6,AM$9,,-$S24,0) -> 1.3047732 | AQ24: =FV($U$6,AO$9,,-$S24,0) -> 1.3439164 | AS24: =FV($U$6,AQ$9,,-$S24,0) -> 1.3842339 | AU24: =FV($U$6,AS$9,,-$S24,0) -> 1.4257609 | AW24: =FV($U$6,AU$9,,-$S24,0) -> 1.4685337 | AY24: =FV($U$6,AW$9,,-$S24,0) -> 1.5125897
A25: =+A24+1 -> 52 | C25: 1 | E25: x | G25: x | I25: x | K25: x | M25: 1 | N25: =N24 -> 2023 | O25: 1 | Q25: 1 | S25: =C25*Q25 -> 1 | U25: =SUM(W25:AY25)+SUM(I58:AK58) -> 47.575416 | W25: =S25 -> 1 | Y25: =FV($U$6,W$9,,-$S25,0) -> 1.03 | AA25: =FV($U$6,Y$9,,-$S25,0) -> 1.0609 | AC25: =FV($U$6,AA$9,,-$S25,0) -> 1.092727 | AE25: =FV($U$6,AC$9,,-$S25,0) -> 1.1255088 | AG25: =FV($U$6,AE$9,,-$S25,0) -> 1.1592741 | AI25: =FV($U$6,AG$9,,-$S25,0) -> 1.1940523 | AK25: =FV($U$6,AI$9,,-$S25,0) -> 1.2298739 | AM25: =FV($U$6,AK$9,,-$S25,0) -> 1.2667701 | AO25: =FV($U$6,AM$9,,-$S25,0) -> 1.3047732 | AQ25: =FV($U$6,AO$9,,-$S25,0) -> 1.3439164 | AS25: =FV($U$6,AQ$9,,-$S25,0) -> 1.3842339 | AU25: =FV($U$6,AS$9,,-$S25,0) -> 1.4257609 | AW25: =FV($U$6,AU$9,,-$S25,0) -> 1.4685337 | AY25: =FV($U$6,AW$9,,-$S25,0) -> 1.5125897
A26: =+A25+1 -> 53 | C26: 1 | E26: x | G26: x | I26: x | K26: x | M26: 1 | N26: =N25 -> 2023 | O26: 1 | Q26: 1 | S26: =C26*Q26 -> 1 | U26: =SUM(W26:AY26)+SUM(I59:AK59) -> 47.575416 | W26: =S26 -> 1 | Y26: =FV($U$6,W$9,,-$S26,0) -> 1.03 | AA26: =FV($U$6,Y$9,,-$S26,0) -> 1.0609 | AC26: =FV($U$6,AA$9,,-$S26,0) -> 1.092727 | AE26: =FV($U$6,AC$9,,-$S26,0) -> 1.1255088 | AG26: =FV($U$6,AE$9,,-$S26,0) -> 1.1592741 | AI26: =FV($U$6,AG$9,,-$S26,0) -> 1.1940523 | AK26: =FV($U$6,AI$9,,-$S26,0) -> 1.2298739 | AM26: =FV($U$6,AK$9,,-$S26,0) -> 1.2667701 | AO26: =FV($U$6,AM$9,,-$S26,0) -> 1.3047732 | AQ26: =FV($U$6,AO$9,,-$S26,0) -> 1.3439164 | AS26: =FV($U$6,AQ$9,,-$S26,0) -> 1.3842339 | AU26: =FV($U$6,AS$9,,-$S26,0) -> 1.4257609 | AW26: =FV($U$6,AU$9,,-$S26,0) -> 1.4685337 | AY26: =FV($U$6,AW$9,,-$S26,0) -> 1.5125897
... A35: =+A34+1 -> 62 | C35: 1 | E35: x | G35: x | I35: x | K35: x | M35: 1 | N35: =N34 -> 2023 | O35: 1 | Q35: 1 | S35: =C35*Q35 -> 1 | U35: =SUM(W35:AY35)+SUM(I68:AK68) -> 47.575416 | W35: =S35 -> 1 | Y35: =FV($U$6,W$9,,-$S35,0) -> 1.03 | AA35: =FV($U$6,Y$9,,-$S35,0) -> 1.0609 | AC35: =FV($U$6,AA$9,,-$S35,0) -> 1.092727 | AE35: =FV($U$6,AC$9,,-$S35,0) -> 1.1255088 | AG35: =FV($U$6,AE$9,,-$S35,0) -> 1.1592741 | AI35: =FV($U$6,AG$9,,-$S35,0) -> 1.1940523 | AK35: =FV($U$6,AI$9,,-$S35,0) -> 1.2298739 | AM35: =FV($U$6,AK$9,,-$S35,0) -> 1.2667701 | AO35: =FV($U$6,AM$9,,-$S35,0) -> 1.3047732 | AQ35: =FV($U$6,AO$9,,-$S35,0) -> 1.3439164 | AS35: =FV($U$6,AQ$9,,-$S35,0) -> 1.3842339 | AU35: =FV($U$6,AS$9,,-$S35,0) -> 1.4257609 | AW35: =FV($U$6,AU$9,,-$S35,0) -> 1.4685337 | AY35: =FV($U$6,AW$9,,-$S35,0) -> 1.5125897
G38: Anticipated Expenditures, By Year | S38: =SUM(S14:S35) -> 22 | U38: =SUM(U14:U35) -> 1046.6591 | W38: =SUM(W14:W36) -> 22 | Y38: =SUM(Y14:Y36) -> 22.66 | AA38: =SUM(AA14:AA36) -> 23.3398 | AC38: =SUM(AC14:AC36) -> 24.039994 | AE38: =SUM(AE14:AE36) -> 24.761194 | AG38: =SUM(AG14:AG36) -> 25.50403 | AI38: =SUM(AI14:AI36) -> 26.269151 | AK38: =SUM(AK14:AK36) -> 27.057225 | AM38: =SUM(AM14:AM36) -> 27.868942 | AO38: =SUM(AO14:AO36) -> 28.70501 | AQ38: =SUM(AQ14:AQ36) -> 29.56616 | AS38: =SUM(AS14:AS36) -> 30.453145 | AU38: =SUM(AU14:AU36) -> 31.36674 | AW38: =SUM(AW14:AW36) -> 32.307742 | AY38: =SUM(AY14:AY36) -> 33.276974
A42: Line Item | I42: 16 | K42: 17 | M42: 18 | O42: 19 | Q42: 20 | S42: =+Q42+1 -> 21 | U42: =+S42+1 -> 22 | W42: =+U42+1 -> 23 | Y42: =+W42+1 -> 24 | AA42: =+Y42+1 -> 25 | AC42: =+AA42+1 -> 26 | AE42: =+AC42+1 -> 27 | AG42: =+AE42+1 -> 28 | AI42: =+AG42+1 -> 29 | AK42: =+AI42+1 -> 30
C43: Quantity | E43: Units | G43: Reserve Component Inventory | I43: =AY10+1 -> 2039 | J43: =AZ10+1 -> 1 | K43: =I43+1 -> 2040 | L43: =J43+1 -> 2 | M43: =K43+1 -> 2041 | N43: =L43+1 -> 3 | O43: =M43+1 -> 2042 | P43: =N43+1 -> 4 | Q43: =O43+1 -> 2043 | S43: =+Q43+1 -> 2044 | T43: =R43+1 -> 1 | U43: =S43+1 -> 2045 | V43: =T43+1 -> 2 | W43: =U43+1 -> 2046 | X43: =V43+1 -> 3 | Y43: =W43+1 -> 2047 | Z43: =X43+1 -> 4 | AA43: =Y43+1 -> 2048 | AC43: =AA43+1 -> 2049 | AE43: =AC43+1 -> 2050 | AG43: =AE43+1 -> 2051 | AI43: =AG43+1 -> 2052 | AK43: =AI43+1 -> 2053
G45: =+G12 -> ELEMENTS
A47: =+A14 -> 41 | C47: =+C14 -> 1 | E47: =+E14 -> x | G47: =+G14 -> x | I47: =FV($U$6,AY$9,,-$S14,0) -> 1.5579674 | K47: =FV($U$6,I$42,,-$S14,0) -> 1.6047064 | M47: =FV($U$6,K$42,,-$S14,0) -> 1.6528476 | O47: =FV($U$6,M$42,,-$S14,0) -> 1.7024331 | Q47: =FV($U$6,O$42,,-$S14,0) -> 1.7535061 | S47: =FV($U$6,Q$42,,-$S14,0) -> 1.8061112 | U47: =FV($U$6,S$42,,-$S14,0) -> 1.8602946 | W47: =FV($U$6,U$42,,-$S14,0) -> 1.9161034 | Y47: =FV($U$6,W$42,,-$S14,0) -> 1.9735865 | AA47: =FV($U$6,Y$42,,-$S14,0) -> 2.0327941 | AC47: =FV($U$6,AA$42,,-$S14,0) -> 2.0937779 | AE47: =FV($U$6,AC$42,,-$S14,0) -> 2.1565913 | AG47: =FV($U$6,AE$42,,-$S14,0) -> 2.221289 | AI47: =FV($U$6,AG$42,,-$S14,0) -> 2.2879277 | AK47: =FV($U$6,AI$42,,-$S14,0) -> 2.3565655
A48: =+A15 -> 42 | C48: =+C15 -> 1 | E48: =+E15 -> x | G48: =+G15 -> x | I48: =FV($U$6,AY$9,,-$S15,0) -> 1.5579674 | K48: =FV($U$6,I$42,,-$S15,0) -> 1.6047064 | M48: =FV($U$6,K$42,,-$S15,0) -> 1.6528476 | O48: =FV($U$6,M$42,,-$S15,0) -> 1.7024331 | Q48: =FV($U$6,O$42,,-$S15,0) -> 1.7535061 | S48: =FV($U$6,Q$42,,-$S15,0) -> 1.8061112 | U48: =FV($U$6,S$42,,-$S15,0) -> 1.8602946 | W48: =FV($U$6,U$42,,-$S15,0) -> 1.9161034 | Y48: =FV($U$6,W$42,,-$S15,0) -> 1.9735865 | AA48: =FV($U$6,Y$42,,-$S15,0) -> 2.0327941 | AC48: =FV($U$6,AA$42,,-$S15,0) -> 2.0937779 | AE48: =FV($U$6,AC$42,,-$S15,0) -> 2.1565913 | AG48: =FV($U$6,AE$42,,-$S15,0) -> 2.221289 | AI48: =FV($U$6,AG$42,,-$S15,0) -> 2.2879277 | AK48: =FV($U$6,AI$42,,-$S15,0) -> 2.3565655
A49: =+A16 -> 43 | C49: =+C16 -> 1 | E49: =+E16 -> x | G49: =+G16 -> x | I49: =FV($U$6,AY$9,,-$S16,0) -> 1.5579674 | K49: =FV($U$6,I$42,,-$S16,0) -> 1.6047064 | M49: =FV($U$6,K$42,,-$S16,0) -> 1.6528476 | O49: =FV($U$6,M$42,,-$S16,0) -> 1.7024331 | Q49: =FV($U$6,O$42,,-$S16,0) -> 1.7535061 | S49: =FV($U$6,Q$42,,-$S16,0) -> 1.8061112 | U49: =FV($U$6,S$42,,-$S16,0) -> 1.8602946 | W49: =FV($U$6,U$42,,-$S16,0) -> 1.9161034 | Y49: =FV($U$6,W$42,,-$S16,0) -> 1.9735865 | AA49: =FV($U$6,Y$42,,-$S16,0) -> 2.0327941 | AC49: =FV($U$6,AA$42,,-$S16,0) -> 2.0937779 | AE49: =FV($U$6,AC$42,,-$S16,0) -> 2.1565913 | AG49: =FV($U$6,AE$42,,-$S16,0) -> 2.221289 | AI49: =FV($U$6,AG$42,,-$S16,0) -> 2.2879277 | AK49: =FV($U$6,AI$42,,-$S16,0) -> 2.3565655
A50: =+A17 -> 44 | C50: =+C17 -> 1 | E50: =+E17 -> x | G50: =+G17 -> x | I50: =FV($U$6,AY$9,,-$S17,0) -> 1.5579674 | K50: =FV($U$6,I$42,,-$S17,0) -> 1.6047064 | M50: =FV($U$6,K$42,,-$S17,0) -> 1.6528476 | O50: =FV($U$6,M$42,,-$S17,0) -> 1.7024331 | Q50: =FV($U$6,O$42,,-$S17,0) -> 1.7535061 | S50: =FV($U$6,Q$42,,-$S17,0) -> 1.8061112 | U50: =FV($U$6,S$42,,-$S17,0) -> 1.8602946 | W50: =FV($U$6,U$42,,-$S17,0) -> 1.9161034 | Y50: =FV($U$6,W$42,,-$S17,0) -> 1.9735865 | AA50: =FV($U$6,Y$42,,-$S17,0) -> 2.0327941 | AC50: =FV($U$6,AA$42,,-$S17,0) -> 2.0937779 | AE50: =FV($U$6,AC$42,,-$S17,0) -> 2.1565913 | AG50: =FV($U$6,AE$42,,-$S17,0) -> 2.221289 | AI50: =FV($U$6,AG$42,,-$S17,0) -> 2.2879277 | AK50: =FV($U$6,AI$42,,-$S17,0) -> 2.3565655
A51: =+A18 -> 45 | C51: =+C18 -> 1 | E51: =+E18 -> x | G51: =+G18 -> x | I51: =FV($U$6,AY$9,,-$S18,0) -> 1.5579674 | K51: =FV($U$6,I$42,,-$S18,0) -> 1.6047064 | M51: =FV($U$6,K$42,,-$S18,0) -> 1.6528476 | O51: =FV($U$6,M$42,,-$S18,0) -> 1.7024331 | Q51: =FV($U$6,O$42,,-$S18,0) -> 1.7535061 | S51: =FV($U$6,Q$42,,-$S18,0) -> 1.8061112 | U51: =FV($U$6,S$42,,-$S18,0) -> 1.8602946 | W51: =FV($U$6,U$42,,-$S18,0) -> 1.9161034 | Y51: =FV($U$6,W$42,,-$S18,0) -> 1.9735865 | AA51: =FV($U$6,Y$42,,-$S18,0) -> 2.0327941 | AC51: =FV($U$6,AA$42,,-$S18,0) -> 2.0937779 | AE51: =FV($U$6,AC$42,,-$S18,0) -> 2.1565913 | AG51: =FV($U$6,AE$42,,-$S18,0) -> 2.221289 | AI51: =FV($U$6,AG$42,,-$S18,0) -> 2.2879277 | AK51: =FV($U$6,AI$42,,-$S18,0) -> 2.3565655
A52: =+A19 -> 46 | C52: =+C19 -> 1 | E52: =+E19 -> x | G52: =+G19 -> x | I52: =FV($U$6,AY$9,,-$S19,0) -> 1.5579674 | K52: =FV($U$6,I$42,,-$S19,0) -> 1.6047064 | M52: =FV($U$6,K$42,,-$S19,0) -> 1.6528476 | O52: =FV($U$6,M$42,,-$S19,0) -> 1.7024331 | Q52: =FV($U$6,O$42,,-$S19,0) -> 1.7535061 | S52: =FV($U$6,Q$42,,-$S19,0) -> 1.8061112 | U52: =FV($U$6,S$42,,-$S19,0) -> 1.8602946 | W52: =FV($U$6,U$42,,-$S19,0) -> 1.9161034 | Y52: =FV($U$6,W$42,,-$S19,0) -> 1.9735865 | AA52: =FV($U$6,Y$42,,-$S19,0) -> 2.0327941 | AC52: =FV($U$6,AA$42,,-$S19,0) -> 2.0937779 | AE52: =FV($U$6,AC$42,,-$S19,0) -> 2.1565913 | AG52: =FV($U$6,AE$42,,-$S19,0) -> 2.221289 | AI52: =FV($U$6,AG$42,,-$S19,0) -> 2.2879277 | AK52: =FV($U$6,AI$42,,-$S19,0) -> 2.3565655
A53: =+A20 -> 47 | C53: =+C20 -> 1 | E53: =+E20 -> x | G53: =+G20 -> x | I53: =FV($U$6,AY$9,,-$S20,0) -> 1.5579674 | K53: =FV($U$6,I$42,,-$S20,0) -> 1.6047064 | M53: =FV($U$6,K$42,,-$S20,0) -> 1.6528476 | O53: =FV($U$6,M$42,,-$S20,0) -> 1.7024331 | Q53: =FV($U$6,O$42,,-$S20,0) -> 1.7535061 | S53: =FV($U$6,Q$42,,-$S20,0) -> 1.8061112 | U53: =FV($U$6,S$42,,-$S20,0) -> 1.8602946 | W53: =FV($U$6,U$42,,-$S20,0) -> 1.9161034 | Y53: =FV($U$6,W$42,,-$S20,0) -> 1.9735865 | AA53: =FV($U$6,Y$42,,-$S20,0) -> 2.0327941 | AC53: =FV($U$6,AA$42,,-$S20,0) -> 2.0937779 | AE53: =FV($U$6,AC$42,,-$S20,0) -> 2.1565913 | AG53: =FV($U$6,AE$42,,-$S20,0) -> 2.221289 | AI53: =FV($U$6,AG$42,,-$S20,0) -> 2.2879277 | AK53: =FV($U$6,AI$42,,-$S20,0) -> 2.3565655
A54: =+A21 -> 48 | C54: =+C21 -> 1 | E54: =+E21 -> x | G54: =+G21 -> x | I54: =FV($U$6,AY$9,,-$S21,0) -> 1.5579674 | K54: =FV($U$6,I$42,,-$S21,0) -> 1.6047064 | M54: =FV($U$6,K$42,,-$S21,0) -> 1.6528476 | O54: =FV($U$6,M$42,,-$S21,0) -> 1.7024331 | Q54: =FV($U$6,O$42,,-$S21,0) -> 1.7535061 | S54: =FV($U$6,Q$42,,-$S21,0) -> 1.8061112 | U54: =FV($U$6,S$42,,-$S21,0) -> 1.8602946 | W54: =FV($U$6,U$42,,-$S21,0) -> 1.9161034 | Y54: =FV($U$6,W$42,,-$S21,0) -> 1.9735865 | AA54: =FV($U$6,Y$42,,-$S21,0) -> 2.0327941 | AC54: =FV($U$6,AA$42,,-$S21,0) -> 2.0937779 | AE54: =FV($U$6,AC$42,,-$S21,0) -> 2.1565913 | AG54: =FV($U$6,AE$42,,-$S21,0) -> 2.221289 | AI54: =FV($U$6,AG$42,,-$S21,0) -> 2.2879277 | AK54: =FV($U$6,AI$42,,-$S21,0) -> 2.3565655
A55: =+A22 -> 49 | C55: =+C22 -> 1 | E55: =+E22 -> x | G55: =+G22 -> x | I55: =FV($U$6,AY$9,,-$S22,0) -> 1.5579674 | K55: =FV($U$6,I$42,,-$S22,0) -> 1.6047064 | M55: =FV($U$6,K$42,,-$S22,0) -> 1.6528476 | O55: =FV($U$6,M$42,,-$S22,0) -> 1.7024331 | Q55: =FV($U$6,O$42,,-$S22,0) -> 1.7535061 | S55: =FV($U$6,Q$42,,-$S22,0) -> 1.8061112 | U55: =FV($U$6,S$42,,-$S22,0) -> 1.8602946 | W55: =FV($U$6,U$42,,-$S22,0) -> 1.9161034 | Y55: =FV($U$6,W$42,,-$S22,0) -> 1.9735865 | AA55: =FV($U$6,Y$42,,-$S22,0) -> 2.0327941 | AC55: =FV($U$6,AA$42,,-$S22,0) -> 2.0937779 | AE55: =FV($U$6,AC$42,,-$S22,0) -> 2.1565913 | AG55: =FV($U$6,AE$42,,-$S22,0) -> 2.221289 | AI55: =FV($U$6,AG$42,,-$S22,0) -> 2.2879277 | AK55: =FV($U$6,AI$42,,-$S22,0) -> 2.3565655
A56: =+A23 -> 50 | C56: =+C23 -> 1 | E56: =+E23 -> x | G56: =+G23 -> x | I56: =FV($U$6,AY$9,,-$S23,0) -> 1.5579674 | K56: =FV($U$6,I$42,,-$S23,0) -> 1.6047064 | M56: =FV($U$6,K$42,,-$S23,0) -> 1.6528476 | O56: =FV($U$6,M$42,,-$S23,0) -> 1.7024331 | Q56: =FV($U$6,O$42,,-$S23,0) -> 1.7535061 | S56: =FV($U$6,Q$42,,-$S23,0) -> 1.8061112 | U56: =FV($U$6,S$42,,-$S23,0) -> 1.8602946 | W56: =FV($U$6,U$42,,-$S23,0) -> 1.9161034 | Y56: =FV($U$6,W$42,,-$S23,0) -> 1.9735865 | AA56: =FV($U$6,Y$42,,-$S23,0) -> 2.0327941 | AC56: =FV($U$6,AA$42,,-$S23,0) -> 2.0937779 | AE56: =FV($U$6,AC$42,,-$S23,0) -> 2.1565913 | AG56: =FV($U$6,AE$42,,-$S23,0) -> 2.221289 | AI56: =FV($U$6,AG$42,,-$S23,0) -> 2.2879277 | AK56: =FV($U$6,AI$42,,-$S23,0) -> 2.3565655
A57: =+A24 -> 51 | C57: =+C24 -> 1 | E57: =+E24 -> x | G57: =+G24 -> x | I57: =FV($U$6,AY$9,,-$S24,0) -> 1.5579674 | K57: =FV($U$6,I$42,,-$S24,0) -> 1.6047064 | M57: =FV($U$6,K$42,,-$S24,0) -> 1.6528476 | O57: =FV($U$6,M$42,,-$S24,0) -> 1.7024331 | Q57: =FV($U$6,O$42,,-$S24,0) -> 1.7535061 | S57: =FV($U$6,Q$42,,-$S24,0) -> 1.8061112 | U57: =FV($U$6,S$42,,-$S24,0) -> 1.8602946 | W57: =FV($U$6,U$42,,-$S24,0) -> 1.9161034 | Y57: =FV($U$6,W$42,,-$S24,0) -> 1.9735865 | AA57: =FV($U$6,Y$42,,-$S24,0) -> 2.0327941 | AC57: =FV($U$6,AA$42,,-$S24,0) -> 2.0937779 | AE57: =FV($U$6,AC$42,,-$S24,0) -> 2.1565913 | AG57: =FV($U$6,AE$42,,-$S24,0) -> 2.221289 | AI57: =FV($U$6,AG$42,,-$S24,0) -> 2.2879277 | AK57: =FV($U$6,AI$42,,-$S24,0) -> 2.3565655
A58: =+A25 -> 52 | C58: =+C25 -> 1 | E58: =+E25 -> x | G58: =+G25 -> x | I58: =FV($U$6,AY$9,,-$S25,0) -> 1.5579674 | K58: =FV($U$6,I$42,,-$S25,0) -> 1.6047064 | M58: =FV($U$6,K$42,,-$S25,0) -> 1.6528476 | O58: =FV($U$6,M$42,,-$S25,0) -> 1.7024331 | Q58: =FV($U$6,O$42,,-$S25,0) -> 1.7535061 | S58: =FV($U$6,Q$42,,-$S25,0) -> 1.8061112 | U58: =FV($U$6,S$42,,-$S25,0) -> 1.8602946 | W58: =FV($U$6,U$42,,-$S25,0) -> 1.9161034 | Y58: =FV($U$6,W$42,,-$S25,0) -> 1.9735865 | AA58: =FV($U$6,Y$42,,-$S25,0) -> 2.0327941 | AC58: =FV($U$6,AA$42,,-$S25,0) -> 2.0937779 | AE58: =FV($U$6,AC$42,,-$S25,0) -> 2.1565913 | AG58: =FV($U$6,AE$42,,-$S25,0) -> 2.221289 | AI58: =FV($U$6,AG$42,,-$S25,0) -> 2.2879277 | AK58: =FV($U$6,AI$42,,-$S25,0) -> 2.3565655
... A68: =+A35 -> 62 | C68: =+C35 -> 1 | E68: =+E35 -> x | G68: =+G35 -> x | I68: =FV($U$6,AY$9,,-$S35,0) -> 1.5579674 | K68: =FV($U$6,I$42,,-$S35,0) -> 1.6047064 | M68: =FV($U$6,K$42,,-$S35,0) -> 1.6528476 | O68: =FV($U$6,M$42,,-$S35,0) -> 1.7024331 | Q68: =FV($U$6,O$42,,-$S35,0) -> 1.7535061 | S68: =FV($U$6,Q$42,,-$S35,0) -> 1.8061112 | U68: =FV($U$6,S$42,,-$S35,0) -> 1.8602946 | W68: =FV($U$6,U$42,,-$S35,0) -> 1.9161034 | Y68: =FV($U$6,W$42,,-$S35,0) -> 1.9735865 | AA68: =FV($U$6,Y$42,,-$S35,0) -> 2.0327941 | AC68: =FV($U$6,AA$42,,-$S35,0) -> 2.0937779 | AE68: =FV($U$6,AC$42,,-$S35,0) -> 2.1565913 | AG68: =FV($U$6,AE$42,,-$S35,0) -> 2.221289 | AI68: =FV($U$6,AG$42,,-$S35,0) -> 2.2879277 | AK68: =FV($U$6,AI$42,,-$S35,0) -> 2.3565655
G71: =+G38 -> Anticipated Expenditures, By Year | I71: =SUM(I47:I69) -> 34.275283 | K71: =SUM(K47:K69) -> 35.303542 | M71: =SUM(M47:M69) -> 36.362648 | O71: =SUM(O47:O69) -> 37.453527 | Q71: =SUM(Q47:Q69) -> 38.577133 | S71: =SUM(S47:S69) -> 39.734447 | U71: =SUM(U47:U69) -> 40.926481 | W71: =SUM(W47:W69) -> 42.154275 | Y71: =SUM(Y47:Y69) -> 43.418903 | AA71: =SUM(AA47:AA69) -> 44.72147 | AC71: =SUM(AC47:AC69) -> 46.063114 | AE71: =SUM(AE47:AE69) -> 47.445008 | AG71: =SUM(AG47:AG69) -> 48.868358 | AI71: =SUM(AI47:AI69) -> 50.334409 | AK71: =SUM(AK47:AK69) -> 51.844441

Sheet Roofs 2
H1: Exhibit B
V2: Explanatory Notes:
H3: RESERVE EXPENDITURES | P3: RefYr | U3: 1) | V3: 0.03 | W3: is the estimated future Inflation Rate for estimating Future Replacement Costs.
H4: for | P4: ='Roofs 1'!P4 -> 2023 | U4: 2) | V4: Fiscal Year is beginning January 1 and ending December 31.
H5: ='Funding Plan'!G9 -> Association
B6: Line Item | D6: Estimated | J6: Estimated Year Last Replaced | L6: Life Analysis, Years | P6: Estimated Year of 1st Replacement | R6: 2024 Unit Cost | T6: 2024 Cost of Replacement | V6: Total Future Cost of Replacement | X6: 1 | Z6: 2 | AB6: 3 | AD6: 4 | AF6: 5 | AH6: 6 | AJ6: 7 | AL6: 8 | AN6: 9 | AP6: 10 | AR6: 11 | AT6: 12 | AV6: 13 | AX6: 14 | AZ6: 15
D7: Quantity | F7: Units | H7: Reserve Component Inventory | L7: Useful | N7: Remaining | X7: 2024 | Z7: =X7+1 -> 2025 | AA7: =Y7+1 -> 1 | AB7: =Z7+1 -> 2026 | AC7: =AA7+1 -> 2 | AD7: =AB7+1 -> 2027 | AE7: =AC7+1 -> 3 | AF7: =AD7+1 -> 2028 | AG7: =AE7+1 -> 4 | ... AZ7: =AX7+1 -> 2038
H9: Roofs
B11: 1 | D11: 1 | F11: x | H11: x | J11: 1 | K11: 23 | L11: 1 | N11: =P11-O11 -> -1999 | O11: =P4 -> 2023 | P11: =J11+K11 -> 24 | R11: 1 | T11: =D11*R11 -> 1 | V11: =SUM(X11:AZ11)+SUM(J61:AL61) -> 0 | X11: =IF(X$6=$N11,FV($V$3,$N11-1,,-$T11,0),0) -> 0 | Z11: =IF(Z$6=$N11,FV($V$3,$N11-1,,-$T11,0),0) -> 0 | AB11: =IF(AB$6=$N11,FV($V$3,$N11-1,,-$T11,0),0) -> 0 | AD11: =IF(AD$6=$N11,FV($V$3,$N11-1,,-$T11,0),0) -> 0 | AF11: =IF(AF$6=$N11,FV($V$3,$N11-1,,-$T11,0),0) -> 0 | AH11: =IF(AH$6=$N11,FV($V$3,$N11-1,,-$T11,0),0) -> 0 | AJ11: =IF(AJ$6=$N11,FV($V$3,$N11-1,,-$T11,0),0) -> 0 | AL11: =IF(AL$6=$N11,FV($V$3,$N11-1,,-$T11,0),0) -> 0 | AN11: =IF(AN$6=$N11,FV($V$3,$N11-1,,-$T11,0),0) -> 0 | AP11: =IF(AP$6=$N11,FV($V$3,$N11-1,,-$T11,0),0) -> 0 | AR11: =IF(AR$6=$N11,FV($V$3,$N11-1,,-$T11,0),0) -> 0 | AT11: =IF(AT$6=$N11,FV($V$3,$N11-1,,-$T11,0),0) -> 0 | AV11: =IF(AV$6=$N11,FV($V$3,$N11-1,,-$T11,0),0) -> 0 | AX11: =IF(AX$6=$N11,FV($V$3,$N11-1,,-$T11,0),0) -> 0 | AZ11: =IF(AZ$6=$N11,FV($V$3,$N11-1,,-$T11,0),0) -> 0
B12: =+B11+1 -> 2 | D12: 1 | F12: =F11 -> x | H12: x | J12: 1 | K12: 23 | L12: =L11 -> 1 | N12: =P12-O12 -> -1999 | O12: =O11 -> 2023 | P12: =J12+K12 -> 24 | R12: =R11 -> 1 | T12: =D12*R12 -> 1 | V12: =SUM(X12:AZ12)+SUM(J62:AL62) -> 0 | X12: =IF(X$6=$N12,FV($V$3,$N12-1,,-$T12,0),0) -> 0 | Z12: =IF(Z$6=$N12,FV($V$3,$N12-1,,-$T12,0),0) -> 0 | AB12: =IF(AB$6=$N12,FV($V$3,$N12-1,,-$T12,0),0) -> 0 | AD12: =IF(AD$6=$N12,FV($V$3,$N12-1,,-$T12,0),0) -> 0 | AF12: =IF(AF$6=$N12,FV($V$3,$N12-1,,-$T12,0),0) -> 0 | AH12: =IF(AH$6=$N12,FV($V$3,$N12-1,,-$T12,0),0) -> 0 | AJ12: =IF(AJ$6=$N12,FV($V$3,$N12-1,,-$T12,0),0) -> 0 | AL12: =IF(AL$6=$N12,FV($V$3,$N12-1,,-$T12,0),0) -> 0 | AN12: =IF(AN$6=$N12,FV($V$3,$N12-1,,-$T12,0),0) -> 0 | AP12: =IF(AP$6=$N12,FV($V$3,$N12-1,,-$T12,0),0) -> 0 | AR12: =IF(AR$6=$N12,FV($V$3,$N12-1,,-$T12,0),0) -> 0 | AT12: =IF(AT$6=$N12,FV($V$3,$N12-1,,-$T12,0),0) -> 0 | AV12: =IF(AV$6=$N12,FV($V$3,$N12-1,,-$T12,0),0) -> 0 | AX12: =IF(AX$6=$N12,FV($V$3,$N12-1,,-$T12,0),0) -> 0 | AZ12: =IF(AZ$6=$N12,FV($V$3,$N12-1,,-$T12,0),0) -> 0
B13: =+B12+1 -> 3 | D13: 1 | F13: =F12 -> x | H13: x | J13: 1 | K13: 23 | L13: =L12 -> 1 | N13: =P13-O13 -> -1999 | O13: =O12 -> 2023 | P13: =J13+K13 -> 24 | R13: =R12 -> 1 | T13: =D13*R13 -> 1 | V13: =SUM(X13:AZ13)+SUM(J63:AL63) -> 0 | X13: =IF(X$6=$N13,FV($V$3,$N13-1,,-$T13,0),0) -> 0 | Z13: =IF(Z$6=$N13,FV($V$3,$N13-1,,-$T13,0),0) -> 0 | AB13: =IF(AB$6=$N13,FV($V$3,$N13-1,,-$T13,0),0) -> 0 | AD13: =IF(AD$6=$N13,FV($V$3,$N13-1,,-$T13,0),0) -> 0 | AF13: =IF(AF$6=$N13,FV($V$3,$N13-1,,-$T13,0),0) -> 0 | AH13: =IF(AH$6=$N13,FV($V$3,$N13-1,,-$T13,0),0) -> 0 | AJ13: =IF(AJ$6=$N13,FV($V$3,$N13-1,,-$T13,0),0) -> 0 | AL13: =IF(AL$6=$N13,FV($V$3,$N13-1,,-$T13,0),0) -> 0 | AN13: =IF(AN$6=$N13,FV($V$3,$N13-1,,-$T13,0),0) -> 0 | AP13: =IF(AP$6=$N13,FV($V$3,$N13-1,,-$T13,0),0) -> 0 | AR13: =IF(AR$6=$N13,FV($V$3,$N13-1,,-$T13,0),0) -> 0 | AT13: =IF(AT$6=$N13,FV($V$3,$N13-1,,-$T13,0),0) -> 0 | AV13: =IF(AV$6=$N13,FV($V$3,$N13-1,,-$T13,0),0) -> 0 | AX13: =IF(AX$6=$N13,FV($V$3,$N13-1,,-$T13,0),0) -> 0 | AZ13: =IF(AZ$6=$N13,FV($V$3,$N13-1,,-$T13,0),0) -> 0
B14: =+B13+1 -> 4 | D14: 1 | F14: =F13 -> x | H14: x | J14: 1 | K14: 23 | L14: =L13 -> 1 | N14: =P14-O14 -> -1999 | O14: =O13 -> 2023 | P14: =J14+K14 -> 24 | R14: =R13 -> 1 | T14: =D14*R14 -> 1 | V14: =SUM(X14:AZ14)+SUM(J64:AL64) -> 0 | X14: =IF(X$6=$N14,FV($V$3,$N14-1,,-$T14,0),0) -> 0 | Z14: =IF(Z$6=$N14,FV($V$3,$N14-1,,-$T14,0),0) -> 0 | AB14: =IF(AB$6=$N14,FV($V$3,$N14-1,,-$T14,0),0) -> 0 | AD14: =IF(AD$6=$N14,FV($V$3,$N14-1,,-$T14,0),0) -> 0 | AF14: =IF(AF$6=$N14,FV($V$3,$N14-1,,-$T14,0),0) -> 0 | AH14: =IF(AH$6=$N14,FV($V$3,$N14-1,,-$T14,0),0) -> 0 | AJ14: =IF(AJ$6=$N14,FV($V$3,$N14-1,,-$T14,0),0) -> 0 | AL14: =IF(AL$6=$N14,FV($V$3,$N14-1,,-$T14,0),0) -> 0 | AN14: =IF(AN$6=$N14,FV($V$3,$N14-1,,-$T14,0),0) -> 0 | AP14: =IF(AP$6=$N14,FV($V$3,$N14-1,,-$T14,0),0) -> 0 | AR14: =IF(AR$6=$N14,FV($V$3,$N14-1,,-$T14,0),0) -> 0 | AT14: =IF(AT$6=$N14,FV($V$3,$N14-1,,-$T14,0),0) -> 0 | AV14: =IF(AV$6=$N14,FV($V$3,$N14-1,,-$T14,0),0) -> 0 | AX14: =IF(AX$6=$N14,FV($V$3,$N14-1,,-$T14,0),0) -> 0 | AZ14: =IF(AZ$6=$N14,FV($V$3,$N14-1,,-$T14,0),0) -> 0
B15: =+B14+1 -> 5 | D15: 1 | F15: =F14 -> x | H15: x | J15: 1 | K15: 23 | L15: =L14 -> 1 | N15: =P15-O15 -> -1999 | O15: =O14 -> 2023 | P15: =J15+K15 -> 24 | R15: =R14 -> 1 | T15: =D15*R15 -> 1 | V15: =SUM(X15:AZ15)+SUM(J65:AL65) -> 0 | X15: =IF(X$6=$N15,FV($V$3,$N15-1,,-$T15,0),0) -> 0 | Z15: =IF(Z$6=$N15,FV($V$3,$N15-1,,-$T15,0),0) -> 0 | AB15: =IF(AB$6=$N15,FV($V$3,$N15-1,,-$T15,0),0) -> 0 | AD15: =IF(AD$6=$N15,FV($V$3,$N15-1,,-$T15,0),0) -> 0 | AF15: =IF(AF$6=$N15,FV($V$3,$N15-1,,-$T15,0),0) -> 0 | AH15: =IF(AH$6=$N15,FV($V$3,$N15-1,,-$T15,0),0) -> 0 | AJ15: =IF(AJ$6=$N15,FV($V$3,$N15-1,,-$T15,0),0) -> 0 | AL15: =IF(AL$6=$N15,FV($V$3,$N15-1,,-$T15,0),0) -> 0 | AN15: =IF(AN$6=$N15,FV($V$3,$N15-1,,-$T15,0),0) -> 0 | AP15: =IF(AP$6=$N15,FV($V$3,$N15-1,,-$T15,0),0) -> 0 | AR15: =IF(AR$6=$N15,FV($V$3,$N15-1,,-$T15,0),0) -> 0 | AT15: =IF(AT$6=$N15,FV($V$3,$N15-1,,-$T15,0),0) -> 0 | AV15: =IF(AV$6=$N15,FV($V$3,$N15-1,,-$T15,0),0) -> 0 | AX15: =IF(AX$6=$N15,FV($V$3,$N15-1,,-$T15,0),0) -> 0 | AZ15: =IF(AZ$6=$N15,FV($V$3,$N15-1,,-$T15,0),0) -> 0
B16: =+B15+1 -> 6 | D16: 1 | F16: =F15 -> x | H16: x | J16: 1 | K16: 23 | L16: =L15 -> 1 | N16: =P16-O16 -> -1999 | O16: =O15 -> 2023 | P16: =J16+K16 -> 24 | R16: =R15 -> 1 | T16: =D16*R16 -> 1 | V16: =SUM(X16:AZ16)+SUM(J66:AL66) -> 0 | X16: =IF(X$6=$N16,FV($V$3,$N16-1,,-$T16,0),0) -> 0 | Z16: =IF(Z$6=$N16,FV($V$3,$N16-1,,-$T16,0),0) -> 0 | AB16: =IF(AB$6=$N16,FV($V$3,$N16-1,,-$T16,0),0) -> 0 | AD16: =IF(AD$6=$N16,FV($V$3,$N16-1,,-$T16,0),0) -> 0 | AF16: =IF(AF$6=$N16,FV($V$3,$N16-1,,-$T16,0),0) -> 0 | AH16: =IF(AH$6=$N16,FV($V$3,$N16-1,,-$T16,0),0) -> 0 | AJ16: =IF(AJ$6=$N16,FV($V$3,$N16-1,,-$T16,0),0) -> 0 | AL16: =IF(AL$6=$N16,FV($V$3,$N16-1,,-$T16,0),0) -> 0 | AN16: =IF(AN$6=$N16,FV($V$3,$N16-1,,-$T16,0),0) -> 0 | AP16: =IF(AP$6=$N16,FV($V$3,$N16-1,,-$T16,0),0) -> 0 | AR16: =IF(AR$6=$N16,FV($V$3,$N16-1,,-$T16,0),0) -> 0 | AT16: =IF(AT$6=$N16,FV($V$3,$N16-1,,-$T16,0),0) -> 0 | AV16: =IF(AV$6=$N16,FV($V$3,$N16-1,,-$T16,0),0) -> 0 | AX16: =IF(AX$6=$N16,FV($V$3,$N16-1,,-$T16,0),0) -> 0 | AZ16: =IF(AZ$6=$N16,FV($V$3,$N16-1,,-$T16,0),0) -> 0
B17: =+B16+1 -> 7 | D17: 1 | F17: =F16 -> x | H17: x | J17: 1 | K17: 23 | L17: =L16 -> 1 | N17: =P17-O17 -> -1999 | O17: =O16 -> 2023 | P17: =J17+K17 -> 24 | R17: =R16 -> 1 | T17: =D17*R17 -> 1 | V17: =SUM(X17:AZ17)+SUM(J67:AL67) -> 0 | X17: =IF(X$6=$N17,FV($V$3,$N17-1,,-$T17,0),0) -> 0 | Z17: =IF(Z$6=$N17,FV($V$3,$N17-1,,-$T17,0),0) -> 0 | AB17: =IF(AB$6=$N17,FV($V$3,$N17-1,,-$T17,0),0) -> 0 | AD17: =IF(AD$6=$N17,FV($V$3,$N17-1,,-$T17,0),0) -> 0 | AF17: =IF(AF$6=$N17,FV($V$3,$N17-1,,-$T17,0),0) -> 0 | AH17: =IF(AH$6=$N17,FV($V$3,$N17-1,,-$T17,0),0) -> 0 | AJ17: =IF(AJ$6=$N17,FV($V$3,$N17-1,,-$T17,0),0) -> 0 | AL17: =IF(AL$6=$N17,FV($V$3,$N17-1,,-$T17,0),0) -> 0 | AN17: =IF(AN$6=$N17,FV($V$3,$N17-1,,-$T17,0),0) -> 0 | AP17: =IF(AP$6=$N17,FV($V$3,$N17-1,,-$T17,0),0) -> 0 | AR17: =IF(AR$6=$N17,FV($V$3,$N17-1,,-$T17,0),0) -> 0 | AT17: =IF(AT$6=$N17,FV($V$3,$N17-1,,-$T17,0),0) -> 0 | AV17: =IF(AV$6=$N17,FV($V$3,$N17-1,,-$T17,0),0) -> 0 | AX17: =IF(AX$6=$N17,FV($V$3,$N17-1,,-$T17,0),0) -> 0 | AZ17: =IF(AZ$6=$N17,FV($V$3,$N17-1,,-$T17,0),0) -> 0
B18: =+B17+1 -> 8 | D18: 1 | F18: =F17 -> x | H18: x | J18: 1 | K18: 23 | L18: =L17 -> 1 | N18: =P18-O18 -> -1999 | O18: =O17 -> 2023 | P18: =J18+K18 -> 24 | R18: =R17 -> 1 | T18: =D18*R18 -> 1 | V18: =SUM(X18:AZ18)+SUM(J68:AL68) -> 0 | X18: =IF(X$6=$N18,FV($V$3,$N18-1,,-$T18,0),0) -> 0 | Z18: =IF(Z$6=$N18,FV($V$3,$N18-1,,-$T18,0),0) -> 0 | AB18: =IF(AB$6=$N18,FV($V$3,$N18-1,,-$T18,0),0) -> 0 | AD18: =IF(AD$6=$N18,FV($V$3,$N18-1,,-$T18,0),0) -> 0 | AF18: =IF(AF$6=$N18,FV($V$3,$N18-1,,-$T18,0),0) -> 0 | AH18: =IF(AH$6=$N18,FV($V$3,$N18-1,,-$T18,0),0) -> 0 | AJ18: =IF(AJ$6=$N18,FV($V$3,$N18-1,,-$T18,0),0) -> 0 | AL18: =IF(AL$6=$N18,FV($V$3,$N18-1,,-$T18,0),0) -> 0 | AN18: =IF(AN$6=$N18,FV($V$3,$N18-1,,-$T18,0),0) -> 0 | AP18: =IF(AP$6=$N18,FV($V$3,$N18-1,,-$T18,0),0) -> 0 | AR18: =IF(AR$6=$N18,FV($V$3,$N18-1,,-$T18,0),0) -> 0 | AT18: =IF(AT$6=$N18,FV($V$3,$N18-1,,-$T18,0),0) -> 0 | AV18: =IF(AV$6=$N18,FV($V$3,$N18-1,,-$T18,0),0) -> 0 | AX18: =IF(AX$6=$N18,FV($V$3,$N18-1,,-$T18,0),0) -> 0 | AZ18: =IF(AZ$6=$N18,FV($V$3,$N18-1,,-$T18,0),0) -> 0
B19: =+B18+1 -> 9 | D19: 1 | F19: =F18 -> x | H19: x | J19: 1 | K19: 23 | L19: =L18 -> 1 | N19: =P19-O19 -> -1999 | O19: =O18 -> 2023 | P19: =J19+K19 -> 24 | R19: =R18 -> 1 | T19: =D19*R19 -> 1 | V19: =SUM(X19:AZ19)+SUM(J69:AL69) -> 0 | X19: =IF(X$6=$N19,FV($V$3,$N19-1,,-$T19,0),0) -> 0 | Z19: =IF(Z$6=$N19,FV($V$3,$N19-1,,-$T19,0),0) -> 0 | AB19: =IF(AB$6=$N19,FV($V$3,$N19-1,,-$T19,0),0) -> 0 | AD19: =IF(AD$6=$N19,FV($V$3,$N19-1,,-$T19,0),0) -> 0 | AF19: =IF(AF$6=$N19,FV($V$3,$N19-1,,-$T19,0),0) -> 0 | AH19: =IF(AH$6=$N19,FV($V$3,$N19-1,,-$T19,0),0) -> 0 | AJ19: =IF(AJ$6=$N19,FV($V$3,$N19-1,,-$T19,0),0) -> 0 | AL19: =IF(AL$6=$N19,FV($V$3,$N19-1,,-$T19,0),0) -> 0 | AN19: =IF(AN$6=$N19,FV($V$3,$N19-1,,-$T19,0),0) -> 0 | AP19: =IF(AP$6=$N19,FV($V$3,$N19-1,,-$T19,0),0) -> 0 | AR19: =IF(AR$6=$N19,FV($V$3,$N19-1,,-$T19,0),0) -> 0 | AT19: =IF(AT$6=$N19,FV($V$3,$N19-1,,-$T19,0),0) -> 0 | AV19: =IF(AV$6=$N19,FV($V$3,$N19-1,,-$T19,0),0) -> 0 | AX19: =IF(AX$6=$N19,FV($V$3,$N19-1,,-$T19,0),0) -> 0 | AZ19: =IF(AZ$6=$N19,FV($V$3,$N19-1,,-$T19,0),0) -> 0
B20: =+B19+1 -> 10 | D20: 1 | F20: =F19 -> x | H20: x | J20: 1 | K20: 23 | L20: =L19 -> 1 | N20: =P20-O20 -> -1999 | O20: =O19 -> 2023 | P20: =J20+K20 -> 24 | R20: =R19 -> 1 | T20: =D20*R20 -> 1 | V20: =SUM(X20:AZ20)+SUM(J70:AL70) -> 0 | X20: =IF(X$6=$N20,FV($V$3,$N20-1,,-$T20,0),0) -> 0 | Z20: =IF(Z$6=$N20,FV($V$3,$N20-1,,-$T20,0),0) -> 0 | AB20: =IF(AB$6=$N20,FV($V$3,$N20-1,,-$T20,0),0) -> 0 | AD20: =IF(AD$6=$N20,FV($V$3,$N20-1,,-$T20,0),0) -> 0 | AF20: =IF(AF$6=$N20,FV($V$3,$N20-1,,-$T20,0),0) -> 0 | AH20: =IF(AH$6=$N20,FV($V$3,$N20-1,,-$T20,0),0) -> 0 | AJ20: =IF(AJ$6=$N20,FV($V$3,$N20-1,,-$T20,0),0) -> 0 | AL20: =IF(AL$6=$N20,FV($V$3,$N20-1,,-$T20,0),0) -> 0 | AN20: =IF(AN$6=$N20,FV($V$3,$N20-1,,-$T20,0),0) -> 0 | AP20: =IF(AP$6=$N20,FV($V$3,$N20-1,,-$T20,0),0) -> 0 | AR20: =IF(AR$6=$N20,FV($V$3,$N20-1,,-$T20,0),0) -> 0 | AT20: =IF(AT$6=$N20,FV($V$3,$N20-1,,-$T20,0),0) -> 0 | AV20: =IF(AV$6=$N20,FV($V$3,$N20-1,,-$T20,0),0) -> 0 | AX20: =IF(AX$6=$N20,FV($V$3,$N20-1,,-$T20,0),0) -> 0 | AZ20: =IF(AZ$6=$N20,FV($V$3,$N20-1,,-$T20,0),0) -> 0
B21: =+B20+1 -> 11 | D21: 1 | F21: =F20 -> x | H21: x | J21: 1 | K21: 23 | L21: =L20 -> 1 | N21: =P21-O21 -> -1999 | O21: =O20 -> 2023 | P21: =J21+K21 -> 24 | R21: =R20 -> 1 | T21: =D21*R21 -> 1 | V21: =SUM(X21:AZ21)+SUM(J71:AL71) -> 0 | X21: =IF(X$6=$N21,FV($V$3,$N21-1,,-$T21,0),0) -> 0 | Z21: =IF(Z$6=$N21,FV($V$3,$N21-1,,-$T21,0),0) -> 0 | AB21: =IF(AB$6=$N21,FV($V$3,$N21-1,,-$T21,0),0) -> 0 | AD21: =IF(AD$6=$N21,FV($V$3,$N21-1,,-$T21,0),0) -> 0 | AF21: =IF(AF$6=$N21,FV($V$3,$N21-1,,-$T21,0),0) -> 0 | AH21: =IF(AH$6=$N21,FV($V$3,$N21-1,,-$T21,0),0) -> 0 | AJ21: =IF(AJ$6=$N21,FV($V$3,$N21-1,,-$T21,0),0) -> 0 | AL21: =IF(AL$6=$N21,FV($V$3,$N21-1,,-$T21,0),0) -> 0 | AN21: =IF(AN$6=$N21,FV($V$3,$N21-1,,-$T21,0),0) -> 0 | AP21: =IF(AP$6=$N21,FV($V$3,$N21-1,,-$T21,0),0) -> 0 | AR21: =IF(AR$6=$N21,FV($V$3,$N21-1,,-$T21,0),0) -> 0 | AT21: =IF(AT$6=$N21,FV($V$3,$N21-1,,-$T21,0),0) -> 0 | AV21: =IF(AV$6=$N21,FV($V$3,$N21-1,,-$T21,0),0) -> 0 | AX21: =IF(AX$6=$N21,FV($V$3,$N21-1,,-$T21,0),0) -> 0 | AZ21: =IF(AZ$6=$N21,FV($V$3,$N21-1,,-$T21,0),0) -> 0
B22: =+B21+1 -> 12 | D22: 1 | F22: =F21 -> x | H22: x | J22: 1 | K22: 23 | L22: =L21 -> 1 | N22: =P22-O22 -> -1999 | O22: =O21 -> 2023 | P22: =J22+K22 -> 24 | R22: =R21 -> 1 | T22: =D22*R22 -> 1 | V22: =SUM(X22:AZ22)+SUM(J72:AL72) -> 0 | X22: =IF(X$6=$N22,FV($V$3,$N22-1,,-$T22,0),0) -> 0 | Z22: =IF(Z$6=$N22,FV($V$3,$N22-1,,-$T22,0),0) -> 0 | AB22: =IF(AB$6=$N22,FV($V$3,$N22-1,,-$T22,0),0) -> 0 | AD22: =IF(AD$6=$N22,FV($V$3,$N22-1,,-$T22,0),0) -> 0 | AF22: =IF(AF$6=$N22,FV($V$3,$N22-1,,-$T22,0),0) -> 0 | AH22: =IF(AH$6=$N22,FV($V$3,$N22-1,,-$T22,0),0) -> 0 | AJ22: =IF(AJ$6=$N22,FV($V$3,$N22-1,,-$T22,0),0) -> 0 | AL22: =IF(AL$6=$N22,FV($V$3,$N22-1,,-$T22,0),0) -> 0 | AN22: =IF(AN$6=$N22,FV($V$3,$N22-1,,-$T22,0),0) -> 0 | AP22: =IF(AP$6=$N22,FV($V$3,$N22-1,,-$T22,0),0) -> 0 | AR22: =IF(AR$6=$N22,FV($V$3,$N22-1,,-$T22,0),0) -> 0 | AT22: =IF(AT$6=$N22,FV($V$3,$N22-1,,-$T22,0),0) -> 0 | AV22: =IF(AV$6=$N22,FV($V$3,$N22-1,,-$T22,0),0) -> 0 | AX22: =IF(AX$6=$N22,FV($V$3,$N22-1,,-$T22,0),0) -> 0 | AZ22: =IF(AZ$6=$N22,FV($V$3,$N22-1,,-$T22,0),0) -> 0
B23: =+B22+1 -> 13 | D23: 1 | F23: =F22 -> x | H23: x | J23: 1 | K23: 23 | L23: =L22 -> 1 | N23: =P23-O23 -> -1999 | O23: =O22 -> 2023 | P23: =J23+K23 -> 24 | R23: =R22 -> 1 | T23: =D23*R23 -> 1 | V23: =SUM(X23:AZ23)+SUM(J73:AL73) -> 0 | X23: =IF(X$6=$N23,FV($V$3,$N23-1,,-$T23,0),0) -> 0 | Z23: =IF(Z$6=$N23,FV($V$3,$N23-1,,-$T23,0),0) -> 0 | AB23: =IF(AB$6=$N23,FV($V$3,$N23-1,,-$T23,0),0) -> 0 | AD23: =IF(AD$6=$N23,FV($V$3,$N23-1,,-$T23,0),0) -> 0 | AF23: =IF(AF$6=$N23,FV($V$3,$N23-1,,-$T23,0),0) -> 0 | AH23: =IF(AH$6=$N23,FV($V$3,$N23-1,,-$T23,0),0) -> 0 | AJ23: =IF(AJ$6=$N23,FV($V$3,$N23-1,,-$T23,0),0) -> 0 | AL23: =IF(AL$6=$N23,FV($V$3,$N23-1,,-$T23,0),0) -> 0 | AN23: =IF(AN$6=$N23,FV($V$3,$N23-1,,-$T23,0),0) -> 0 | AP23: =IF(AP$6=$N23,FV($V$3,$N23-1,,-$T23,0),0) -> 0 | AR23: =IF(AR$6=$N23,FV($V$3,$N23-1,,-$T23,0),0) -> 0 | AT23: =IF(AT$6=$N23,FV($V$3,$N23-1,,-$T23,0),0) -> 0 | AV23: =IF(AV$6=$N23,FV($V$3,$N23-1,,-$T23,0),0) -> 0 | AX23: =IF(AX$6=$N23,FV($V$3,$N23-1,,-$T23,0),0) -> 0 | AZ23: =IF(AZ$6=$N23,FV($V$3,$N23-1,,-$T23,0),0) -> 0
... B50: =+B49+1 -> 40 | D50: 1 | F50: =F49 -> x | H50: x | J50: 1 | K50: 23 | L50: =L49 -> 1 | N50: =P50-O50 -> -1999 | O50: =O49 -> 2023 | P50: =J50+K50 -> 24 | R50: =R49 -> 1 | T50: =D50*R50 -> 1 | V50: =SUM(X50:AZ50)+SUM(J100:AL100) -> 0 | X50: =IF(X$6=$N50,FV($V$3,$N50-1,,-$T50,0),0) -> 0 | Z50: =IF(Z$6=$N50,FV($V$3,$N50-1,,-$T50,0),0) -> 0 | AB50: =IF(AB$6=$N50,FV($V$3,$N50-1,,-$T50,0),0) -> 0 | AD50: =IF(AD$6=$N50,FV($V$3,$N50-1,,-$T50,0),0) -> 0 | AF50: =IF(AF$6=$N50,FV($V$3,$N50-1,,-$T50,0),0) -> 0 | AH50: =IF(AH$6=$N50,FV($V$3,$N50-1,,-$T50,0),0) -> 0 | AJ50: =IF(AJ$6=$N50,FV($V$3,$N50-1,,-$T50,0),0) -> 0 | AL50: =IF(AL$6=$N50,FV($V$3,$N50-1,,-$T50,0),0) -> 0 | AN50: =IF(AN$6=$N50,FV($V$3,$N50-1,,-$T50,0),0) -> 0 | AP50: =IF(AP$6=$N50,FV($V$3,$N50-1,,-$T50,0),0) -> 0 | AR50: =IF(AR$6=$N50,FV($V$3,$N50-1,,-$T50,0),0) -> 0 | AT50: =IF(AT$6=$N50,FV($V$3,$N50-1,,-$T50,0),0) -> 0 | AV50: =IF(AV$6=$N50,FV($V$3,$N50-1,,-$T50,0),0) -> 0 | AX50: =IF(AX$6=$N50,FV($V$3,$N50-1,,-$T50,0),0) -> 0 | AZ50: =IF(AZ$6=$N50,FV($V$3,$N50-1,,-$T50,0),0) -> 0
H52: Anticipated Expenditures, By Year | T52: =SUM(T11:T50) -> 40 | V52: =SUM(V11:V50) -> 0 | X52: =SUM(X11:X50) -> 0 | Z52: =SUM(Z11:Z50) -> 0 | AB52: =SUM(AB11:AB50) -> 0 | AD52: =SUM(AD11:AD50) -> 0 | AF52: =SUM(AF11:AF50) -> 0 | AH52: =SUM(AH11:AH50) -> 0 | AJ52: =SUM(AJ11:AJ50) -> 0 | AL52: =SUM(AL11:AL50) -> 0 | AN52: =SUM(AN11:AN50) -> 0 | AP52: =SUM(AP11:AP50) -> 0 | AR52: =SUM(AR11:AR50) -> 0 | AT52: =SUM(AT11:AT50) -> 0 | AV52: =SUM(AV11:AV50) -> 0 | AX52: =SUM(AX11:AX50) -> 0 | AZ52: =SUM(AZ11:AZ50) -> 0
B56: Line Item | J56: 16 | L56: 17 | N56: 18 | P56: 19 | R56: 20 | T56: =+R56+1 -> 21 | V56: =+T56+1 -> 22 | X56: =+V56+1 -> 23 | Z56: =+X56+1 -> 24 | AB56: =+Z56+1 -> 25 | AD56: =+AB56+1 -> 26 | AF56: =+AD56+1 -> 27 | AH56: =+AF56+1 -> 28 | AJ56: =+AH56+1 -> 29 | AL56: =+AJ56+1 -> 30
D57: Quantity | F57: Units | H57: Reserve Component Inventory | J57: =AZ7+1 -> 2039 | K57: =BA7+1 -> 1 | L57: =J57+1 -> 2040 | M57: =K57+1 -> 2 | N57: =L57+1 -> 2041 | O57: =M57+1 -> 3 | P57: =N57+1 -> 2042 | Q57: =O57+1 -> 4 | R57: =P57+1 -> 2043 | T57: =+R57+1 -> 2044 | U57: =S57+1 -> 1 | V57: =T57+1 -> 2045 | W57: =U57+1 -> 2 | X57: =V57+1 -> 2046 | Y57: =W57+1 -> 3 | Z57: =X57+1 -> 2047 | AA57: =Y57+1 -> 4 | AB57: =Z57+1 -> 2048 | AD57: =AB57+1 -> 2049 | AF57: =AD57+1 -> 2050 | AH57: =AF57+1 -> 2051 | AJ57: =AH57+1 -> 2052 | AL57: =AJ57+1 -> 2053
H59: =+H9 -> Roofs
B61: =+B11 -> 1 | D61: =+D11 -> 1 | F61: =+F11 -> x | H61: =+H11 -> x | J61: =IF(J$56=$N11,FV($V$3,$N11-1,,-$T11,0),0) -> 0 | L61: =IF(L$56=$N11,FV($V$3,$N11-1,,-$T11,0),0) -> 0 | N61: =IF(N$56=$N11,FV($V$3,$N11-1,,-$T11,0),0) -> 0 | P61: =IF(P$56=$N11,FV($V$3,$N11-1,,-$T11,0),0) -> 0 | R61: =IF(R$56=$N11,FV($V$3,$N11-1,,-$T11,0),0) -> 0 | T61: =IF(T$56=$N11,FV($V$3,$N11-1,,-$T11,0),0) -> 0 | V61: =IF(V$56=$N11,FV($V$3,$N11-1,,-$T11,0),0) -> 0 | X61: =IF(X$56=$N11,FV($V$3,$N11-1,,-$T11,0),0) -> 0 | Z61: =IF(Z$56=$N11,FV($V$3,$N11-1,,-$T11,0),0) -> 0 | AB61: =IF(AB$56=$N11,FV($V$3,$N11-1,,-$T11,0),0) -> 0 | AD61: =IF(AD$56=$N11,FV($V$3,$N11-1,,-$T11,0),0) -> 0 | AF61: =IF(AF$56=$N11,FV($V$3,$N11-1,,-$T11,0),0) -> 0 | AH61: =IF(AH$56=$N11,FV($V$3,$N11-1,,-$T11,0),0) -> 0 | AJ61: =IF(AJ$56=$N11,FV($V$3,$N11-1,,-$T11,0),0) -> 0 | AL61: =IF(AL$56=$N11,FV($V$3,$N11-1,,-$T11,0),0) -> 0
B62: =+B12 -> 2 | D62: =+D12 -> 1 | F62: =+F12 -> x | H62: =+H12 -> x | J62: =IF(J$56=$N12,FV($V$3,$N12-1,,-$T12,0),0) -> 0 | L62: =IF(L$56=$N12,FV($V$3,$N12-1,,-$T12,0),0) -> 0 | N62: =IF(N$56=$N12,FV($V$3,$N12-1,,-$T12,0),0) -> 0 | P62: =IF(P$56=$N12,FV($V$3,$N12-1,,-$T12,0),0) -> 0 | R62: =IF(R$56=$N12,FV($V$3,$N12-1,,-$T12,0),0) -> 0 | T62: =IF(T$56=$N12,FV($V$3,$N12-1,,-$T12,0),0) -> 0 | V62: =IF(V$56=$N12,FV($V$3,$N12-1,,-$T12,0),0) -> 0 | X62: =IF(X$56=$N12,FV($V$3,$N12-1,,-$T12,0),0) -> 0 | Z62: =IF(Z$56=$N12,FV($V$3,$N12-1,,-$T12,0),0) -> 0 | AB62: =IF(AB$56=$N12,FV($V$3,$N12-1,,-$T12,0),0) -> 0 | AD62: =IF(AD$56=$N12,FV($V$3,$N12-1,,-$T12,0),0) -> 0 | AF62: =IF(AF$56=$N12,FV($V$3,$N12-1,,-$T12,0),0) -> 0 | AH62: =IF(AH$56=$N12,FV($V$3,$N12-1,,-$T12,0),0) -> 0 | AJ62: =IF(AJ$56=$N12,FV($V$3,$N12-1,,-$T12,0),0) -> 0 | AL62: =IF(AL$56=$N12,FV($V$3,$N12-1,,-$T12,0),0) -> 0
B63: =+B13 -> 3 | D63: =+D13 -> 1 | F63: =+F13 -> x | H63: =+H13 -> x | J63: =IF(J$56=$N13,FV($V$3,$N13-1,,-$T13,0),0) -> 0 | L63: =IF(L$56=$N13,FV($V$3,$N13-1,,-$T13,0),0) -> 0 | N63: =IF(N$56=$N13,FV($V$3,$N13-1,,-$T13,0),0) -> 0 | P63: =IF(P$56=$N13,FV($V$3,$N13-1,,-$T13,0),0) -> 0 | R63: =IF(R$56=$N13,FV($V$3,$N13-1,,-$T13,0),0) -> 0 | T63: =IF(T$56=$N13,FV($V$3,$N13-1,,-$T13,0),0) -> 0 | V63: =IF(V$56=$N13,FV($V$3,$N13-1,,-$T13,0),0) -> 0 | X63: =IF(X$56=$N13,FV($V$3,$N13-1,,-$T13,0),0) -> 0 | Z63: =IF(Z$56=$N13,FV($V$3,$N13-1,,-$T13,0),0) -> 0 | AB63: =IF(AB$56=$N13,FV($V$3,$N13-1,,-$T13,0),0) -> 0 | AD63: =IF(AD$56=$N13,FV($V$3,$N13-1,,-$T13,0),0) -> 0 | AF63: =IF(AF$56=$N13,FV($V$3,$N13-1,,-$T13,0),0) -> 0 | AH63: =IF(AH$56=$N13,FV($V$3,$N13-1,,-$T13,0),0) -> 0 | AJ63: =IF(AJ$56=$N13,FV($V$3,$N13-1,,-$T13,0),0) -> 0 | AL63: =IF(AL$56=$N13,FV($V$3,$N13-1,,-$T13,0),0) -> 0
B64: =+B14 -> 4 | D64: =+D14 -> 1 | F64: =+F14 -> x | H64: =+H14 -> x | J64: =IF(J$56=$N14,FV($V$3,$N14-1,,-$T14,0),0) -> 0 | L64: =IF(L$56=$N14,FV($V$3,$N14-1,,-$T14,0),0) -> 0 | N64: =IF(N$56=$N14,FV($V$3,$N14-1,,-$T14,0),0) -> 0 | P64: =IF(P$56=$N14,FV($V$3,$N14-1,,-$T14,0),0) -> 0 | R64: =IF(R$56=$N14,FV($V$3,$N14-1,,-$T14,0),0) -> 0 | T64: =IF(T$56=$N14,FV($V$3,$N14-1,,-$T14,0),0) -> 0 | V64: =IF(V$56=$N14,FV($V$3,$N14-1,,-$T14,0),0) -> 0 | X64: =IF(X$56=$N14,FV($V$3,$N14-1,,-$T14,0),0) -> 0 | Z64: =IF(Z$56=$N14,FV($V$3,$N14-1,,-$T14,0),0) -> 0 | AB64: =IF(AB$56=$N14,FV($V$3,$N14-1,,-$T14,0),0) -> 0 | AD64: =IF(AD$56=$N14,FV($V$3,$N14-1,,-$T14,0),0) -> 0 | AF64: =IF(AF$56=$N14,FV($V$3,$N14-1,,-$T14,0),0) -> 0 | AH64: =IF(AH$56=$N14,FV($V$3,$N14-1,,-$T14,0),0) -> 0 | AJ64: =IF(AJ$56=$N14,FV($V$3,$N14-1,,-$T14,0),0) -> 0 | AL64: =IF(AL$56=$N14,FV($V$3,$N14-1,,-$T14,0),0) -> 0
B65: =+B15 -> 5 | D65: =+D15 -> 1 | F65: =+F15 -> x | H65: =+H15 -> x | J65: =IF(J$56=$N15,FV($V$3,$N15-1,,-$T15,0),0) -> 0 | L65: =IF(L$56=$N15,FV($V$3,$N15-1,,-$T15,0),0) -> 0 | N65: =IF(N$56=$N15,FV($V$3,$N15-1,,-$T15,0),0) -> 0 | P65: =IF(P$56=$N15,FV($V$3,$N15-1,,-$T15,0),0) -> 0 | R65: =IF(R$56=$N15,FV($V$3,$N15-1,,-$T15,0),0) -> 0 | T65: =IF(T$56=$N15,FV($V$3,$N15-1,,-$T15,0),0) -> 0 | V65: =IF(V$56=$N15,FV($V$3,$N15-1,,-$T15,0),0) -> 0 | X65: =IF(X$56=$N15,FV($V$3,$N15-1,,-$T15,0),0) -> 0 | Z65: =IF(Z$56=$N15,FV($V$3,$N15-1,,-$T15,0),0) -> 0 | AB65: =IF(AB$56=$N15,FV($V$3,$N15-1,,-$T15,0),0) -> 0 | AD65: =IF(AD$56=$N15,FV($V$3,$N15-1,,-$T15,0),0) -> 0 | AF65: =IF(AF$56=$N15,FV($V$3,$N15-1,,-$T15,0),0) -> 0 | AH65: =IF(AH$56=$N15,FV($V$3,$N15-1,,-$T15,0),0) -> 0 | AJ65: =IF(AJ$56=$N15,FV($V$3,$N15-1,,-$T15,0),0) -> 0 | AL65: =IF(AL$56=$N15,FV($V$3,$N15-1,,-$T15,0),0) -> 0
B66: =+B16 -> 6 | D66: =+D16 -> 1 | F66: =+F16 -> x | H66: =+H16 -> x | J66: =IF(J$56=$N16,FV($V$3,$N16-1,,-$T16,0),0) -> 0 | L66: =IF(L$56=$N16,FV($V$3,$N16-1,,-$T16,0),0) -> 0 | N66: =IF(N$56=$N16,FV($V$3,$N16-1,,-$T16,0),0) -> 0 | P66: =IF(P$56=$N16,FV($V$3,$N16-1,,-$T16,0),0) -> 0 | R66: =IF(R$56=$N16,FV($V$3,$N16-1,,-$T16,0),0) -> 0 | T66: =IF(T$56=$N16,FV($V$3,$N16-1,,-$T16,0),0) -> 0 | V66: =IF(V$56=$N16,FV($V$3,$N16-1,,-$T16,0),0) -> 0 | X66: =IF(X$56=$N16,FV($V$3,$N16-1,,-$T16,0),0) -> 0 | Z66: =IF(Z$56=$N16,FV($V$3,$N16-1,,-$T16,0),0) -> 0 | AB66: =IF(AB$56=$N16,FV($V$3,$N16-1,,-$T16,0),0) -> 0 | AD66: =IF(AD$56=$N16,FV($V$3,$N16-1,,-$T16,0),0) -> 0 | AF66: =IF(AF$56=$N16,FV($V$3,$N16-1,,-$T16,0),0) -> 0 | AH66: =IF(AH$56=$N16,FV($V$3,$N16-1,,-$T16,0),0) -> 0 | AJ66: =IF(AJ$56=$N16,FV($V$3,$N16-1,,-$T16,0),0) -> 0 | AL66: =IF(AL$56=$N16,FV($V$3,$N16-1,,-$T16,0),0) -> 0
B67: =+B17 -> 7 | D67: =+D17 -> 1 | F67: =+F17 -> x | H67: =+H17 -> x | J67: =IF(J$56=$N17,FV($V$3,$N17-1,,-$T17,0),0) -> 0 | L67: =IF(L$56=$N17,FV($V$3,$N17-1,,-$T17,0),0) -> 0 | N67: =IF(N$56=$N17,FV($V$3,$N17-1,,-$T17,0),0) -> 0 | P67: =IF(P$56=$N17,FV($V$3,$N17-1,,-$T17,0),0) -> 0 | R67: =IF(R$56=$N17,FV($V$3,$N17-1,,-$T17,0),0) -> 0 | T67: =IF(T$56=$N17,FV($V$3,$N17-1,,-$T17,0),0) -> 0 | V67: =IF(V$56=$N17,FV($V$3,$N17-1,,-$T17,0),0) -> 0 | X67: =IF(X$56=$N17,FV($V$3,$N17-1,,-$T17,0),0) -> 0 | Z67: =IF(Z$56=$N17,FV($V$3,$N17-1,,-$T17,0),0) -> 0 | AB67: =IF(AB$56=$N17,FV($V$3,$N17-1,,-$T17,0),0) -> 0 | AD67: =IF(AD$56=$N17,FV($V$3,$N17-1,,-$T17,0),0) -> 0 | AF67: =IF(AF$56=$N17,FV($V$3,$N17-1,,-$T17,0),0) -> 0 | AH67: =IF(AH$56=$N17,FV($V$3,$N17-1,,-$T17,0),0) -> 0 | AJ67: =IF(AJ$56=$N17,FV($V$3,$N17-1,,-$T17,0),0) -> 0 | AL67: =IF(AL$56=$N17,FV($V$3,$N17-1,,-$T17,0),0) -> 0
B68: =+B18 -> 8 | D68: =+D18 -> 1 | F68: =+F18 -> x | H68: =+H18 -> x | J68: =IF(J$56=$N18,FV($V$3,$N18-1,,-$T18,0),0) -> 0 | L68: =IF(L$56=$N18,FV($V$3,$N18-1,,-$T18,0),0) -> 0 | N68: =IF(N$56=$N18,FV($V$3,$N18-1,,-$T18,0),0) -> 0 | P68: =IF(P$56=$N18,FV($V$3,$N18-1,,-$T18,0),0) -> 0 | R68: =IF(R$56=$N18,FV($V$3,$N18-1,,-$T18,0),0) -> 0 | T68: =IF(T$56=$N18,FV($V$3,$N18-1,,-$T18,0),0) -> 0 | V68: =IF(V$56=$N18,FV($V$3,$N18-1,,-$T18,0),0) -> 0 | X68: =IF(X$56=$N18,FV($V$3,$N18-1,,-$T18,0),0) -> 0 | Z68: =IF(Z$56=$N18,FV($V$3,$N18-1,,-$T18,0),0) -> 0 | AB68: =IF(AB$56=$N18,FV($V$3,$N18-1,,-$T18,0),0) -> 0 | AD68: =IF(AD$56=$N18,FV($V$3,$N18-1,,-$T18,0),0) -> 0 | AF68: =IF(AF$56=$N18,FV($V$3,$N18-1,,-$T18,0),0) -> 0 | AH68: =IF(AH$56=$N18,FV($V$3,$N18-1,,-$T18,0),0) -> 0 | AJ68: =IF(AJ$56=$N18,FV($V$3,$N18-1,,-$T18,0),0) -> 0 | AL68: =IF(AL$56=$N18,FV($V$3,$N18-1,,-$T18,0),0) -> 0
B69: =+B19 -> 9 | D69: =+D19 -> 1 | F69: =+F19 -> x | H69: =+H19 -> x | J69: =IF(J$56=$N19,FV($V$3,$N19-1,,-$T19,0),0) -> 0 | L69: =IF(L$56=$N19,FV($V$3,$N19-1,,-$T19,0),0) -> 0 | N69: =IF(N$56=$N19,FV($V$3,$N19-1,,-$T19,0),0) -> 0 | P69: =IF(P$56=$N19,FV($V$3,$N19-1,,-$T19,0),0) -> 0 | R69: =IF(R$56=$N19,FV($V$3,$N19-1,,-$T19,0),0) -> 0 | T69: =IF(T$56=$N19,FV($V$3,$N19-1,,-$T19,0),0) -> 0 | V69: =IF(V$56=$N19,FV($V$3,$N19-1,,-$T19,0),0) -> 0 | X69: =IF(X$56=$N19,FV($V$3,$N19-1,,-$T19,0),0) -> 0 | Z69: =IF(Z$56=$N19,FV($V$3,$N19-1,,-$T19,0),0) -> 0 | AB69: =IF(AB$56=$N19,FV($V$3,$N19-1,,-$T19,0),0) -> 0 | AD69: =IF(AD$56=$N19,FV($V$3,$N19-1,,-$T19,0),0) -> 0 | AF69: =IF(AF$56=$N19,FV($V$3,$N19-1,,-$T19,0),0) -> 0 | AH69: =IF(AH$56=$N19,FV($V$3,$N19-1,,-$T19,0),0) -> 0 | AJ69: =IF(AJ$56=$N19,FV($V$3,$N19-1,,-$T19,0),0) -> 0 | AL69: =IF(AL$56=$N19,FV($V$3,$N19-1,,-$T19,0),0) -> 0
B70: =+B20 -> 10 | D70: =+D20 -> 1 | F70: =+F20 -> x | H70: =+H20 -> x | J70: =IF(J$56=$N20,FV($V$3,$N20-1,,-$T20,0),0) -> 0 | L70: =IF(L$56=$N20,FV($V$3,$N20-1,,-$T20,0),0) -> 0 | N70: =IF(N$56=$N20,FV($V$3,$N20-1,,-$T20,0),0) -> 0 | P70: =IF(P$56=$N20,FV($V$3,$N20-1,,-$T20,0),0) -> 0 | R70: =IF(R$56=$N20,FV($V$3,$N20-1,,-$T20,0),0) -> 0 | T70: =IF(T$56=$N20,FV($V$3,$N20-1,,-$T20,0),0) -> 0 | V70: =IF(V$56=$N20,FV($V$3,$N20-1,,-$T20,0),0) -> 0 | X70: =IF(X$56=$N20,FV($V$3,$N20-1,,-$T20,0),0) -> 0 | Z70: =IF(Z$56=$N20,FV($V$3,$N20-1,,-$T20,0),0) -> 0 | AB70: =IF(AB$56=$N20,FV($V$3,$N20-1,,-$T20,0),0) -> 0 | AD70: =IF(AD$56=$N20,FV($V$3,$N20-1,,-$T20,0),0) -> 0 | AF70: =IF(AF$56=$N20,FV($V$3,$N20-1,,-$T20,0),0) -> 0 | AH70: =IF(AH$56=$N20,FV($V$3,$N20-1,,-$T20,0),0) -> 0 | AJ70: =IF(AJ$56=$N20,FV($V$3,$N20-1,,-$T20,0),0) -> 0 | AL70: =IF(AL$56=$N20,FV($V$3,$N20-1,,-$T20,0),0) -> 0
B71: =+B21 -> 11 | D71: =+D21 -> 1 | F71: =+F21 -> x | H71: =+H21 -> x | J71: =IF(J$56=$N21,FV($V$3,$N21-1,,-$T21,0),0) -> 0 | L71: =IF(L$56=$N21,FV($V$3,$N21-1,,-$T21,0),0) -> 0 | N71: =IF(N$56=$N21,FV($V$3,$N21-1,,-$T21,0),0) -> 0 | P71: =IF(P$56=$N21,FV($V$3,$N21-1,,-$T21,0),0) -> 0 | R71: =IF(R$56=$N21,FV($V$3,$N21-1,,-$T21,0),0) -> 0 | T71: =IF(T$56=$N21,FV($V$3,$N21-1,,-$T21,0),0) -> 0 | V71: =IF(V$56=$N21,FV($V$3,$N21-1,,-$T21,0),0) -> 0 | X71: =IF(X$56=$N21,FV($V$3,$N21-1,,-$T21,0),0) -> 0 | Z71: =IF(Z$56=$N21,FV($V$3,$N21-1,,-$T21,0),0) -> 0 | AB71: =IF(AB$56=$N21,FV($V$3,$N21-1,,-$T21,0),0) -> 0 | AD71: =IF(AD$56=$N21,FV($V$3,$N21-1,,-$T21,0),0) -> 0 | AF71: =IF(AF$56=$N21,FV($V$3,$N21-1,,-$T21,0),0) -> 0 | AH71: =IF(AH$56=$N21,FV($V$3,$N21-1,,-$T21,0),0) -> 0 | AJ71: =IF(AJ$56=$N21,FV($V$3,$N21-1,,-$T21,0),0) -> 0 | AL71: =IF(AL$56=$N21,FV($V$3,$N21-1,,-$T21,0),0) -> 0
B72: =+B22 -> 12 | D72: =+D22 -> 1 | F72: =+F22 -> x | H72: =+H22 -> x | J72: =IF(J$56=$N22,FV($V$3,$N22-1,,-$T22,0),0) -> 0 | L72: =IF(L$56=$N22,FV($V$3,$N22-1,,-$T22,0),0) -> 0 | N72: =IF(N$56=$N22,FV($V$3,$N22-1,,-$T22,0),0) -> 0 | P72: =IF(P$56=$N22,FV($V$3,$N22-1,,-$T22,0),0) -> 0 | R72: =IF(R$56=$N22,FV($V$3,$N22-1,,-$T22,0),0) -> 0 | T72: =IF(T$56=$N22,FV($V$3,$N22-1,,-$T22,0),0) -> 0 | V72: =IF(V$56=$N22,FV($V$3,$N22-1,,-$T22,0),0) -> 0 | X72: =IF(X$56=$N22,FV($V$3,$N22-1,,-$T22,0),0) -> 0 | Z72: =IF(Z$56=$N22,FV($V$3,$N22-1,,-$T22,0),0) -> 0 | AB72: =IF(AB$56=$N22,FV($V$3,$N22-1,,-$T22,0),0) -> 0 | AD72: =IF(AD$56=$N22,FV($V$3,$N22-1,,-$T22,0),0) -> 0 | AF72: =IF(AF$56=$N22,FV($V$3,$N22-1,,-$T22,0),0) -> 0 | AH72: =IF(AH$56=$N22,FV($V$3,$N22-1,,-$T22,0),0) -> 0 | AJ72: =IF(AJ$56=$N22,FV($V$3,$N22-1,,-$T22,0),0) -> 0 | AL72: =IF(AL$56=$N22,FV($V$3,$N22-1,,-$T22,0),0) -> 0
... B100: =+B50 -> 40 | D100: =+D50 -> 1 | F100: =+F50 -> x | H100: =+H50 -> x | J100: =IF(J$56=$N50,FV($V$3,$N50-1,,-$T50,0),0) -> 0 | L100: =IF(L$56=$N50,FV($V$3,$N50-1,,-$T50,0),0) -> 0 | N100: =IF(N$56=$N50,FV($V$3,$N50-1,,-$T50,0),0) -> 0 | P100: =IF(P$56=$N50,FV($V$3,$N50-1,,-$T50,0),0) -> 0 | R100: =IF(R$56=$N50,FV($V$3,$N50-1,,-$T50,0),0) -> 0 | T100: =IF(T$56=$N50,FV($V$3,$N50-1,,-$T50,0),0) -> 0 | V100: =IF(V$56=$N50,FV($V$3,$N50-1,,-$T50,0),0) -> 0 | X100: =IF(X$56=$N50,FV($V$3,$N50-1,,-$T50,0),0) -> 0 | Z100: =IF(Z$56=$N50,FV($V$3,$N50-1,,-$T50,0),0) -> 0 | AB100: =IF(AB$56=$N50,FV($V$3,$N50-1,,-$T50,0),0) -> 0 | AD100: =IF(AD$56=$N50,FV($V$3,$N50-1,,-$T50,0),0) -> 0 | AF100: =IF(AF$56=$N50,FV($V$3,$N50-1,,-$T50,0),0) -> 0 | AH100: =IF(AH$56=$N50,FV($V$3,$N50-1,,-$T50,0),0) -> 0 | AJ100: =IF(AJ$56=$N50,FV($V$3,$N50-1,,-$T50,0),0) -> 0 | AL100: =IF(AL$56=$N50,FV($V$3,$N50-1,,-$T50,0),0) -> 0
H102: =+H52 -> Anticipated Expenditures, By Year | J102: =SUM(J61:J100) -> 0 | L102: =SUM(L61:L100) -> 0 | N102: =SUM(N61:N100) -> 0 | P102: =SUM(P61:P100) -> 0 | R102: =SUM(R61:R100) -> 0 | T102: =SUM(T61:T100) -> 0 | V102: =SUM(V61:V100) -> 0 | X102: =SUM(X61:X100) -> 0 | Z102: =SUM(Z61:Z100) -> 0 | AB102: =SUM(AB61:AB100) -> 0 | AD102: =SUM(AD61:AD100) -> 0 | AF102: =SUM(AF61:AF100) -> 0 | AH102: =SUM(AH61:AH100) -> 0 | AJ102: =SUM(AJ61:AJ100) -> 0 | AL102: =SUM(AL61:AL100) -> 0

Sheet Roofs 3
H1: Exhibit B
V2: Explanatory Notes:
H3: RESERVE EXPENDITURES | P3: RefYr | U3: 1) | V3: 0.03 | W3: is the estimated future Inflation Rate for estimating Future Replacement Costs.
H4: for | P4: 2023 | U4: 2) | V4: Fiscal Year is beginning January 1 and ending December 31.
H5: ='Funding Plan'!G9 -> Association
B6: Line Item | D6: Estimated | J6: Estimated Year Last Replaced | L6: Life Analysis, Years | P6: Estimated Year of 1st Replacement | R6: 2024 Unit Cost | T6: 2024 Cost of Replacement | V6: Total Future Cost of Replacement | X6: 1 | Z6: 2 | AB6: 3 | AD6: 4 | AF6: 5 | AH6: 6 | AJ6: 7 | AL6: 8 | AN6: 9 | AP6: 10 | AR6: 11 | AT6: 12 | AV6: 13 | AX6: 14 | AZ6: 15
D7: Quantity | F7: Units | H7: Reserve Component Inventory | L7: Useful | N7: Remaining | X7: 2024 | Z7: =X7+1 -> 2025 | AA7: =Y7+1 -> 1 | AB7: =Z7+1 -> 2026 | AC7: =AA7+1 -> 2 | AD7: =AB7+1 -> 2027 | AE7: =AC7+1 -> 3 | AF7: =AD7+1 -> 2028 | AG7: =AE7+1 -> 4 | ... AZ7: =AX7+1 -> 2038
H9: Roofs
B11: 1 | D11: 1 | F11: x | H11: x | J11: 1 | K11: 23 | L11: 1 | N11: =P11-O11 -> -1999 | O11: =P4 -> 2023 | P11: =J11+K11 -> 24 | R11: 1 | T11: =D11*R11 -> 1 | V11: =SUM(X11:AZ11)+SUM(J61:AL61) -> 0 | X11: =IF(X$6=$N11,FV($V$3,$N11-1,,-$T11,0),0) -> 0 | Z11: =IF(Z$6=$N11,FV($V$3,$N11-1,,-$T11,0),0) -> 0 | AB11: =IF(AB$6=$N11,FV($V$3,$N11-1,,-$T11,0),0) -> 0 | AD11: =IF(AD$6=$N11,FV($V$3,$N11-1,,-$T11,0),0) -> 0 | AF11: =IF(AF$6=$N11,FV($V$3,$N11-1,,-$T11,0),0) -> 0 | AH11: =IF(AH$6=$N11,FV($V$3,$N11-1,,-$T11,0),0) -> 0 | AJ11: =IF(AJ$6=$N11,FV($V$3,$N11-1,,-$T11,0),0) -> 0 | AL11: =IF(AL$6=$N11,FV($V$3,$N11-1,,-$T11,0),0) -> 0 | AN11: =IF(AN$6=$N11,FV($V$3,$N11-1,,-$T11,0),0) -> 0 | AP11: =IF(AP$6=$N11,FV($V$3,$N11-1,,-$T11,0),0) -> 0 | AR11: =IF(AR$6=$N11,FV($V$3,$N11-1,,-$T11,0),0) -> 0 | AT11: =IF(AT$6=$N11,FV($V$3,$N11-1,,-$T11,0),0) -> 0 | AV11: =IF(AV$6=$N11,FV($V$3,$N11-1,,-$T11,0),0) -> 0 | AX11: =IF(AX$6=$N11,FV($V$3,$N11-1,,-$T11,0),0) -> 0 | AZ11: =IF(AZ$6=$N11,FV($V$3,$N11-1,,-$T11,0),0) -> 0
B12: =+B11+1 -> 2 | D12: 1 | F12: =F11 -> x | H12: x | J12: 1 | K12: 23 | L12: =L11 -> 1 | N12: =P12-O12 -> -1999 | O12: =O11 -> 2023 | P12: =J12+K12 -> 24 | R12: =R11 -> 1 | T12: =D12*R12 -> 1 | V12: =SUM(X12:AZ12)+SUM(J62:AL62) -> 0 | X12: =IF(X$6=$N12,FV($V$3,$N12-1,,-$T12,0),0) -> 0 | Z12: =IF(Z$6=$N12,FV($V$3,$N12-1,,-$T12,0),0) -> 0 | AB12: =IF(AB$6=$N12,FV($V$3,$N12-1,,-$T12,0),0) -> 0 | AD12: =IF(AD$6=$N12,FV($V$3,$N12-1,,-$T12,0),0) -> 0 | AF12: =IF(AF$6=$N12,FV($V$3,$N12-1,,-$T12,0),0) -> 0 | AH12: =IF(AH$6=$N12,FV($V$3,$N12-1,,-$T12,0),0) -> 0 | AJ12: =IF(AJ$6=$N12,FV($V$3,$N12-1,,-$T12,0),0) -> 0 | AL12: =IF(AL$6=$N12,FV($V$3,$N12-1,,-$T12,0),0) -> 0 | AN12: =IF(AN$6=$N12,FV($V$3,$N12-1,,-$T12,0),0) -> 0 | AP12: =IF(AP$6=$N12,FV($V$3,$N12-1,,-$T12,0),0) -> 0 | AR12: =IF(AR$6=$N12,FV($V$3,$N12-1,,-$T12,0),0) -> 0 | AT12: =IF(AT$6=$N12,FV($V$3,$N12-1,,-$T12,0),0) -> 0 | AV12: =IF(AV$6=$N12,FV($V$3,$N12-1,,-$T12,0),0) -> 0 | AX12: =IF(AX$6=$N12,FV($V$3,$N12-1,,-$T12,0),0) -> 0 | AZ12: =IF(AZ$6=$N12,FV($V$3,$N12-1,,-$T12,0),0) -> 0
B13: =+B12+1 -> 3 | D13: 1 | F13: =F12 -> x | H13: x | J13: 1 | K13: 23 | L13: =L12 -> 1 | N13: =P13-O13 -> -1999 | O13: =O12 -> 2023 | P13: =J13+K13 -> 24 | R13: =R12 -> 1 | T13: =D13*R13 -> 1 | V13: =SUM(X13:AZ13)+SUM(J63:AL63) -> 0 | X13: =IF(X$6=$N13,FV($V$3,$N13-1,,-$T13,0),0) -> 0 | Z13: =IF(Z$6=$N13,FV($V$3,$N13-1,,-$T13,0),0) -> 0 | AB13: =IF(AB$6=$N13,FV($V$3,$N13-1,,-$T13,0),0) -> 0 | AD13: =IF(AD$6=$N13,FV($V$3,$N13-1,,-$T13,0),0) -> 0 | AF13: =IF(AF$6=$N13,FV($V$3,$N13-1,,-$T13,0),0) -> 0 | AH13: =IF(AH$6=$N13,FV($V$3,$N13-1,,-$T13,0),0) -> 0 | AJ13: =IF(AJ$6=$N13,FV($V$3,$N13-1,,-$T13,0),0) -> 0 | AL13: =IF(AL$6=$N13,FV($V$3,$N13-1,,-$T13,0),0) -> 0 | AN13: =IF(AN$6=$N13,FV($V$3,$N13-1,,-$T13,0),0) -> 0 | AP13: =IF(AP$6=$N13,FV($V$3,$N13-1,,-$T13,0),0) -> 0 | AR13: =IF(AR$6=$N13,FV($V$3,$N13-1,,-$T13,0),0) -> 0 | AT13: =IF(AT$6=$N13,FV($V$3,$N13-1,,-$T13,0),0) -> 0 | AV13: =IF(AV$6=$N13,FV($V$3,$N13-1,,-$T13,0),0) -> 0 | AX13: =IF(AX$6=$N13,FV($V$3,$N13-1,,-$T13,0),0) -> 0 | AZ13: =IF(AZ$6=$N13,FV($V$3,$N13-1,,-$T13,0),0) -> 0
B14: =+B13+1 -> 4 | D14: 1 | F14: =F13 -> x | H14: x | J14: 1 | K14: 23 | L14: =L13 -> 1 | N14: =P14-O14 -> -1999 | O14: =O13 -> 2023 | P14: =J14+K14 -> 24 | R14: =R13 -> 1 | T14: =D14*R14 -> 1 | V14: =SUM(X14:AZ14)+SUM(J64:AL64) -> 0 | X14: =IF(X$6=$N14,FV($V$3,$N14-1,,-$T14,0),0) -> 0 | Z14: =IF(Z$6=$N14,FV($V$3,$N14-1,,-$T14,0),0) -> 0 | AB14: =IF(AB$6=$N14,FV($V$3,$N14-1,,-$T14,0),0) -> 0 | AD14: =IF(AD$6=$N14,FV($V$3,$N14-1,,-$T14,0),0) -> 0 | AF14: =IF(AF$6=$N14,FV($V$3,$N14-1,,-$T14,0),0) -> 0 | AH14: =IF(AH$6=$N14,FV($V$3,$N14-1,,-$T14,0),0) -> 0 | AJ14: =IF(AJ$6=$N14,FV($V$3,$N14-1,,-$T14,0),0) -> 0 | AL14: =IF(AL$6=$N14,FV($V$3,$N14-1,,-$T14,0),0) -> 0 | AN14: =IF(AN$6=$N14,FV($V$3,$N14-1,,-$T14,0),0) -> 0 | AP14: =IF(AP$6=$N14,FV($V$3,$N14-1,,-$T14,0),0) -> 0 | AR14: =IF(AR$6=$N14,FV($V$3,$N14-1,,-$T14,0),0) -> 0 | AT14: =IF(AT$6=$N14,FV($V$3,$N14-1,,-$T14,0),0) -> 0 | AV14: =IF(AV$6=$N14,FV($V$3,$N14-1,,-$T14,0),0) -> 0 | AX14: =IF(AX$6=$N14,FV($V$3,$N14-1,,-$T14,0),0) -> 0 | AZ14: =IF(AZ$6=$N14,FV($V$3,$N14-1,,-$T14,0),0) -> 0
B15: =+B14+1 -> 5 | D15: 1 | F15: =F14 -> x | H15: x | J15: 1 | K15: 23 | L15: =L14 -> 1 | N15: =P15-O15 -> -1999 | O15: =O14 -> 2023 | P15: =J15+K15 -> 24 | R15: =R14 -> 1 | T15: =D15*R15 -> 1 | V15: =SUM(X15:AZ15)+SUM(J65:AL65) -> 0 | X15: =IF(X$6=$N15,FV($V$3,$N15-1,,-$T15,0),0) -> 0 | Z15: =IF(Z$6=$N15,FV($V$3,$N15-1,,-$T15,0),0) -> 0 | AB15: =IF(AB$6=$N15,FV($V$3,$N15-1,,-$T15,0),0) -> 0 | AD15: =IF(AD$6=$N15,FV($V$3,$N15-1,,-$T15,0),0) -> 0 | AF15: =IF(AF$6=$N15,FV($V$3,$N15-1,,-$T15,0),0) -> 0 | AH15: =IF(AH$6=$N15,FV($V$3,$N15-1,,-$T15,0),0) -> 0 | AJ15: =IF(AJ$6=$N15,FV($V$3,$N15-1,,-$T15,0),0) -> 0 | AL15: =IF(AL$6=$N15,FV($V$3,$N15-1,,-$T15,0),0) -> 0 | AN15: =IF(AN$6=$N15,FV($V$3,$N15-1,,-$T15,0),0) -> 0 | AP15: =IF(AP$6=$N15,FV($V$3,$N15-1,,-$T15,0),0) -> 0 | AR15: =IF(AR$6=$N15,FV($V$3,$N15-1,,-$T15,0),0) -> 0 | AT15: =IF(AT$6=$N15,FV($V$3,$N15-1,,-$T15,0),0) -> 0 | AV15: =IF(AV$6=$N15,FV($V$3,$N15-1,,-$T15,0),0) -> 0 | AX15: =IF(AX$6=$N15,FV($V$3,$N15-1,,-$T15,0),0) -> 0 | AZ15: =IF(AZ$6=$N15,FV($V$3,$N15-1,,-$T15,0),0) -> 0
B16: =+B15+1 -> 6 | D16: 1 | F16: =F15 -> x | H16: x | J16: 1 | K16: 23 | L16: =L15 -> 1 | N16: =P16-O16 -> -1999 | O16: =O15 -> 2023 | P16: =J16+K16 -> 24 | R16: =R15 -> 1 | T16: =D16*R16 -> 1 | V16: =SUM(X16:AZ16)+SUM(J66:AL66) -> 0 | X16: =IF(X$6=$N16,FV($V$3,$N16-1,,-$T16,0),0) -> 0 | Z16: =IF(Z$6=$N16,FV($V$3,$N16-1,,-$T16,0),0) -> 0 | AB16: =IF(AB$6=$N16,FV($V$3,$N16-1,,-$T16,0),0) -> 0 | AD16: =IF(AD$6=$N16,FV($V$3,$N16-1,,-$T16,0),0) -> 0 | AF16: =IF(AF$6=$N16,FV($V$3,$N16-1,,-$T16,0),0) -> 0 | AH16: =IF(AH$6=$N16,FV($V$3,$N16-1,,-$T16,0),0) -> 0 | AJ16: =IF(AJ$6=$N16,FV($V$3,$N16-1,,-$T16,0),0) -> 0 | AL16: =IF(AL$6=$N16,FV($V$3,$N16-1,,-$T16,0),0) -> 0 | AN16: =IF(AN$6=$N16,FV($V$3,$N16-1,,-$T16,0),0) -> 0 | AP16: =IF(AP$6=$N16,FV($V$3,$N16-1,,-$T16,0),0) -> 0 | AR16: =IF(AR$6=$N16,FV($V$3,$N16-1,,-$T16,0),0) -> 0 | AT16: =IF(AT$6=$N16,FV($V$3,$N16-1,,-$T16,0),0) -> 0 | AV16: =IF(AV$6=$N16,FV($V$3,$N16-1,,-$T16,0),0) -> 0 | AX16: =IF(AX$6=$N16,FV($V$3,$N16-1,,-$T16,0),0) -> 0 | AZ16: =IF(AZ$6=$N16,FV($V$3,$N16-1,,-$T16,0),0) -> 0
B17: =+B16+1 -> 7 | D17: 1 | F17: =F16 -> x | H17: x | J17: 1 | K17: 23 | L17: =L16 -> 1 | N17: =P17-O17 -> -1999 | O17: =O16 -> 2023 | P17: =J17+K17 -> 24 | R17: =R16 -> 1 | T17: =D17*R17 -> 1 | V17: =SUM(X17:AZ17)+SUM(J67:AL67) -> 0 | X17: =IF(X$6=$N17,FV($V$3,$N17-1,,-$T17,0),0) -> 0 | Z17: =IF(Z$6=$N17,FV($V$3,$N17-1,,-$T17,0),0) -> 0 | AB17: =IF(AB$6=$N17,FV($V$3,$N17-1,,-$T17,0),0) -> 0 | AD17: =IF(AD$6=$N17,FV($V$3,$N17-1,,-$T17,0),0) -> 0 | AF17: =IF(AF$6=$N17,FV($V$3,$N17-1,,-$T17,0),0) -> 0 | AH17: =IF(AH$6=$N17,FV($V$3,$N17-1,,-$T17,0),0) -> 0 | AJ17: =IF(AJ$6=$N17,FV($V$3,$N17-1,,-$T17,0),0) -> 0 | AL17: =IF(AL$6=$N17,FV($V$3,$N17-1,,-$T17,0),0) -> 0 | AN17: =IF(AN$6=$N17,FV($V$3,$N17-1,,-$T17,0),0) -> 0 | AP17: =IF(AP$6=$N17,FV($V$3,$N17-1,,-$T17,0),0) -> 0 | AR17: =IF(AR$6=$N17,FV($V$3,$N17-1,,-$T17,0),0) -> 0 | AT17: =IF(AT$6=$N17,FV($V$3,$N17-1,,-$T17,0),0) -> 0 | AV17: =IF(AV$6=$N17,FV($V$3,$N17-1,,-$T17,0),0) -> 0 | AX17: =IF(AX$6=$N17,FV($V$3,$N17-1,,-$T17,0),0) -> 0 | AZ17: =IF(AZ$6=$N17,FV($V$3,$N17-1,,-$T17,0),0) -> 0
B18: =+B17+1 -> 8 | D18: 1 | F18: =F17 -> x | H18: x | J18: 1 | K18: 23 | L18: =L17 -> 1 | N18: =P18-O18 -> -1999 | O18: =O17 -> 2023 | P18: =J18+K18 -> 24 | R18: =R17 -> 1 | T18: =D18*R18 -> 1 | V18: =SUM(X18:AZ18)+SUM(J68:AL68) -> 0 | X18: =IF(X$6=$N18,FV($V$3,$N18-1,,-$T18,0),0) -> 0 | Z18: =IF(Z$6=$N18,FV($V$3,$N18-1,,-$T18,0),0) -> 0 | AB18: =IF(AB$6=$N18,FV($V$3,$N18-1,,-$T18,0),0) -> 0 | AD18: =IF(AD$6=$N18,FV($V$3,$N18-1,,-$T18,0),0) -> 0 | AF18: =IF(AF$6=$N18,FV($V$3,$N18-1,,-$T18,0),0) -> 0 | AH18: =IF(AH$6=$N18,FV($V$3,$N18-1,,-$T18,0),0) -> 0 | AJ18: =IF(AJ$6=$N18,FV($V$3,$N18-1,,-$T18,0),0) -> 0 | AL18: =IF(AL$6=$N18,FV($V$3,$N18-1,,-$T18,0),0) -> 0 | AN18: =IF(AN$6=$N18,FV($V$3,$N18-1,,-$T18,0),0) -> 0 | AP18: =IF(AP$6=$N18,FV($V$3,$N18-1,,-$T18,0),0) -> 0 | AR18: =IF(AR$6=$N18,FV($V$3,$N18-1,,-$T18,0),0) -> 0 | AT18: =IF(AT$6=$N18,FV($V$3,$N18-1,,-$T18,0),0) -> 0 | AV18: =IF(AV$6=$N18,FV($V$3,$N18-1,,-$T18,0),0) -> 0 | AX18: =IF(AX$6=$N18,FV($V$3,$N18-1,,-$T18,0),0) -> 0 | AZ18: =IF(AZ$6=$N18,FV($V$3,$N18-1,,-$T18,0),0) -> 0
B19: =+B18+1 -> 9 | D19: 1 | F19: =F18 -> x | H19: x | J19: 1 | K19: 23 | L19: =L18 -> 1 | N19: =P19-O19 -> -1999 | O19: =O18 -> 2023 | P19: =J19+K19 -> 24 | R19: =R18 -> 1 | T19: =D19*R19 -> 1 | V19: =SUM(X19:AZ19)+SUM(J69:AL69) -> 0 | X19: =IF(X$6=$N19,FV($V$3,$N19-1,,-$T19,0),0) -> 0 | Z19: =IF(Z$6=$N19,FV($V$3,$N19-1,,-$T19,0),0) -> 0 | AB19: =IF(AB$6=$N19,FV($V$3,$N19-1,,-$T19,0),0) -> 0 | AD19: =IF(AD$6=$N19,FV($V$3,$N19-1,,-$T19,0),0) -> 0 | AF19: =IF(AF$6=$N19,FV($V$3,$N19-1,,-$T19,0),0) -> 0 | AH19: =IF(AH$6=$N19,FV($V$3,$N19-1,,-$T19,0),0) -> 0 | AJ19: =IF(AJ$6=$N19,FV($V$3,$N19-1,,-$T19,0),0) -> 0 | AL19: =IF(AL$6=$N19,FV($V$3,$N19-1,,-$T19,0),0) -> 0 | AN19: =IF(AN$6=$N19,FV($V$3,$N19-1,,-$T19,0),0) -> 0 | AP19: =IF(AP$6=$N19,FV($V$3,$N19-1,,-$T19,0),0) -> 0 | AR19: =IF(AR$6=$N19,FV($V$3,$N19-1,,-$T19,0),0) -> 0 | AT19: =IF(AT$6=$N19,FV($V$3,$N19-1,,-$T19,0),0) -> 0 | AV19: =IF(AV$6=$N19,FV($V$3,$N19-1,,-$T19,0),0) -> 0 | AX19: =IF(AX$6=$N19,FV($V$3,$N19-1,,-$T19,0),0) -> 0 | AZ19: =IF(AZ$6=$N19,FV($V$3,$N19-1,,-$T19,0),0) -> 0
B20: =+B19+1 -> 10 | D20: 1 | F20: =F19 -> x | H20: x | J20: 1 | K20: 23 | L20: =L19 -> 1 | N20: =P20-O20 -> -1999 | O20: =O19 -> 2023 | P20: =J20+K20 -> 24 | R20: =R19 -> 1 | T20: =D20*R20 -> 1 | V20: =SUM(X20:AZ20)+SUM(J70:AL70) -> 0 | X20: =IF(X$6=$N20,FV($V$3,$N20-1,,-$T20,0),0) -> 0 | Z20: =IF(Z$6=$N20,FV($V$3,$N20-1,,-$T20,0),0) -> 0 | AB20: =IF(AB$6=$N20,FV($V$3,$N20-1,,-$T20,0),0) -> 0 | AD20: =IF(AD$6=$N20,FV($V$3,$N20-1,,-$T20,0),0) -> 0 | AF20: =IF(AF$6=$N20,FV($V$3,$N20-1,,-$T20,0),0) -> 0 | AH20: =IF(AH$6=$N20,FV($V$3,$N20-1,,-$T20,0),0) -> 0 | AJ20: =IF(AJ$6=$N20,FV($V$3,$N20-1,,-$T20,0),0) -> 0 | AL20: =IF(AL$6=$N20,FV($V$3,$N20-1,,-$T20,0),0) -> 0 | AN20: =IF(AN$6=$N20,FV($V$3,$N20-1,,-$T20,0),0) -> 0 | AP20: =IF(AP$6=$N20,FV($V$3,$N20-1,,-$T20,0),0) -> 0 | AR20: =IF(AR$6=$N20,FV($V$3,$N20-1,,-$T20,0),0) -> 0 | AT20: =IF(AT$6=$N20,FV($V$3,$N20-1,,-$T20,0),0) -> 0 | AV20: =IF(AV$6=$N20,FV($V$3,$N20-1,,-$T20,0),0) -> 0 | AX20: =IF(AX$6=$N20,FV($V$3,$N20-1,,-$T20,0),0) -> 0 | AZ20: =IF(AZ$6=$N20,FV($V$3,$N20-1,,-$T20,0),0) -> 0
B21: =+B20+1 -> 11 | D21: 1 | F21: =F20 -> x | H21: x | J21: 1 | K21: 23 | L21: =L20 -> 1 | N21: =P21-O21 -> -1999 | O21: =O20 -> 2023 | P21: =J21+K21 -> 24 | R21: =R20 -> 1 | T21: =D21*R21 -> 1 | V21: =SUM(X21:AZ21)+SUM(J71:AL71) -> 0 | X21: =IF(X$6=$N21,FV($V$3,$N21-1,,-$T21,0),0) -> 0 | Z21: =IF(Z$6=$N21,FV($V$3,$N21-1,,-$T21,0),0) -> 0 | AB21: =IF(AB$6=$N21,FV($V$3,$N21-1,,-$T21,0),0) -> 0 | AD21: =IF(AD$6=$N21,FV($V$3,$N21-1,,-$T21,0),0) -> 0 | AF21: =IF(AF$6=$N21,FV($V$3,$N21-1,,-$T21,0),0) -> 0 | AH21: =IF(AH$6=$N21,FV($V$3,$N21-1,,-$T21,0),0) -> 0 | AJ21: =IF(AJ$6=$N21,FV($V$3,$N21-1,,-$T21,0),0) -> 0 | AL21: =IF(AL$6=$N21,FV($V$3,$N21-1,,-$T21,0),0) -> 0 | AN21: =IF(AN$6=$N21,FV($V$3,$N21-1,,-$T21,0),0) -> 0 | AP21: =IF(AP$6=$N21,FV($V$3,$N21-1,,-$T21,0),0) -> 0 | AR21: =IF(AR$6=$N21,FV($V$3,$N21-1,,-$T21,0),0) -> 0 | AT21: =IF(AT$6=$N21,FV($V$3,$N21-1,,-$T21,0),0) -> 0 | AV21: =IF(AV$6=$N21,FV($V$3,$N21-1,,-$T21,0),0) -> 0 | AX21: =IF(AX$6=$N21,FV($V$3,$N21-1,,-$T21,0),0) -> 0 | AZ21: =IF(AZ$6=$N21,FV($V$3,$N21-1,,-$T21,0),0) -> 0
B22: =+B21+1 -> 12 | D22: 1 | F22: =F21 -> x | H22: x | J22: 1 | K22: 23 | L22: =L21 -> 1 | N22: =P22-O22 -> -1999 | O22: =O21 -> 2023 | P22: =J22+K22 -> 24 | R22: =R21 -> 1 | T22: =D22*R22 -> 1 | V22: =SUM(X22:AZ22)+SUM(J72:AL72) -> 0 | X22: =IF(X$6=$N22,FV($V$3,$N22-1,,-$T22,0),0) -> 0 | Z22: =IF(Z$6=$N22,FV($V$3,$N22-1,,-$T22,0),0) -> 0 | AB22: =IF(AB$6=$N22,FV($V$3,$N22-1,,-$T22,0),0) -> 0 | AD22: =IF(AD$6=$N22,FV($V$3,$N22-1,,-$T22,0),0) -> 0 | AF22: =IF(AF$6=$N22,FV($V$3,$N22-1,,-$T22,0),0) -> 0 | AH22: =IF(AH$6=$N22,FV($V$3,$N22-1,,-$T22,0),0) -> 0 | AJ22: =IF(AJ$6=$N22,FV($V$3,$N22-1,,-$T22,0),0) -> 0 | AL22: =IF(AL$6=$N22,FV($V$3,$N22-1,,-$T22,0),0) -> 0 | AN22: =IF(AN$6=$N22,FV($V$3,$N22-1,,-$T22,0),0) -> 0 | AP22: =IF(AP$6=$N22,FV($V$3,$N22-1,,-$T22,0),0) -> 0 | AR22: =IF(AR$6=$N22,FV($V$3,$N22-1,,-$T22,0),0) -> 0 | AT22: =IF(AT$6=$N22,FV($V$3,$N22-1,,-$T22,0),0) -> 0 | AV22: =IF(AV$6=$N22,FV($V$3,$N22-1,,-$T22,0),0) -> 0 | AX22: =IF(AX$6=$N22,FV($V$3,$N22-1,,-$T22,0),0) -> 0 | AZ22: =IF(AZ$6=$N22,FV($V$3,$N22-1,,-$T22,0),0) -> 0
B23: =+B22+1 -> 13 | D23: 1 | F23: =F22 -> x | H23: x | J23: 1 | K23: 23 | L23: =L22 -> 1 | N23: =P23-O23 -> -1999 | O23: =O22 -> 2023 | P23: =J23+K23 -> 24 | R23: =R22 -> 1 | T23: =D23*R23 -> 1 | V23: =SUM(X23:AZ23)+SUM(J73:AL73) -> 0 | X23: =IF(X$6=$N23,FV($V$3,$N23-1,,-$T23,0),0) -> 0 | Z23: =IF(Z$6=$N23,FV($V$3,$N23-1,,-$T23,0),0) -> 0 | AB23: =IF(AB$6=$N23,FV($V$3,$N23-1,,-$T23,0),0) -> 0 | AD23: =IF(AD$6=$N23,FV($V$3,$N23-1,,-$T23,0),0) -> 0 | AF23: =IF(AF$6=$N23,FV($V$3,$N23-1,,-$T23,0),0) -> 0 | AH23: =IF(AH$6=$N23,FV($V$3,$N23-1,,-$T23,0),0) -> 0 | AJ23: =IF(AJ$6=$N23,FV($V$3,$N23-1,,-$T23,0),0) -> 0 | AL23: =IF(AL$6=$N23,FV($V$3,$N23-1,,-$T23,0),0) -> 0 | AN23: =IF(AN$6=$N23,FV($V$3,$N23-1,,-$T23,0),0) -> 0 | AP23: =IF(AP$6=$N23,FV($V$3,$N23-1,,-$T23,0),0) -> 0 | AR23: =IF(AR$6=$N23,FV($V$3,$N23-1,,-$T23,0),0) -> 0 | AT23: =IF(AT$6=$N23,FV($V$3,$N23-1,,-$T23,0),0) -> 0 | AV23: =IF(AV$6=$N23,FV($V$3,$N23-1,,-$T23,0),0) -> 0 | AX23: =IF(AX$6=$N23,FV($V$3,$N23-1,,-$T23,0),0) -> 0 | AZ23: =IF(AZ$6=$N23,FV($V$3,$N23-1,,-$T23,0),0) -> 0
... B50: =+B49+1 -> 40 | D50: 1 | F50: =F49 -> x | H50: x | J50: 1 | K50: 23 | L50: =L49 -> 1 | N50: =P50-O50 -> -1999 | O50: =O49 -> 2023 | P50: =J50+K50 -> 24 | R50: =R49 -> 1 | T50: =D50*R50 -> 1 | V50: =SUM(X50:AZ50)+SUM(J100:AL100) -> 0 | X50: =IF(X$6=$N50,FV($V$3,$N50-1,,-$T50,0),0) -> 0 | Z50: =IF(Z$6=$N50,FV($V$3,$N50-1,,-$T50,0),0) -> 0 | AB50: =IF(AB$6=$N50,FV($V$3,$N50-1,,-$T50,0),0) -> 0 | AD50: =IF(AD$6=$N50,FV($V$3,$N50-1,,-$T50,0),0) -> 0 | AF50: =IF(AF$6=$N50,FV($V$3,$N50-1,,-$T50,0),0) -> 0 | AH50: =IF(AH$6=$N50,FV($V$3,$N50-1,,-$T50,0),0) -> 0 | AJ50: =IF(AJ$6=$N50,FV($V$3,$N50-1,,-$T50,0),0) -> 0 | AL50: =IF(AL$6=$N50,FV($V$3,$N50-1,,-$T50,0),0) -> 0 | AN50: =IF(AN$6=$N50,FV($V$3,$N50-1,,-$T50,0),0) -> 0 | AP50: =IF(AP$6=$N50,FV($V$3,$N50-1,,-$T50,0),0) -> 0 | AR50: =IF(AR$6=$N50,FV($V$3,$N50-1,,-$T50,0),0) -> 0 | AT50: =IF(AT$6=$N50,FV($V$3,$N50-1,,-$T50,0),0) -> 0 | AV50: =IF(AV$6=$N50,FV($V$3,$N50-1,,-$T50,0),0) -> 0 | AX50: =IF(AX$6=$N50,FV($V$3,$N50-1,,-$T50,0),0) -> 0 | AZ50: =IF(AZ$6=$N50,FV($V$3,$N50-1,,-$T50,0),0) -> 0
H52: Anticipated Expenditures, By Year | T52: =SUM(T11:T50) -> 40 | V52: =SUM(V11:V50) -> 0 | X52: =SUM(X11:X50) -> 0 | Z52: =SUM(Z11:Z50) -> 0 | AB52: =SUM(AB11:AB50) -> 0 | AD52: =SUM(AD11:AD50) -> 0 | AF52: =SUM(AF11:AF50) -> 0 | AH52: =SUM(AH11:AH50) -> 0 | AJ52: =SUM(AJ11:AJ50) -> 0 | AL52: =SUM(AL11:AL50) -> 0 | AN52: =SUM(AN11:AN50) -> 0 | AP52: =SUM(AP11:AP50) -> 0 | AR52: =SUM(AR11:AR50) -> 0 | AT52: =SUM(AT11:AT50) -> 0 | AV52: =SUM(AV11:AV50) -> 0 | AX52: =SUM(AX11:AX50) -> 0 | AZ52: =SUM(AZ11:AZ50) -> 0
B56: Line Item | J56: 16 | L56: 17 | N56: 18 | P56: 19 | R56: 20 | T56: =+R56+1 -> 21 | V56: =+T56+1 -> 22 | X56: =+V56+1 -> 23 | Z56: =+X56+1 -> 24 | AB56: =+Z56+1 -> 25 | AD56: =+AB56+1 -> 26 | AF56: =+AD56+1 -> 27 | AH56: =+AF56+1 -> 28 | AJ56: =+AH56+1 -> 29 | AL56: =+AJ56+1 -> 30
D57: Quantity | F57: Units | H57: Reserve Component Inventory | J57: =AZ7+1 -> 2039 | K57: =BA7+1 -> 1 | L57: =J57+1 -> 2040 | M57: =K57+1 -> 2 | N57: =L57+1 -> 2041 | O57: =M57+1 -> 3 | P57: =N57+1 -> 2042 | Q57: =O57+1 -> 4 | R57: =P57+1 -> 2043 | T57: =+R57+1 -> 2044 | U57: =S57+1 -> 1 | V57: =T57+1 -> 2045 | W57: =U57+1 -> 2 | X57: =V57+1 -> 2046 | Y57: =W57+1 -> 3 | Z57: =X57+1 -> 2047 | AA57: =Y57+1 -> 4 | AB57: =Z57+1 -> 2048 | AD57: =AB57+1 -> 2049 | AF57: =AD57+1 -> 2050 | AH57: =AF57+1 -> 2051 | AJ57: =AH57+1 -> 2052 | AL57: =AJ57+1 -> 2053
H59: =+H9 -> Roofs
B61: =+B11 -> 1 | D61: =+D11 -> 1 | F61: =+F11 -> x | H61: =+H11 -> x | J61: =IF(J$56=$N11,FV($V$3,$N11-1,,-$T11,0),0) -> 0 | L61: =IF(L$56=$N11,FV($V$3,$N11-1,,-$T11,0),0) -> 0 | N61: =IF(N$56=$N11,FV($V$3,$N11-1,,-$T11,0),0) -> 0 | P61: =IF(P$56=$N11,FV($V$3,$N11-1,,-$T11,0),0) -> 0 | R61: =IF(R$56=$N11,FV($V$3,$N11-1,,-$T11,0),0) -> 0 | T61: =IF(T$56=$N11,FV($V$3,$N11-1,,-$T11,0),0) -> 0 | V61: =IF(V$56=$N11,FV($V$3,$N11-1,,-$T11,0),0) -> 0 | X61: =IF(X$56=$N11,FV($V$3,$N11-1,,-$T11,0),0) -> 0 | Z61: =IF(Z$56=$N11,FV($V$3,$N11-1,,-$T11,0),0) -> 0 | AB61: =IF(AB$56=$N11,FV($V$3,$N11-1,,-$T11,0),0) -> 0 | AD61: =IF(AD$56=$N11,FV($V$3,$N11-1,,-$T11,0),0) -> 0 | AF61: =IF(AF$56=$N11,FV($V$3,$N11-1,,-$T11,0),0) -> 0 | AH61: =IF(AH$56=$N11,FV($V$3,$N11-1,,-$T11,0),0) -> 0 | AJ61: =IF(AJ$56=$N11,FV($V$3,$N11-1,,-$T11,0),0) -> 0 | AL61: =IF(AL$56=$N11,FV($V$3,$N11-1,,-$T11,0),0) -> 0
B62: =+B12 -> 2 | D62: =+D12 -> 1 | F62: =+F12 -> x | H62: =+H12 -> x | J62: =IF(J$56=$N12,FV($V$3,$N12-1,,-$T12,0),0) -> 0 | L62: =IF(L$56=$N12,FV($V$3,$N12-1,,-$T12,0),0) -> 0 | N62: =IF(N$56=$N12,FV($V$3,$N12-1,,-$T12,0),0) -> 0 | P62: =IF(P$56=$N12,FV($V$3,$N12-1,,-$T12,0),0) -> 0 | R62: =IF(R$56=$N12,FV($V$3,$N12-1,,-$T12,0),0) -> 0 | T62: =IF(T$56=$N12,FV($V$3,$N12-1,,-$T12,0),0) -> 0 | V62: =IF(V$56=$N12,FV($V$3,$N12-1,,-$T12,0),0) -> 0 | X62: =IF(X$56=$N12,FV($V$3,$N12-1,,-$T12,0),0) -> 0 | Z62: =IF(Z$56=$N12,FV($V$3,$N12-1,,-$T12,0),0) -> 0 | AB62: =IF(AB$56=$N12,FV($V$3,$N12-1,,-$T12,0),0) -> 0 | AD62: =IF(AD$56=$N12,FV($V$3,$N12-1,,-$T12,0),0) -> 0 | AF62: =IF(AF$56=$N12,FV($V$3,$N12-1,,-$T12,0),0) -> 0 | AH62: =IF(AH$56=$N12,FV($V$3,$N12-1,,-$T12,0),0) -> 0 | AJ62: =IF(AJ$56=$N12,FV($V$3,$N12-1,,-$T12,0),0) -> 0 | AL62: =IF(AL$56=$N12,FV($V$3,$N12-1,,-$T12,0),0) -> 0
B63: =+B13 -> 3 | D63: =+D13 -> 1 | F63: =+F13 -> x | H63: =+H13 -> x | J63: =IF(J$56=$N13,FV($V$3,$N13-1,,-$T13,0),0) -> 0 | L63: =IF(L$56=$N13,FV($V$3,$N13-1,,-$T13,0),0) -> 0 | N63: =IF(N$56=$N13,FV($V$3,$N13-1,,-$T13,0),0) -> 0 | P63: =IF(P$56=$N13,FV($V$3,$N13-1,,-$T13,0),0) -> 0 | R63: =IF(R$56=$N13,FV($V$3,$N13-1,,-$T13,0),0) -> 0 | T63: =IF(T$56=$N13,FV($V$3,$N13-1,,-$T13,0),0) -> 0 | V63: =IF(V$56=$N13,FV($V$3,$N13-1,,-$T13,0),0) -> 0 | X63: =IF(X$56=$N13,FV($V$3,$N13-1,,-$T13,0),0) -> 0 | Z63: =IF(Z$56=$N13,FV($V$3,$N13-1,,-$T13,0),0) -> 0 | AB63: =IF(AB$56=$N13,FV($V$3,$N13-1,,-$T13,0),0) -> 0 | AD63: =IF(AD$56=$N13,FV($V$3,$N13-1,,-$T13,0),0) -> 0 | AF63: =IF(AF$56=$N13,FV($V$3,$N13-1,,-$T13,0),0) -> 0 | AH63: =IF(AH$56=$N13,FV($V$3,$N13-1,,-$T13,0),0) -> 0 | AJ63: =IF(AJ$56=$N13,FV($V$3,$N13-1,,-$T13,0),0) -> 0 | AL63: =IF(AL$56=$N13,FV($V$3,$N13-1,,-$T13,0),0) -> 0
B64: =+B14 -> 4 | D64: =+D14 -> 1 | F64: =+F14 -> x | H64: =+H14 -> x | J64: =IF(J$56=$N14,FV($V$3,$N14-1,,-$T14,0),0) -> 0 | L64: =IF(L$56=$N14,FV($V$3,$N14-1,,-$T14,0),0) -> 0 | N64: =IF(N$56=$N14,FV($V$3,$N14-1,,-$T14,0),0) -> 0 | P64: =IF(P$56=$N14,FV($V$3,$N14-1,,-$T14,0),0) -> 0 | R64: =IF(R$56=$N14,FV($V$3,$N14-1,,-$T14,0),0) -> 0 | T64: =IF(T$56=$N14,FV($V$3,$N14-1,,-$T14,0),0) -> 0 | V64: =IF(V$56=$N14,FV($V$3,$N14-1,,-$T14,0),0) -> 0 | X64: =IF(X$56=$N14,FV($V$3,$N14-1,,-$T14,0),0) -> 0 | Z64: =IF(Z$56=$N14,FV($V$3,$N14-1,,-$T14,0),0) -> 0 | AB64: =IF(AB$56=$N14,FV($V$3,$N14-1,,-$T14,0),0) -> 0 | AD64: =IF(AD$56=$N14,FV($V$3,$N14-1,,-$T14,0),0) -> 0 | AF64: =IF(AF$56=$N14,FV($V$3,$N14-1,,-$T14,0),0) -> 0 | AH64: =IF(AH$56=$N14,FV($V$3,$N14-1,,-$T14,0),0) -> 0 | AJ64: =IF(AJ$56=$N14,FV($V$3,$N14-1,,-$T14,0),0) -> 0 | AL64: =IF(AL$56=$N14,FV($V$3,$N14-1,,-$T14,0),0) -> 0
B65: =+B15 -> 5 | D65: =+D15 -> 1 | F65: =+F15 -> x | H65: =+H15 -> x | J65: =IF(J$56=$N15,FV($V$3,$N15-1,,-$T15,0),0) -> 0 | L65: =IF(L$56=$N15,FV($V$3,$N15-1,,-$T15,0),0) -> 0 | N65: =IF(N$56=$N15,FV($V$3,$N15-1,,-$T15,0),0) -> 0 | P65: =IF(P$56=$N15,FV($V$3,$N15-1,,-$T15,0),0) -> 0 | R65: =IF(R$56=$N15,FV($V$3,$N15-1,,-$T15,0),0) -> 0 | T65: =IF(T$56=$N15,FV($V$3,$N15-1,,-$T15,0),0) -> 0 | V65: =IF(V$56=$N15,FV($V$3,$N15-1,,-$T15,0),0) -> 0 | X65: =IF(X$56=$N15,FV($V$3,$N15-1,,-$T15,0),0) -> 0 | Z65: =IF(Z$56=$N15,FV($V$3,$N15-1,,-$T15,0),0) -> 0 | AB65: =IF(AB$56=$N15,FV($V$3,$N15-1,,-$T15,0),0) -> 0 | AD65: =IF(AD$56=$N15,FV($V$3,$N15-1,,-$T15,0),0) -> 0 | AF65: =IF(AF$56=$N15,FV($V$3,$N15-1,,-$T15,0),0) -> 0 | AH65: =IF(AH$56=$N15,FV($V$3,$N15-1,,-$T15,0),0) -> 0 | AJ65: =IF(AJ$56=$N15,FV($V$3,$N15-1,,-$T15,0),0) -> 0 | AL65: =IF(AL$56=$N15,FV($V$3,$N15-1,,-$T15,0),0) -> 0
B66: =+B16 -> 6 | D66: =+D16 -> 1 | F66: =+F16 -> x | H66: =+H16 -> x | J66: =IF(J$56=$N16,FV($V$3,$N16-1,,-$T16,0),0) -> 0 | L66: =IF(L$56=$N16,FV($V$3,$N16-1,,-$T16,0),0) -> 0 | N66: =IF(N$56=$N16,FV($V$3,$N16-1,,-$T16,0),0) -> 0 | P66: =IF(P$56=$N16,FV($V$3,$N16-1,,-$T16,0),0) -> 0 | R66: =IF(R$56=$N16,FV($V$3,$N16-1,,-$T16,0),0) -> 0 | T66: =IF(T$56=$N16,FV($V$3,$N16-1,,-$T16,0),0) -> 0 | V66: =IF(V$56=$N16,FV($V$3,$N16-1,,-$T16,0),0) -> 0 | X66: =IF(X$56=$N16,FV($V$3,$N16-1,,-$T16,0),0) -> 0 | Z66: =IF(Z$56=$N16,FV($V$3,$N16-1,,-$T16,0),0) -> 0 | AB66: =IF(AB$56=$N16,FV($V$3,$N16-1,,-$T16,0),0) -> 0 | AD66: =IF(AD$56=$N16,FV($V$3,$N16-1,,-$T16,0),0) -> 0 | AF66: =IF(AF$56=$N16,FV($V$3,$N16-1,,-$T16,0),0) -> 0 | AH66: =IF(AH$56=$N16,FV($V$3,$N16-1,,-$T16,0),0) -> 0 | AJ66: =IF(AJ$56=$N16,FV($V$3,$N16-1,,-$T16,0),0) -> 0 | AL66: =IF(AL$56=$N16,FV($V$3,$N16-1,,-$T16,0),0) -> 0
B67: =+B17 -> 7 | D67: =+D17 -> 1 | F67: =+F17 -> x | H67: =+H17 -> x | J67: =IF(J$56=$N17,FV($V$3,$N17-1,,-$T17,0),0) -> 0 | L67: =IF(L$56=$N17,FV($V$3,$N17-1,,-$T17,0),0) -> 0 | N67: =IF(N$56=$N17,FV($V$3,$N17-1,,-$T17,0),0) -> 0 | P67: =IF(P$56=$N17,FV($V$3,$N17-1,,-$T17,0),0) -> 0 | R67: =IF(R$56=$N17,FV($V$3,$N17-1,,-$T17,0),0) -> 0 | T67: =IF(T$56=$N17,FV($V$3,$N17-1,,-$T17,0),0) -> 0 | V67: =IF(V$56=$N17,FV($V$3,$N17-1,,-$T17,0),0) -> 0 | X67: =IF(X$56=$N17,FV($V$3,$N17-1,,-$T17,0),0) -> 0 | Z67: =IF(Z$56=$N17,FV($V$3,$N17-1,,-$T17,0),0) -> 0 | AB67: =IF(AB$56=$N17,FV($V$3,$N17-1,,-$T17,0),0) -> 0 | AD67: =IF(AD$56=$N17,FV($V$3,$N17-1,,-$T17,0),0) -> 0 | AF67: =IF(AF$56=$N17,FV($V$3,$N17-1,,-$T17,0),0) -> 0 | AH67: =IF(AH$56=$N17,FV($V$3,$N17-1,,-$T17,0),0) -> 0 | AJ67: =IF(AJ$56=$N17,FV($V$3,$N17-1,,-$T17,0),0) -> 0 | AL67: =IF(AL$56=$N17,FV($V$3,$N17-1,,-$T17,0),0) -> 0
B68: =+B18 -> 8 | D68: =+D18 -> 1 | F68: =+F18 -> x | H68: =+H18 -> x | J68: =IF(J$56=$N18,FV($V$3,$N18-1,,-$T18,0),0) -> 0 | L68: =IF(L$56=$N18,FV($V$3,$N18-1,,-$T18,0),0) -> 0 | N68: =IF(N$56=$N18,FV($V$3,$N18-1,,-$T18,0),0) -> 0 | P68: =IF(P$56=$N18,FV($V$3,$N18-1,,-$T18,0),0) -> 0 | R68: =IF(R$56=$N18,FV($V$3,$N18-1,,-$T18,0),0) -> 0 | T68: =IF(T$56=$N18,FV($V$3,$N18-1,,-$T18,0),0) -> 0 | V68: =IF(V$56=$N18,FV($V$3,$N18-1,,-$T18,0),0) -> 0 | X68: =IF(X$56=$N18,FV($V$3,$N18-1,,-$T18,0),0) -> 0 | Z68: =IF(Z$56=$N18,FV($V$3,$N18-1,,-$T18,0),0) -> 0 | AB68: =IF(AB$56=$N18,FV($V$3,$N18-1,,-$T18,0),0) -> 0 | AD68: =IF(AD$56=$N18,FV($V$3,$N18-1,,-$T18,0),0) -> 0 | AF68: =IF(AF$56=$N18,FV($V$3,$N18-1,,-$T18,0),0) -> 0 | AH68: =IF(AH$56=$N18,FV($V$3,$N18-1,,-$T18,0),0) -> 0 | AJ68: =IF(AJ$56=$N18,FV($V$3,$N18-1,,-$T18,0),0) -> 0 | AL68: =IF(AL$56=$N18,FV($V$3,$N18-1,,-$T18,0),0) -> 0
B69: =+B19 -> 9 | D69: =+D19 -> 1 | F69: =+F19 -> x | H69: =+H19 -> x | J69: =IF(J$56=$N19,FV($V$3,$N19-1,,-$T19,0),0) -> 0 | L69: =IF(L$56=$N19,FV($V$3,$N19-1,,-$T19,0),0) -> 0 | N69: =IF(N$56=$N19,FV($V$3,$N19-1,,-$T19,0),0) -> 0 | P69: =IF(P$56=$N19,FV($V$3,$N19-1,,-$T19,0),0) -> 0 | R69: =IF(R$56=$N19,FV($V$3,$N19-1,,-$T19,0),0) -> 0 | T69: =IF(T$56=$N19,FV($V$3,$N19-1,,-$T19,0),0) -> 0 | V69: =IF(V$56=$N19,FV($V$3,$N19-1,,-$T19,0),0) -> 0 | X69: =IF(X$56=$N19,FV($V$3,$N19-1,,-$T19,0),0) -> 0 | Z69: =IF(Z$56=$N19,FV($V$3,$N19-1,,-$T19,0),0) -> 0 | AB69: =IF(AB$56=$N19,FV($V$3,$N19-1,,-$T19,0),0) -> 0 | AD69: =IF(AD$56=$N19,FV($V$3,$N19-1,,-$T19,0),0) -> 0 | AF69: =IF(AF$56=$N19,FV($V$3,$N19-1,,-$T19,0),0) -> 0 | AH69: =IF(AH$56=$N19,FV($V$3,$N19-1,,-$T19,0),0) -> 0 | AJ69: =IF(AJ$56=$N19,FV($V$3,$N19-1,,-$T19,0),0) -> 0 | AL69: =IF(AL$56=$N19,FV($V$3,$N19-1,,-$T19,0),0) -> 0
B70: =+B20 -> 10 | D70: =+D20 -> 1 | F70: =+F20 -> x | H70: =+H20 -> x | J70: =IF(J$56=$N20,FV($V$3,$N20-1,,-$T20,0),0) -> 0 | L70: =IF(L$56=$N20,FV($V$3,$N20-1,,-$T20,0),0) -> 0 | N70: =IF(N$56=$N20,FV($V$3,$N20-1,,-$T20,0),0) -> 0 | P70: =IF(P$56=$N20,FV($V$3,$N20-1,,-$T20,0),0) -> 0 | R70: =IF(R$56=$N20,FV($V$3,$N20-1,,-$T20,0),0) -> 0 | T70: =IF(T$56=$N20,FV($V$3,$N20-1,,-$T20,0),0) -> 0 | V70: =IF(V$56=$N20,FV($V$3,$N20-1,,-$T20,0),0) -> 0 | X70: =IF(X$56=$N20,FV($V$3,$N20-1,,-$T20,0),0) -> 0 | Z70: =IF(Z$56=$N20,FV($V$3,$N20-1,,-$T20,0),0) -> 0 | AB70: =IF(AB$56=$N20,FV($V$3,$N20-1,,-$T20,0),0) -> 0 | AD70: =IF(AD$56=$N20,FV($V$3,$N20-1,,-$T20,0),0) -> 0 | AF70: =IF(AF$56=$N20,FV($V$3,$N20-1,,-$T20,0),0) -> 0 | AH70: =IF(AH$56=$N20,FV($V$3,$N20-1,,-$T20,0),0) -> 0 | AJ70: =IF(AJ$56=$N20,FV($V$3,$N20-1,,-$T20,0),0) -> 0 | AL70: =IF(AL$56=$N20,FV($V$3,$N20-1,,-$T20,0),0) -> 0
B71: =+B21 -> 11 | D71: =+D21 -> 1 | F71: =+F21 -> x | H71: =+H21 -> x | J71: =IF(J$56=$N21,FV($V$3,$N21-1,,-$T21,0),0) -> 0 | L71: =IF(L$56=$N21,FV($V$3,$N21-1,,-$T21,0),0) -> 0 | N71: =IF(N$56=$N21,FV($V$3,$N21-1,,-$T21,0),0) -> 0 | P71: =IF(P$56=$N21,FV($V$3,$N21-1,,-$T21,0),0) -> 0 | R71: =IF(R$56=$N21,FV($V$3,$N21-1,,-$T21,0),0) -> 0 | T71: =IF(T$56=$N21,FV($V$3,$N21-1,,-$T21,0),0) -> 0 | V71: =IF(V$56=$N21,FV($V$3,$N21-1,,-$T21,0),0) -> 0 | X71: =IF(X$56=$N21,FV($V$3,$N21-1,,-$T21,0),0) -> 0 | Z71: =IF(Z$56=$N21,FV($V$3,$N21-1,,-$T21,0),0) -> 0 | AB71: =IF(AB$56=$N21,FV($V$3,$N21-1,,-$T21,0),0) -> 0 | AD71: =IF(AD$56=$N21,FV($V$3,$N21-1,,-$T21,0),0) -> 0 | AF71: =IF(AF$56=$N21,FV($V$3,$N21-1,,-$T21,0),0) -> 0 | AH71: =IF(AH$56=$N21,FV($V$3,$N21-1,,-$T21,0),0) -> 0 | AJ71: =IF(AJ$56=$N21,FV($V$3,$N21-1,,-$T21,0),0) -> 0 | AL71: =IF(AL$56=$N21,FV($V$3,$N21-1,,-$T21,0),0) -> 0
B72: =+B22 -> 12 | D72: =+D22 -> 1 | F72: =+F22 -> x | H72: =+H22 -> x | J72: =IF(J$56=$N22,FV($V$3,$N22-1,,-$T22,0),0) -> 0 | L72: =IF(L$56=$N22,FV($V$3,$N22-1,,-$T22,0),0) -> 0 | N72: =IF(N$56=$N22,FV($V$3,$N22-1,,-$T22,0),0) -> 0 | P72: =IF(P$56=$N22,FV($V$3,$N22-1,,-$T22,0),0) -> 0 | R72: =IF(R$56=$N22,FV($V$3,$N22-1,,-$T22,0),0) -> 0 | T72: =IF(T$56=$N22,FV($V$3,$N22-1,,-$T22,0),0) -> 0 | V72: =IF(V$56=$N22,FV($V$3,$N22-1,,-$T22,0),0) -> 0 | X72: =IF(X$56=$N22,FV($V$3,$N22-1,,-$T22,0),0) -> 0 | Z72: =IF(Z$56=$N22,FV($V$3,$N22-1,,-$T22,0),0) -> 0 | AB72: =IF(AB$56=$N22,FV($V$3,$N22-1,,-$T22,0),0) -> 0 | AD72: =IF(AD$56=$N22,FV($V$3,$N22-1,,-$T22,0),0) -> 0 | AF72: =IF(AF$56=$N22,FV($V$3,$N22-1,,-$T22,0),0) -> 0 | AH72: =IF(AH$56=$N22,FV($V$3,$N22-1,,-$T22,0),0) -> 0 | AJ72: =IF(AJ$56=$N22,FV($V$3,$N22-1,,-$T22,0),0) -> 0 | AL72: =IF(AL$56=$N22,FV($V$3,$N22-1,,-$T22,0),0) -> 0
... B100: =+B50 -> 40 | D100: =+D50 -> 1 | F100: =+F50 -> x | H100: =+H50 -> x | J100: =IF(J$56=$N50,FV($V$3,$N50-1,,-$T50,0),0) -> 0 | L100: =IF(L$56=$N50,FV($V$3,$N50-1,,-$T50,0),0) -> 0 | N100: =IF(N$56=$N50,FV($V$3,$N50-1,,-$T50,0),0) -> 0 | P100: =IF(P$56=$N50,FV($V$3,$N50-1,,-$T50,0),0) -> 0 | R100: =IF(R$56=$N50,FV($V$3,$N50-1,,-$T50,0),0) -> 0 | T100: =IF(T$56=$N50,FV($V$3,$N50-1,,-$T50,0),0) -> 0 | V100: =IF(V$56=$N50,FV($V$3,$N50-1,,-$T50,0),0) -> 0 | X100: =IF(X$56=$N50,FV($V$3,$N50-1,,-$T50,0),0) -> 0 | Z100: =IF(Z$56=$N50,FV($V$3,$N50-1,,-$T50,0),0) -> 0 | AB100: =IF(AB$56=$N50,FV($V$3,$N50-1,,-$T50,0),0) -> 0 | AD100: =IF(AD$56=$N50,FV($V$3,$N50-1,,-$T50,0),0) -> 0 | AF100: =IF(AF$56=$N50,FV($V$3,$N50-1,,-$T50,0),0) -> 0 | AH100: =IF(AH$56=$N50,FV($V$3,$N50-1,,-$T50,0),0) -> 0 | AJ100: =IF(AJ$56=$N50,FV($V$3,$N50-1,,-$T50,0),0) -> 0 | AL100: =IF(AL$56=$N50,FV($V$3,$N50-1,,-$T50,0),0) -> 0
H102: =+H52 -> Anticipated Expenditures, By Year | J102: =SUM(J61:J100) -> 0 | L102: =SUM(L61:L100) -> 0 | N102: =SUM(N61:N100) -> 0 | P102: =SUM(P61:P100) -> 0 | R102: =SUM(R61:R100) -> 0 | T102: =SUM(T61:T100) -> 0 | V102: =SUM(V61:V100) -> 0 | X102: =SUM(X61:X100) -> 0 | Z102: =SUM(Z61:Z100) -> 0 | AB102: =SUM(AB61:AB100) -> 0 | AD102: =SUM(AD61:AD100) -> 0 | AF102: =SUM(AF61:AF100) -> 0 | AH102: =SUM(AH61:AH100) -> 0 | AJ102: =SUM(AJ61:AJ100) -> 0 | AL102: =SUM(AL61:AL100) -> 0

Sheet Combo 1
G3: Exhibit B
G5: RESERVE EXPENDITURES | U5: Explanatory Notes:
G6: for | T6: 1) | U6: =+'Roofs 1'!V3 -> 0.03 | V6: is the estimated future Inflation Rate for estimating Future Replacement Costs.
G7: ='Funding Plan'!G9 -> Association | T7: 2) | U7: Fiscal Year is beginning January 1 and ending December 31.
A9: Line Item | C9: Estimated | I9: Estimated Year Last Replaced | K9: Life Analysis, Years | O9: Estimated Year of 1st Replacement | Q9: =+'Roofs 1'!R6 -> 2024 Unit Cost | S9: =+'Roofs 1'!T6 -> 2024 Cost of Replacement | U9: Total Future Cost of Replacement | W9: 1 | Y9: 2 | AA9: 3 | AC9: 4 | AE9: 5 | AG9: 6 | AI9: 7 | AK9: 8 | AM9: 9 | AO9: 10 | AQ9: 11 | AS9: 12 | AU9: 13 | AW9: 14 | AY9: 15
C10: Quantity | E10: Units | G10: Reserve Component Inventory | K10: Useful | M10: Remaining | W10: =+'Roofs 1'!X7 -> 2024 | Y10: =W10+1 -> 2025 | Z10: =X10+1 -> 1 | AA10: =Y10+1 -> 2026 | AB10: =Z10+1 -> 2 | AC10: =AA10+1 -> 2027 | AD10: =AB10+1 -> 3 | AE10: =AC10+1 -> 2028 | AF10: =AD10+1 -> 4 | ... AY10: =AW10+1 -> 2038
G12: ELEMENTS REPLACE | X12: =+'Roofs 1'!Y9 -> 0 | Z12: =+'Roofs 1'!AA9 -> 0
A14: 1 | C14: 1 | E14: x | G14: x | I14: x | K14: x | M14: 1 | N14: ='Roofs 1'!P4 -> 2023 | O14: =+$W$10-1+M14 -> 2024 | Q14: 1 | S14: =C14*Q14 -> 1 | U14: =SUM(W14:AY14)+SUM(I64:AK64) -> 1 | W14: =IF(W$9=$M14,FV($U$6,$M14-1,,-$S14,0),0) -> 1 | Y14: =IF(Y$9=$M14,FV($U$6,$M14-1,,-$S14,0),0) -> 0 | AA14: =IF(AA$9=$M14,FV($U$6,$M14-1,,-$S14,0),0) -> 0 | AC14: =IF(AC$9=$M14,FV($U$6,$M14-1,,-$S14,0),0) -> 0 | AE14: =IF(AE$9=$M14,FV($U$6,$M14-1,,-$S14,0),0) -> 0 | AG14: =IF(AG$9=$M14,FV($U$6,$M14-1,,-$S14,0),0) -> 0 | AI14: =IF(AI$9=$M14,FV($U$6,$M14-1,,-$S14,0),0) -> 0 | AK14: =IF(AK$9=$M14,FV($U$6,$M14-1,,-$S14,0),0) -> 0 | AM14: =IF(AM$9=$M14,FV($U$6,$M14-1,,-$S14,0),0) -> 0 | AO14: =IF(AO$9=$M14,FV($U$6,$M14-1,,-$S14,0),0) -> 0 | AQ14: =IF(AQ$9=$M14,FV($U$6,$M14-1,,-$S14,0),0) -> 0 | AS14: =IF(AS$9=$M14,FV($U$6,$M14-1,,-$S14,0),0) -> 0 | AU14: =IF(AU$9=$M14,FV($U$6,$M14-1,,-$S14,0),0) -> 0 | AW14: =IF(AW$9=$M14,FV($U$6,$M14-1,,-$S14,0),0) -> 0 | AY14: =IF(AY$9=$M14,FV($U$6,$M14-1,,-$S14,0),0) -> 0
A15: =A14+1 -> 2 | C15: 1 | E15: x | G15: x | I15: x | K15: x | M15: 1 | N15: =N14 -> 2023 | O15: =+$W$10-1+M15 -> 2024 | Q15: 1 | S15: =C15*Q15 -> 1 | U15: =SUM(W15:AY15)+SUM(I65:AK65) -> 1 | W15: =IF(W$9=$M15,FV($U$6,$M15-1,,-$S15,0),0) -> 1 | Y15: =IF(Y$9=$M15,FV($U$6,$M15-1,,-$S15,0),0) -> 0 | AA15: =IF(AA$9=$M15,FV($U$6,$M15-1,,-$S15,0),0) -> 0 | AC15: =IF(AC$9=$M15,FV($U$6,$M15-1,,-$S15,0),0) -> 0 | AE15: =IF(AE$9=$M15,FV($U$6,$M15-1,,-$S15,0),0) -> 0 | AG15: =IF(AG$9=$M15,FV($U$6,$M15-1,,-$S15,0),0) -> 0 | AI15: =IF(AI$9=$M15,FV($U$6,$M15-1,,-$S15,0),0) -> 0 | AK15: =IF(AK$9=$M15,FV($U$6,$M15-1,,-$S15,0),0) -> 0 | AM15: =IF(AM$9=$M15,FV($U$6,$M15-1,,-$S15,0),0) -> 0 | AO15: =IF(AO$9=$M15,FV($U$6,$M15-1,,-$S15,0),0) -> 0 | AQ15: =IF(AQ$9=$M15,FV($U$6,$M15-1,,-$S15,0),0) -> 0 | AS15: =IF(AS$9=$M15,FV($U$6,$M15-1,,-$S15,0),0) -> 0 | AU15: =IF(AU$9=$M15,FV($U$6,$M15-1,,-$S15,0),0) -> 0 | AW15: =IF(AW$9=$M15,FV($U$6,$M15-1,,-$S15,0),0) -> 0 | AY15: =IF(AY$9=$M15,FV($U$6,$M15-1,,-$S15,0),0) -> 0
A16: =A15+1 -> 3 | C16: 1 | E16: x | G16: x | I16: x | K16: x | M16: 1 | N16: =N15 -> 2023 | O16: =+$W$10-1+M16 -> 2024 | Q16: 1 | S16: =C16*Q16 -> 1 | U16: =SUM(W16:AY16)+SUM(I66:AK66) -> 1 | W16: =IF(W$9=$M16,FV($U$6,$M16-1,,-$S16,0),0) -> 1 | Y16: =IF(Y$9=$M16,FV($U$6,$M16-1,,-$S16,0),0) -> 0 | AA16: =IF(AA$9=$M16,FV($U$6,$M16-1,,-$S16,0),0) -> 0 | AC16: =IF(AC$9=$M16,FV($U$6,$M16-1,,-$S16,0),0) -> 0 | AE16: =IF(AE$9=$M16,FV($U$6,$M16-1,,-$S16,0),0) -> 0 | AG16: =IF(AG$9=$M16,FV($U$6,$M16-1,,-$S16,0),0) -> 0 | AI16: =IF(AI$9=$M16,FV($U$6,$M16-1,,-$S16,0),0) -> 0 | AK16: =IF(AK$9=$M16,FV($U$6,$M16-1,,-$S16,0),0) -> 0 | AM16: =IF(AM$9=$M16,FV($U$6,$M16-1,,-$S16,0),0) -> 0 | AO16: =IF(AO$9=$M16,FV($U$6,$M16-1,,-$S16,0),0) -> 0 | AQ16: =IF(AQ$9=$M16,FV($U$6,$M16-1,,-$S16,0),0) -> 0 | AS16: =IF(AS$9=$M16,FV($U$6,$M16-1,,-$S16,0),0) -> 0 | AU16: =IF(AU$9=$M16,FV($U$6,$M16-1,,-$S16,0),0) -> 0 | AW16: =IF(AW$9=$M16,FV($U$6,$M16-1,,-$S16,0),0) -> 0 | AY16: =IF(AY$9=$M16,FV($U$6,$M16-1,,-$S16,0),0) -> 0
A17: =A16+1 -> 4 | C17: 1 | E17: x | G17: x | I17: x | K17: x | M17: 1 | N17: =N16 -> 2023 | O17: =+$W$10-1+M17 -> 2024 | Q17: 1 | S17: =C17*Q17 -> 1 | U17: =SUM(W17:AY17)+SUM(I67:AK67) -> 1 | W17: =IF(W$9=$M17,FV($U$6,$M17-1,,-$S17,0),0) -> 1 | Y17: =IF(Y$9=$M17,FV($U$6,$M17-1,,-$S17,0),0) -> 0 | AA17: =IF(AA$9=$M17,FV($U$6,$M17-1,,-$S17,0),0) -> 0 | AC17: =IF(AC$9=$M17,FV($U$6,$M17-1,,-$S17,0),0) -> 0 | AE17: =IF(AE$9=$M17,FV($U$6,$M17-1,,-$S17,0),0) -> 0 | AG17: =IF(AG$9=$M17,FV($U$6,$M17-1,,-$S17,0),0) -> 0 | AI17: =IF(AI$9=$M17,FV($U$6,$M17-1,,-$S17,0),0) -> 0 | AK17: =IF(AK$9=$M17,FV($U$6,$M17-1,,-$S17,0),0) -> 0 | AM17: =IF(AM$9=$M17,FV($U$6,$M17-1,,-$S17,0),0) -> 0 | AO17: =IF(AO$9=$M17,FV($U$6,$M17-1,,-$S17,0),0) -> 0 | AQ17: =IF(AQ$9=$M17,FV($U$6,$M17-1,,-$S17,0),0) -> 0 | AS17: =IF(AS$9=$M17,FV($U$6,$M17-1,,-$S17,0),0) -> 0 | AU17: =IF(AU$9=$M17,FV($U$6,$M17-1,,-$S17,0),0) -> 0 | AW17: =IF(AW$9=$M17,FV($U$6,$M17-1,,-$S17,0),0) -> 0 | AY17: =IF(AY$9=$M17,FV($U$6,$M17-1,,-$S17,0),0) -> 0
A18: =A17+1 -> 5 | C18: 1 | E18: x | G18: x | I18: x | K18: x | M18: 1 | N18: =N17 -> 2023 | O18: =+$W$10-1+M18 -> 2024 | Q18: 1 | S18: =C18*Q18 -> 1 | U18: =SUM(W18:AY18)+SUM(I68:AK68) -> 1 | W18: =IF(W$9=$M18,FV($U$6,$M18-1,,-$S18,0),0) -> 1 | Y18: =IF(Y$9=$M18,FV($U$6,$M18-1,,-$S18,0),0) -> 0 | AA18: =IF(AA$9=$M18,FV($U$6,$M18-1,,-$S18,0),0) -> 0 | AC18: =IF(AC$9=$M18,FV($U$6,$M18-1,,-$S18,0),0) -> 0 | AE18: =IF(AE$9=$M18,FV($U$6,$M18-1,,-$S18,0),0) -> 0 | AG18: =IF(AG$9=$M18,FV($U$6,$M18-1,,-$S18,0),0) -> 0 | AI18: =IF(AI$9=$M18,FV($U$6,$M18-1,,-$S18,0),0) -> 0 | AK18: =IF(AK$9=$M18,FV($U$6,$M18-1,,-$S18,0),0) -> 0 | AM18: =IF(AM$9=$M18,FV($U$6,$M18-1,,-$S18,0),0) -> 0 | AO18: =IF(AO$9=$M18,FV($U$6,$M18-1,,-$S18,0),0) -> 0 | AQ18: =IF(AQ$9=$M18,FV($U$6,$M18-1,,-$S18,0),0) -> 0 | AS18: =IF(AS$9=$M18,FV($U$6,$M18-1,,-$S18,0),0) -> 0 | AU18: =IF(AU$9=$M18,FV($U$6,$M18-1,,-$S18,0),0) -> 0 | AW18: =IF(AW$9=$M18,FV($U$6,$M18-1,,-$S18,0),0) -> 0 | AY18: =IF(AY$9=$M18,FV($U$6,$M18-1,,-$S18,0),0) -> 0
A19: =A18+1 -> 6 | C19: 1 | E19: x | G19: x | I19: x | K19: x | M19: 1 | N19: =N18 -> 2023 | O19: =+$W$10-1+M19 -> 2024 | Q19: 1 | S19: =C19*Q19 -> 1 | U19: =SUM(W19:AY19)+SUM(I69:AK69) -> 1 | W19: =IF(W$9=$M19,FV($U$6,$M19-1,,-$S19,0),0) -> 1 | Y19: =IF(Y$9=$M19,FV($U$6,$M19-1,,-$S19,0),0) -> 0 | AA19: =IF(AA$9=$M19,FV($U$6,$M19-1,,-$S19,0),0) -> 0 | AC19: =IF(AC$9=$M19,FV($U$6,$M19-1,,-$S19,0),0) -> 0 | AE19: =IF(AE$9=$M19,FV($U$6,$M19-1,,-$S19,0),0) -> 0 | AG19: =IF(AG$9=$M19,FV($U$6,$M19-1,,-$S19,0),0) -> 0 | AI19: =IF(AI$9=$M19,FV($U$6,$M19-1,,-$S19,0),0) -> 0 | AK19: =IF(AK$9=$M19,FV($U$6,$M19-1,,-$S19,0),0) -> 0 | AM19: =IF(AM$9=$M19,FV($U$6,$M19-1,,-$S19,0),0) -> 0 | AO19: =IF(AO$9=$M19,FV($U$6,$M19-1,,-$S19,0),0) -> 0 | AQ19: =IF(AQ$9=$M19,FV($U$6,$M19-1,,-$S19,0),0) -> 0 | AS19: =IF(AS$9=$M19,FV($U$6,$M19-1,,-$S19,0),0) -> 0 | AU19: =IF(AU$9=$M19,FV($U$6,$M19-1,,-$S19,0),0) -> 0 | AW19: =IF(AW$9=$M19,FV($U$6,$M19-1,,-$S19,0),0) -> 0 | AY19: =IF(AY$9=$M19,FV($U$6,$M19-1,,-$S19,0),0) -> 0
A20: =A19+1 -> 7 | C20: 1 | E20: x | G20: x | I20: x | K20: x | M20: 1 | N20: =N19 -> 2023 | O20: =+$W$10-1+M20 -> 2024 | Q20: 1 | S20: =C20*Q20 -> 1 | U20: =SUM(W20:AY20)+SUM(I70:AK70) -> 1 | W20: =IF(W$9=$M20,FV($U$6,$M20-1,,-$S20,0),0) -> 1 | Y20: =IF(Y$9=$M20,FV($U$6,$M20-1,,-$S20,0),0) -> 0 | AA20: =IF(AA$9=$M20,FV($U$6,$M20-1,,-$S20,0),0) -> 0 | AC20: =IF(AC$9=$M20,FV($U$6,$M20-1,,-$S20,0),0) -> 0 | AE20: =IF(AE$9=$M20,FV($U$6,$M20-1,,-$S20,0),0) -> 0 | AG20: =IF(AG$9=$M20,FV($U$6,$M20-1,,-$S20,0),0) -> 0 | AI20: =IF(AI$9=$M20,FV($U$6,$M20-1,,-$S20,0),0) -> 0 | AK20: =IF(AK$9=$M20,FV($U$6,$M20-1,,-$S20,0),0) -> 0 | AM20: =IF(AM$9=$M20,FV($U$6,$M20-1,,-$S20,0),0) -> 0 | AO20: =IF(AO$9=$M20,FV($U$6,$M20-1,,-$S20,0),0) -> 0 | AQ20: =IF(AQ$9=$M20,FV($U$6,$M20-1,,-$S20,0),0) -> 0 | AS20: =IF(AS$9=$M20,FV($U$6,$M20-1,,-$S20,0),0) -> 0 | AU20: =IF(AU$9=$M20,FV($U$6,$M20-1,,-$S20,0),0) -> 0 | AW20: =IF(AW$9=$M20,FV($U$6,$M20-1,,-$S20,0),0) -> 0 | AY20: =IF(AY$9=$M20,FV($U$6,$M20-1,,-$S20,0),0) -> 0
A21: =A20+1 -> 8 | C21: 1 | E21: x | G21: x | I21: x | K21: x | M21: 1 | N21: =N20 -> 2023 | O21: =+$W$10-1+M21 -> 2024 | Q21: 1 | S21: =C21*Q21 -> 1 | U21: =SUM(W21:AY21)+SUM(I71:AK71) -> 1 | W21: =IF(W$9=$M21,FV($U$6,$M21-1,,-$S21,0),0) -> 1 | Y21: =IF(Y$9=$M21,FV($U$6,$M21-1,,-$S21,0),0) -> 0 | AA21: =IF(AA$9=$M21,FV($U$6,$M21-1,,-$S21,0),0) -> 0 | AC21: =IF(AC$9=$M21,FV($U$6,$M21-1,,-$S21,0),0) -> 0 | AE21: =IF(AE$9=$M21,FV($U$6,$M21-1,,-$S21,0),0) -> 0 | AG21: =IF(AG$9=$M21,FV($U$6,$M21-1,,-$S21,0),0) -> 0 | AI21: =IF(AI$9=$M21,FV($U$6,$M21-1,,-$S21,0),0) -> 0 | AK21: =IF(AK$9=$M21,FV($U$6,$M21-1,,-$S21,0),0) -> 0 | AM21: =IF(AM$9=$M21,FV($U$6,$M21-1,,-$S21,0),0) -> 0 | AO21: =IF(AO$9=$M21,FV($U$6,$M21-1,,-$S21,0),0) -> 0 | AQ21: =IF(AQ$9=$M21,FV($U$6,$M21-1,,-$S21,0),0) -> 0 | AS21: =IF(AS$9=$M21,FV($U$6,$M21-1,,-$S21,0),0) -> 0 | AU21: =IF(AU$9=$M21,FV($U$6,$M21-1,,-$S21,0),0) -> 0 | AW21: =IF(AW$9=$M21,FV($U$6,$M21-1,,-$S21,0),0) -> 0 | AY21: =IF(AY$9=$M21,FV($U$6,$M21-1,,-$S21,0),0) -> 0
A22: =A21+1 -> 9 | C22: 1 | E22: x | G22: x | I22: x | K22: x | M22: 1 | N22: =N21 -> 2023 | O22: =+$W$10-1+M22 -> 2024 | Q22: 1 | S22: =C22*Q22 -> 1 | U22: =SUM(W22:AY22)+SUM(I72:AK72) -> 1 | W22: =IF(W$9=$M22,FV($U$6,$M22-1,,-$S22,0),0) -> 1 | Y22: =IF(Y$9=$M22,FV($U$6,$M22-1,,-$S22,0),0) -> 0 | AA22: =IF(AA$9=$M22,FV($U$6,$M22-1,,-$S22,0),0) -> 0 | AC22: =IF(AC$9=$M22,FV($U$6,$M22-1,,-$S22,0),0) -> 0 | AE22: =IF(AE$9=$M22,FV($U$6,$M22-1,,-$S22,0),0) -> 0 | AG22: =IF(AG$9=$M22,FV($U$6,$M22-1,,-$S22,0),0) -> 0 | AI22: =IF(AI$9=$M22,FV($U$6,$M22-1,,-$S22,0),0) -> 0 | AK22: =IF(AK$9=$M22,FV($U$6,$M22-1,,-$S22,0),0) -> 0 | AM22: =IF(AM$9=$M22,FV($U$6,$M22-1,,-$S22,0),0) -> 0 | AO22: =IF(AO$9=$M22,FV($U$6,$M22-1,,-$S22,0),0) -> 0 | AQ22: =IF(AQ$9=$M22,FV($U$6,$M22-1,,-$S22,0),0) -> 0 | AS22: =IF(AS$9=$M22,FV($U$6,$M22-1,,-$S22,0),0) -> 0 | AU22: =IF(AU$9=$M22,FV($U$6,$M22-1,,-$S22,0),0) -> 0 | AW22: =IF(AW$9=$M22,FV($U$6,$M22-1,,-$S22,0),0) -> 0 | AY22: =IF(AY$9=$M22,FV($U$6,$M22-1,,-$S22,0),0) -> 0
A23: =A22+1 -> 10 | C23: 1 | E23: x | G23: x | I23: x | K23: x | M23: 1 | N23: =N22 -> 2023 | O23: =+$W$10-1+M23 -> 2024 | Q23: 1 | S23: =C23*Q23 -> 1 | U23: =SUM(W23:AY23)+SUM(I73:AK73) -> 1 | W23: =IF(W$9=$M23,FV($U$6,$M23-1,,-$S23,0),0) -> 1 | Y23: =IF(Y$9=$M23,FV($U$6,$M23-1,,-$S23,0),0) -> 0 | AA23: =IF(AA$9=$M23,FV($U$6,$M23-1,,-$S23,0),0) -> 0 | AC23: =IF(AC$9=$M23,FV($U$6,$M23-1,,-$S23,0),0) -> 0 | AE23: =IF(AE$9=$M23,FV($U$6,$M23-1,,-$S23,0),0) -> 0 | AG23: =IF(AG$9=$M23,FV($U$6,$M23-1,,-$S23,0),0) -> 0 | AI23: =IF(AI$9=$M23,FV($U$6,$M23-1,,-$S23,0),0) -> 0 | AK23: =IF(AK$9=$M23,FV($U$6,$M23-1,,-$S23,0),0) -> 0 | AM23: =IF(AM$9=$M23,FV($U$6,$M23-1,,-$S23,0),0) -> 0 | AO23: =IF(AO$9=$M23,FV($U$6,$M23-1,,-$S23,0),0) -> 0 | AQ23: =IF(AQ$9=$M23,FV($U$6,$M23-1,,-$S23,0),0) -> 0 | AS23: =IF(AS$9=$M23,FV($U$6,$M23-1,,-$S23,0),0) -> 0 | AU23: =IF(AU$9=$M23,FV($U$6,$M23-1,,-$S23,0),0) -> 0 | AW23: =IF(AW$9=$M23,FV($U$6,$M23-1,,-$S23,0),0) -> 0 | AY23: =IF(AY$9=$M23,FV($U$6,$M23-1,,-$S23,0),0) -> 0
A24: =A23+1 -> 11 | C24: 1 | E24: x | G24: x | I24: x | K24: x | M24: 1 | N24: =N23 -> 2023 | O24: =+$W$10-1+M24 -> 2024 | Q24: 1 | S24: =C24*Q24 -> 1 | U24: =SUM(W24:AY24)+SUM(I74:AK74) -> 1 | W24: =IF(W$9=$M24,FV($U$6,$M24-1,,-$S24,0),0) -> 1 | Y24: =IF(Y$9=$M24,FV($U$6,$M24-1,,-$S24,0),0) -> 0 | AA24: =IF(AA$9=$M24,FV($U$6,$M24-1,,-$S24,0),0) -> 0 | AC24: =IF(AC$9=$M24,FV($U$6,$M24-1,,-$S24,0),0) -> 0 | AE24: =IF(AE$9=$M24,FV($U$6,$M24-1,,-$S24,0),0) -> 0 | AG24: =IF(AG$9=$M24,FV($U$6,$M24-1,,-$S24,0),0) -> 0 | AI24: =IF(AI$9=$M24,FV($U$6,$M24-1,,-$S24,0),0) -> 0 | AK24: =IF(AK$9=$M24,FV($U$6,$M24-1,,-$S24,0),0) -> 0 | AM24: =IF(AM$9=$M24,FV($U$6,$M24-1,,-$S24,0),0) -> 0 | AO24: =IF(AO$9=$M24,FV($U$6,$M24-1,,-$S24,0),0) -> 0 | AQ24: =IF(AQ$9=$M24,FV($U$6,$M24-1,,-$S24,0),0) -> 0 | AS24: =IF(AS$9=$M24,FV($U$6,$M24-1,,-$S24,0),0) -> 0 | AU24: =IF(AU$9=$M24,FV($U$6,$M24-1,,-$S24,0),0) -> 0 | AW24: =IF(AW$9=$M24,FV($U$6,$M24-1,,-$S24,0),0) -> 0 | AY24: =IF(AY$9=$M24,FV($U$6,$M24-1,,-$S24,0),0) -> 0
A25: =A24+1 -> 12 | C25: 1 | E25: x | G25: x | I25: x | K25: x | M25: 1 | N25: =N24 -> 2023 | O25: =+$W$10-1+M25 -> 2024 | Q25: 1 | S25: =C25*Q25 -> 1 | U25: =SUM(W25:AY25)+SUM(I75:AK75) -> 1 | W25: =IF(W$9=$M25,FV($U$6,$M25-1,,-$S25,0),0) -> 1 | Y25: =IF(Y$9=$M25,FV($U$6,$M25-1,,-$S25,0),0) -> 0 | AA25: =IF(AA$9=$M25,FV($U$6,$M25-1,,-$S25,0),0) -> 0 | AC25: =IF(AC$9=$M25,FV($U$6,$M25-1,,-$S25,0),0) -> 0 | AE25: =IF(AE$9=$M25,FV($U$6,$M25-1,,-$S25,0),0) -> 0 | AG25: =IF(AG$9=$M25,FV($U$6,$M25-1,,-$S25,0),0) -> 0 | AI25: =IF(AI$9=$M25,FV($U$6,$M25-1,,-$S25,0),0) -> 0 | AK25: =IF(AK$9=$M25,FV($U$6,$M25-1,,-$S25,0),0) -> 0 | AM25: =IF(AM$9=$M25,FV($U$6,$M25-1,,-$S25,0),0) -> 0 | AO25: =IF(AO$9=$M25,FV($U$6,$M25-1,,-$S25,0),0) -> 0 | AQ25: =IF(AQ$9=$M25,FV($U$6,$M25-1,,-$S25,0),0) -> 0 | AS25: =IF(AS$9=$M25,FV($U$6,$M25-1,,-$S25,0),0) -> 0 | AU25: =IF(AU$9=$M25,FV($U$6,$M25-1,,-$S25,0),0) -> 0 | AW25: =IF(AW$9=$M25,FV($U$6,$M25-1,,-$S25,0),0) -> 0 | AY25: =IF(AY$9=$M25,FV($U$6,$M25-1,,-$S25,0),0) -> 0
A26: =A25+1 -> 13 | C26: 1 | E26: x | G26: x | I26: x | K26: x | M26: 1 | N26: =N25 -> 2023 | O26: =+$W$10-1+M26 -> 2024 | Q26: 1 | S26: =C26*Q26 -> 1 | U26: =SUM(W26:AY26)+SUM(I76:AK76) -> 1 | W26: =IF(W$9=$M26,FV($U$6,$M26-1,,-$S26,0),0) -> 1 | Y26: =IF(Y$9=$M26,FV($U$6,$M26-1,,-$S26,0),0) -> 0 | AA26: =IF(AA$9=$M26,FV($U$6,$M26-1,,-$S26,0),0) -> 0 | AC26: =IF(AC$9=$M26,FV($U$6,$M26-1,,-$S26,0),0) -> 0 | AE26: =IF(AE$9=$M26,FV($U$6,$M26-1,,-$S26,0),0) -> 0 | AG26: =IF(AG$9=$M26,FV($U$6,$M26-1,,-$S26,0),0) -> 0 | AI26: =IF(AI$9=$M26,FV($U$6,$M26-1,,-$S26,0),0) -> 0 | AK26: =IF(AK$9=$M26,FV($U$6,$M26-1,,-$S26,0),0) -> 0 | AM26: =IF(AM$9=$M26,FV($U$6,$M26-1,,-$S26,0),0) -> 0 | AO26: =IF(AO$9=$M26,FV($U$6,$M26-1,,-$S26,0),0) -> 0 | AQ26: =IF(AQ$9=$M26,FV($U$6,$M26-1,,-$S26,0),0) -> 0 | AS26: =IF(AS$9=$M26,FV($U$6,$M26-1,,-$S26,0),0) -> 0 | AU26: =IF(AU$9=$M26,FV($U$6,$M26-1,,-$S26,0),0) -> 0 | AW26: =IF(AW$9=$M26,FV($U$6,$M26-1,,-$S26,0),0) -> 0 | AY26: =IF(AY$9=$M26,FV($U$6,$M26-1,,-$S26,0),0) -> 0
... A37: =A36+1 -> 24 | C37: 1 | E37: x | G37: x | I37: x | K37: x | M37: 1 | N37: =N36 -> 2023 | O37: =+$W$10-1+M37 -> 2024 | Q37: 1 | S37: =C37*Q37 -> 1 | U37: =SUM(W37:AY37)+SUM(I87:AK87) -> 1 | W37: =IF(W$9=$M37,FV($U$6,$M37-1,,-$S37,0),0) -> 1 | Y37: =IF(Y$9=$M37,FV($U$6,$M37-1,,-$S37,0),0) -> 0 | AA37: =IF(AA$9=$M37,FV($U$6,$M37-1,,-$S37,0),0) -> 0 | AC37: =IF(AC$9=$M37,FV($U$6,$M37-1,,-$S37,0),0) -> 0 | AE37: =IF(AE$9=$M37,FV($U$6,$M37-1,,-$S37,0),0) -> 0 | AG37: =IF(AG$9=$M37,FV($U$6,$M37-1,,-$S37,0),0) -> 0 | AI37: =IF(AI$9=$M37,FV($U$6,$M37-1,,-$S37,0),0) -> 0 | AK37: =IF(AK$9=$M37,FV($U$6,$M37-1,,-$S37,0),0) -> 0 | AM37: =IF(AM$9=$M37,FV($U$6,$M37-1,,-$S37,0),0) -> 0 | AO37: =IF(AO$9=$M37,FV($U$6,$M37-1,,-$S37,0),0) -> 0 | AQ37: =IF(AQ$9=$M37,FV($U$6,$M37-1,,-$S37,0),0) -> 0 | AS37: =IF(AS$9=$M37,FV($U$6,$M37-1,,-$S37,0),0) -> 0 | AU37: =IF(AU$9=$M37,FV($U$6,$M37-1,,-$S37,0),0) -> 0 | AW37: =IF(AW$9=$M37,FV($U$6,$M37-1,,-$S37,0),0) -> 0 | AY37: =IF(AY$9=$M37,FV($U$6,$M37-1,,-$S37,0),0) -> 0
G39: ELEMENTS (PRN)
A40: =A37+1 -> 25 | C40: 1 | E40: x | G40: x | I40: x | K40: x | M40: 1 | N40: ='Roofs 1'!P4 -> 2023 | O40: =+$W$10-1+M40 -> 2024 | Q40: 1 | S40: =C40*Q40 -> 1 | U40: =SUM(W40:AY40)+SUM(I90:AK90) -> 47.575416 | W40: =S40 -> 1 | Y40: =FV($U$6,W$9,,-$S40,0) -> 1.03 | AA40: =FV($U$6,Y$9,,-$S40,0) -> 1.0609 | AC40: =FV($U$6,AA$9,,-$S40,0) -> 1.092727 | AE40: =FV($U$6,AC$9,,-$S40,0) -> 1.1255088 | AG40: =FV($U$6,AE$9,,-$S40,0) -> 1.1592741 | AI40: =FV($U$6,AG$9,,-$S40,0) -> 1.1940523 | AK40: =FV($U$6,AI$9,,-$S40,0) -> 1.2298739 | AM40: =FV($U$6,AK$9,,-$S40,0) -> 1.2667701 | AO40: =FV($U$6,AM$9,,-$S40,0) -> 1.3047732 | AQ40: =FV($U$6,AO$9,,-$S40,0) -> 1.3439164 | AS40: =FV($U$6,AQ$9,,-$S40,0) -> 1.3842339 | AU40: =FV($U$6,AS$9,,-$S40,0) -> 1.4257609 | AW40: =FV($U$6,AU$9,,-$S40,0) -> 1.4685337 | AY40: =FV($U$6,AW$9,,-$S40,0) -> 1.5125897
A41: =A40+1 -> 26 | C41: 1 | E41: x | G41: x | I41: x | K41: x | M41: 1 | N41: =N40 -> 2023 | O41: =+$W$10-1+M41 -> 2024 | Q41: 1 | S41: =C41*Q41 -> 1 | U41: =SUM(W41:AY41)+SUM(I91:AK91) -> 47.575416 | W41: =S41 -> 1 | Y41: =FV($U$6,W$9,,-$S41,0) -> 1.03 | AA41: =FV($U$6,Y$9,,-$S41,0) -> 1.0609 | AC41: =FV($U$6,AA$9,,-$S41,0) -> 1.092727 | AE41: =FV($U$6,AC$9,,-$S41,0) -> 1.1255088 | AG41: =FV($U$6,AE$9,,-$S41,0) -> 1.1592741 | AI41: =FV($U$6,AG$9,,-$S41,0) -> 1.1940523 | AK41: =FV($U$6,AI$9,,-$S41,0) -> 1.2298739 | AM41: =FV($U$6,AK$9,,-$S41,0) -> 1.2667701 | AO41: =FV($U$6,AM$9,,-$S41,0) -> 1.3047732 | AQ41: =FV($U$6,AO$9,,-$S41,0) -> 1.3439164 | AS41: =FV($U$6,AQ$9,,-$S41,0) -> 1.3842339 | AU41: =FV($U$6,AS$9,,-$S41,0) -> 1.4257609 | AW41: =FV($U$6,AU$9,,-$S41,0) -> 1.4685337 | AY41: =FV($U$6,AW$9,,-$S41,0) -> 1.5125897
A42: =A41+1 -> 27 | C42: 1 | E42: x | G42: x | I42: x | K42: x | M42: 1 | N42: =N41 -> 2023 | O42: =+$W$10-1+M42 -> 2024 | Q42: 1 | S42: =C42*Q42 -> 1 | U42: =SUM(W42:AY42)+SUM(I92:AK92) -> 47.575416 | W42: =S42 -> 1 | Y42: =FV($U$6,W$9,,-$S42,0) -> 1.03 | AA42: =FV($U$6,Y$9,,-$S42,0) -> 1.0609 | AC42: =FV($U$6,AA$9,,-$S42,0) -> 1.092727 | AE42: =FV($U$6,AC$9,,-$S42,0) -> 1.1255088 | AG42: =FV($U$6,AE$9,,-$S42,0) -> 1.1592741 | AI42: =FV($U$6,AG$9,,-$S42,0) -> 1.1940523 | AK42: =FV($U$6,AI$9,,-$S42,0) -> 1.2298739 | AM42: =FV($U$6,AK$9,,-$S42,0) -> 1.2667701 | AO42: =FV($U$6,AM$9,,-$S42,0) -> 1.3047732 | AQ42: =FV($U$6,AO$9,,-$S42,0) -> 1.3439164 | AS42: =FV($U$6,AQ$9,,-$S42,0) -> 1.3842339 | AU42: =FV($U$6,AS$9,,-$S42,0) -> 1.4257609 | AW42: =FV($U$6,AU$9,,-$S42,0) -> 1.4685337 | AY42: =FV($U$6,AW$9,,-$S42,0) -> 1.5125897
A43: =A42+1 -> 28 | C43: 1 | E43: x | G43: x | I43: x | K43: x | M43: 1 | N43: =N42 -> 2023 | O43: =+$W$10-1+M43 -> 2024 | Q43: 1 | S43: =C43*Q43 -> 1 | U43: =SUM(W43:AY43)+SUM(I93:AK93) -> 47.575416 | W43: =S43 -> 1 | Y43: =FV($U$6,W$9,,-$S43,0) -> 1.03 | AA43: =FV($U$6,Y$9,,-$S43,0) -> 1.0609 | AC43: =FV($U$6,AA$9,,-$S43,0) -> 1.092727 | AE43: =FV($U$6,AC$9,,-$S43,0) -> 1.1255088 | AG43: =FV($U$6,AE$9,,-$S43,0) -> 1.1592741 | AI43: =FV($U$6,AG$9,,-$S43,0) -> 1.1940523 | AK43: =FV($U$6,AI$9,,-$S43,0) -> 1.2298739 | AM43: =FV($U$6,AK$9,,-$S43,0) -> 1.2667701 | AO43: =FV($U$6,AM$9,,-$S43,0) -> 1.3047732 | AQ43: =FV($U$6,AO$9,,-$S43,0) -> 1.3439164 | AS43: =FV($U$6,AQ$9,,-$S43,0) -> 1.3842339 | AU43: =FV($U$6,AS$9,,-$S43,0) -> 1.4257609 | AW43: =FV($U$6,AU$9,,-$S43,0) -> 1.4685337 | AY43: =FV($U$6,AW$9,,-$S43,0) -> 1.5125897
A44: =A43+1 -> 29 | C44: 1 | E44: x | G44: x | I44: x | K44: x | M44: 1 | N44: =N43 -> 2023 | O44: =+$W$10-1+M44 -> 2024 | Q44: 1 | S44: =C44*Q44 -> 1 | U44: =SUM(W44:AY44)+SUM(I94:AK94) -> 47.575416 | W44: =S44 -> 1 | Y44: =FV($U$6,W$9,,-$S44,0) -> 1.03 | AA44: =FV($U$6,Y$9,,-$S44,0) -> 1.0609 | AC44: =FV($U$6,AA$9,,-$S44,0) -> 1.092727 | AE44: =FV($U$6,AC$9,,-$S44,0) -> 1.1255088 | AG44: =FV($U$6,AE$9,,-$S44,0) -> 1.1592741 | AI44: =FV($U$6,AG$9,,-$S44,0) -> 1.1940523 | AK44: =FV($U$6,AI$9,,-$S44,0) -> 1.2298739 | AM44: =FV($U$6,AK$9,,-$S44,0) -> 1.2667701 | AO44: =FV($U$6,AM$9,,-$S44,0) -> 1.3047732 | AQ44: =FV($U$6,AO$9,,-$S44,0) -> 1.3439164 | AS44: =FV($U$6,AQ$9,,-$S44,0) -> 1.3842339 | AU44: =FV($U$6,AS$9,,-$S44,0) -> 1.4257609 | AW44: =FV($U$6,AU$9,,-$S44,0) -> 1.4685337 | AY44: =FV($U$6,AW$9,,-$S44,0) -> 1.5125897
A45: =A44+1 -> 30 | C45: 1 | E45: x | G45: x | I45: x | K45: x | M45: 1 | N45: =N44 -> 2023 | O45: =+$W$10-1+M45 -> 2024 | Q45: 1 | S45: =C45*Q45 -> 1 | U45: =SUM(W45:AY45)+SUM(I95:AK95) -> 47.575416 | W45: =S45 -> 1 | Y45: =FV($U$6,W$9,,-$S45,0) -> 1.03 | AA45: =FV($U$6,Y$9,,-$S45,0) -> 1.0609 | AC45: =FV($U$6,AA$9,,-$S45,0) -> 1.092727 | AE45: =FV($U$6,AC$9,,-$S45,0) -> 1.1255088 | AG45: =FV($U$6,AE$9,,-$S45,0) -> 1.1592741 | AI45: =FV($U$6,AG$9,,-$S45,0) -> 1.1940523 | AK45: =FV($U$6,AI$9,,-$S45,0) -> 1.2298739 | AM45: =FV($U$6,AK$9,,-$S45,0) -> 1.2667701 | AO45: =FV($U$6,AM$9,,-$S45,0) -> 1.3047732 | AQ45: =FV($U$6,AO$9,,-$S45,0) -> 1.3439164 | AS45: =FV($U$6,AQ$9,,-$S45,0) -> 1.3842339 | AU45: =FV($U$6,AS$9,,-$S45,0) -> 1.4257609 | AW45: =FV($U$6,AU$9,,-$S45,0) -> 1.4685337 | AY45: =FV($U$6,AW$9,,-$S45,0) -> 1.5125897
A46: =A45+1 -> 31 | C46: 1 | E46: x | G46: x | I46: x | K46: x | M46: 1 | N46: =N45 -> 2023 | O46: =+$W$10-1+M46 -> 2024 | Q46: 1 | S46: =C46*Q46 -> 1 | U46: =SUM(W46:AY46)+SUM(I96:AK96) -> 47.575416 | W46: =S46 -> 1 | Y46: =FV($U$6,W$9,,-$S46,0) -> 1.03 | AA46: =FV($U$6,Y$9,,-$S46,0) -> 1.0609 | AC46: =FV($U$6,AA$9,,-$S46,0) -> 1.092727 | AE46: =FV($U$6,AC$9,,-$S46,0) -> 1.1255088 | AG46: =FV($U$6,AE$9,,-$S46,0) -> 1.1592741 | AI46: =FV($U$6,AG$9,,-$S46,0) -> 1.1940523 | AK46: =FV($U$6,AI$9,,-$S46,0) -> 1.2298739 | AM46: =FV($U$6,AK$9,,-$S46,0) -> 1.2667701 | AO46: =FV($U$6,AM$9,,-$S46,0) -> 1.3047732 | AQ46: =FV($U$6,AO$9,,-$S46,0) -> 1.3439164 | AS46: =FV($U$6,AQ$9,,-$S46,0) -> 1.3842339 | AU46: =FV($U$6,AS$9,,-$S46,0) -> 1.4257609 | AW46: =FV($U$6,AU$9,,-$S46,0) -> 1.4685337 | AY46: =FV($U$6,AW$9,,-$S46,0) -> 1.5125897
A47: =A46+1 -> 32 | C47: 1 | E47: x | G47: x | I47: x | K47: x | M47: 1 | N47: =N46 -> 2023 | O47: =+$W$10-1+M47 -> 2024 | Q47: 1 | S47: =C47*Q47 -> 1 | U47: =SUM(W47:AY47)+SUM(I97:AK97) -> 47.575416 | W47: =S47 -> 1 | Y47: =FV($U$6,W$9,,-$S47,0) -> 1.03 | AA47: =FV($U$6,Y$9,,-$S47,0) -> 1.0609 | AC47: =FV($U$6,AA$9,,-$S47,0) -> 1.092727 | AE47: =FV($U$6,AC$9,,-$S47,0) -> 1.1255088 | AG47: =FV($U$6,AE$9,,-$S47,0) -> 1.1592741 | AI47: =FV($U$6,AG$9,,-$S47,0) -> 1.1940523 | AK47: =FV($U$6,AI$9,,-$S47,0) -> 1.2298739 | AM47: =FV($U$6,AK$9,,-$S47,0) -> 1.2667701 | AO47: =FV($U$6,AM$9,,-$S47,0) -> 1.3047732 | AQ47: =FV($U$6,AO$9,,-$S47,0) -> 1.3439164 | AS47: =FV($U$6,AQ$9,,-$S47,0) -> 1.3842339 | AU47: =FV($U$6,AS$9,,-$S47,0) -> 1.4257609 | AW47: =FV($U$6,AU$9,,-$S47,0) -> 1.4685337 | AY47: =FV($U$6,AW$9,,-$S47,0) -> 1.5125897
A48: =A47+1 -> 33 | C48: 1 | E48: x | G48: x | I48: x | K48: x | M48: 1 | N48: =N47 -> 2023 | O48: =+$W$10-1+M48 -> 2024 | Q48: 1 | S48: =C48*Q48 -> 1 | U48: =SUM(W48:AY48)+SUM(I98:AK98) -> 47.575416 | W48: =S48 -> 1 | Y48: =FV($U$6,W$9,,-$S48,0) -> 1.03 | AA48: =FV($U$6,Y$9,,-$S48,0) -> 1.0609 | AC48: =FV($U$6,AA$9,,-$S48,0) -> 1.092727 | AE48: =FV($U$6,AC$9,,-$S48,0) -> 1.1255088 | AG48: =FV($U$6,AE$9,,-$S48,0) -> 1.1592741 | AI48: =FV($U$6,AG$9,,-$S48,0) -> 1.1940523 | AK48: =FV($U$6,AI$9,,-$S48,0) -> 1.2298739 | AM48: =FV($U$6,AK$9,,-$S48,0) -> 1.2667701 | AO48: =FV($U$6,AM$9,,-$S48,0) -> 1.3047732 | AQ48: =FV($U$6,AO$9,,-$S48,0) -> 1.3439164 | AS48: =FV($U$6,AQ$9,,-$S48,0) -> 1.3842339 | AU48: =FV($U$6,AS$9,,-$S48,0) -> 1.4257609 | AW48: =FV($U$6,AU$9,,-$S48,0) -> 1.4685337 | AY48: =FV($U$6,AW$9,,-$S48,0) -> 1.5125897
A49: =A48+1 -> 34 | C49: 1 | E49: x | G49: x | I49: x | K49: x | M49: 1 | N49: =N48 -> 2023 | O49: =+$W$10-1+M49 -> 2024 | Q49: 1 | S49: =C49*Q49 -> 1 | U49: =SUM(W49:AY49)+SUM(I99:AK99) -> 47.575416 | W49: =S49 -> 1 | Y49: =FV($U$6,W$9,,-$S49,0) -> 1.03 | AA49: =FV($U$6,Y$9,,-$S49,0) -> 1.0609 | AC49: =FV($U$6,AA$9,,-$S49,0) -> 1.092727 | AE49: =FV($U$6,AC$9,,-$S49,0) -> 1.1255088 | AG49: =FV($U$6,AE$9,,-$S49,0) -> 1.1592741 | AI49: =FV($U$6,AG$9,,-$S49,0) -> 1.1940523 | AK49: =FV($U$6,AI$9,,-$S49,0) -> 1.2298739 | AM49: =FV($U$6,AK$9,,-$S49,0) -> 1.2667701 | AO49: =FV($U$6,AM$9,,-$S49,0) -> 1.3047732 | AQ49: =FV($U$6,AO$9,,-$S49,0) -> 1.3439164 | AS49: =FV($U$6,AQ$9,,-$S49,0) -> 1.3842339 | AU49: =FV($U$6,AS$9,,-$S49,0) -> 1.4257609 | AW49: =FV($U$6,AU$9,,-$S49,0) -> 1.4685337 | AY49: =FV($U$6,AW$9,,-$S49,0) -> 1.5125897
A50: =A49+1 -> 35 | C50: 1 | E50: x | G50: x | I50: x | K50: x | M50: 1 | N50: =N49 -> 2023 | O50: =+$W$10-1+M50 -> 2024 | Q50: 1 | S50: =C50*Q50 -> 1 | U50: =SUM(W50:AY50)+SUM(I100:AK100) -> 47.575416 | W50: =S50 -> 1 | Y50: =FV($U$6,W$9,,-$S50,0) -> 1.03 | AA50: =FV($U$6,Y$9,,-$S50,0) -> 1.0609 | AC50: =FV($U$6,AA$9,,-$S50,0) -> 1.092727 | AE50: =FV($U$6,AC$9,,-$S50,0) -> 1.1255088 | AG50: =FV($U$6,AE$9,,-$S50,0) -> 1.1592741 | AI50: =FV($U$6,AG$9,,-$S50,0) -> 1.1940523 | AK50: =FV($U$6,AI$9,,-$S50,0) -> 1.2298739 | AM50: =FV($U$6,AK$9,,-$S50,0) -> 1.2667701 | AO50: =FV($U$6,AM$9,,-$S50,0) -> 1.3047732 | AQ50: =FV($U$6,AO$9,,-$S50,0) -> 1.3439164 | AS50: =FV($U$6,AQ$9,,-$S50,0) -> 1.3842339 | AU50: =FV($U$6,AS$9,,-$S50,0) -> 1.4257609 | AW50: =FV($U$6,AU$9,,-$S50,0) -> 1.4685337 | AY50: =FV($U$6,AW$9,,-$S50,0) -> 1.5125897
A51: =A50+1 -> 36 | C51: 1 | E51: x | G51: x | I51: x | K51: x | M51: 1 | N51: =N50 -> 2023 | O51: =+$W$10-1+M51 -> 2024 | Q51: 1 | S51: =C51*Q51 -> 1 | U51: =SUM(W51:AY51)+SUM(I101:AK101) -> 47.575416 | W51: =S51 -> 1 | Y51: =FV($U$6,W$9,,-$S51,0) -> 1.03 | AA51: =FV($U$6,Y$9,,-$S51,0) -> 1.0609 | AC51: =FV($U$6,AA$9,,-$S51,0) -> 1.092727 | AE51: =FV($U$6,AC$9,,-$S51,0) -> 1.1255088 | AG51: =FV($U$6,AE$9,,-$S51,0) -> 1.1592741 | AI51: =FV($U$6,AG$9,,-$S51,0) -> 1.1940523 | AK51: =FV($U$6,AI$9,,-$S51,0) -> 1.2298739 | AM51: =FV($U$6,AK$9,,-$S51,0) -> 1.2667701 | AO51: =FV($U$6,AM$9,,-$S51,0) -> 1.3047732 | AQ51: =FV($U$6,AO$9,,-$S51,0) -> 1.3439164 | AS51: =FV($U$6,AQ$9,,-$S51,0) -> 1.3842339 | AU51: =FV($U$6,AS$9,,-$S51,0) -> 1.4257609 | AW51: =FV($U$6,AU$9,,-$S51,0) -> 1.4685337 | AY51: =FV($U$6,AW$9,,-$S51,0) -> 1.5125897
A52: =A51+1 -> 37 | C52: 1 | E52: x | G52: x | I52: x | K52: x | M52: 1 | N52: =N51 -> 2023 | O52: =+$W$10-1+M52 -> 2024 | Q52: 1 | S52: =C52*Q52 -> 1 | U52: =SUM(W52:AY52)+SUM(I102:AK102) -> 47.575416 | W52: =S52 -> 1 | Y52: =FV($U$6,W$9,,-$S52,0) -> 1.03 | AA52: =FV($U$6,Y$9,,-$S52,0) -> 1.0609 | AC52: =FV($U$6,AA$9,,-$S52,0) -> 1.092727 | AE52: =FV($U$6,AC$9,,-$S52,0) -> 1.1255088 | AG52: =FV($U$6,AE$9,,-$S52,0) -> 1.1592741 | AI52: =FV($U$6,AG$9,,-$S52,0) -> 1.1940523 | AK52: =FV($U$6,AI$9,,-$S52,0) -> 1.2298739 | AM52: =FV($U$6,AK$9,,-$S52,0) -> 1.2667701 | AO52: =FV($U$6,AM$9,,-$S52,0) -> 1.3047732 | AQ52: =FV($U$6,AO$9,,-$S52,0) -> 1.3439164 | AS52: =FV($U$6,AQ$9,,-$S52,0) -> 1.3842339 | AU52: =FV($U$6,AS$9,,-$S52,0) -> 1.4257609 | AW52: =FV($U$6,AU$9,,-$S52,0) -> 1.4685337 | AY52: =FV($U$6,AW$9,,-$S52,0) -> 1.5125897
... A54: =A53+1 -> 39 | C54: 1 | E54: x | G54: x | I54: x | K54: x | M54: 1 | N54: =N53 -> 2023 | O54: =+$W$10-1+M54 -> 2024 | Q54: 1 | S54: =C54*Q54 -> 1 | U54: =SUM(W54:AY54)+SUM(I104:AK104) -> 47.575416 | W54: =S54 -> 1 | Y54: =FV($U$6,W$9,,-$S54,0) -> 1.03 | AA54: =FV($U$6,Y$9,,-$S54,0) -> 1.0609 | AC54: =FV($U$6,AA$9,,-$S54,0) -> 1.092727 | AE54: =FV($U$6,AC$9,,-$S54,0) -> 1.1255088 | AG54: =FV($U$6,AE$9,,-$S54,0) -> 1.1592741 | AI54: =FV($U$6,AG$9,,-$S54,0) -> 1.1940523 | AK54: =FV($U$6,AI$9,,-$S54,0) -> 1.2298739 | AM54: =FV($U$6,AK$9,,-$S54,0) -> 1.2667701 | AO54: =FV($U$6,AM$9,,-$S54,0) -> 1.3047732 | AQ54: =FV($U$6,AO$9,,-$S54,0) -> 1.3439164 | AS54: =FV($U$6,AQ$9,,-$S54,0) -> 1.3842339 | AU54: =FV($U$6,AS$9,,-$S54,0) -> 1.4257609 | AW54: =FV($U$6,AU$9,,-$S54,0) -> 1.4685337 | AY54: =FV($U$6,AW$9,,-$S54,0) -> 1.5125897
G56: Anticipated Expenditures, By Year | S56: =SUM(S14:T54) -> 39 | U56: =SUM(U14:U54) -> 737.63124 | W56: =SUM(W14:W54) -> 39 | Y56: =SUM(Y14:Y54) -> 15.45 | AA56: =SUM(AA14:AA54) -> 15.9135 | AC56: =SUM(AC14:AC54) -> 16.390905 | AE56: =SUM(AE14:AE54) -> 16.882632 | AG56: =SUM(AG14:AG54) -> 17.389111 | AI56: =SUM(AI14:AI54) -> 17.910784 | AK56: =SUM(AK14:AK54) -> 18.448108 | AM56: =SUM(AM14:AM54) -> 19.001551 | AO56: =SUM(AO14:AO54) -> 19.571598 | AQ56: =SUM(AQ14:AQ54) -> 20.158746 | AS56: =SUM(AS14:AS54) -> 20.763508 | AU56: =SUM(AU14:AU54) -> 21.386413 | AW56: =SUM(AW14:AW54) -> 22.028006 | AY56: =SUM(AY14:AY54) -> 22.688846
A59: Line Item | I59: 16 | K59: 17 | M59: 18 | O59: 19 | Q59: 20 | S59: =+Q59+1 -> 21 | U59: =+S59+1 -> 22 | W59: =+U59+1 -> 23 | Y59: =+W59+1 -> 24 | AA59: =+Y59+1 -> 25 | AC59: =+AA59+1 -> 26 | AE59: =+AC59+1 -> 27 | AG59: =+AE59+1 -> 28 | AI59: =+AG59+1 -> 29 | AK59: =+AI59+1 -> 30
C60: Quantity | E60: Units | G60: Reserve Component Inventory | I60: =AY10+1 -> 2039 | J60: =AZ10+1 -> 1 | K60: =I60+1 -> 2040 | L60: =J60+1 -> 2 | M60: =K60+1 -> 2041 | N60: =L60+1 -> 3 | O60: =M60+1 -> 2042 | P60: =N60+1 -> 4 | Q60: =O60+1 -> 2043 | S60: =+Q60+1 -> 2044 | T60: =R60+1 -> 1 | U60: =S60+1 -> 2045 | V60: =T60+1 -> 2 | W60: =U60+1 -> 2046 | X60: =V60+1 -> 3 | Y60: =W60+1 -> 2047 | Z60: =X60+1 -> 4 | AA60: =Y60+1 -> 2048 | AC60: =AA60+1 -> 2049 | AE60: =AC60+1 -> 2050 | AG60: =AE60+1 -> 2051 | AI60: =AG60+1 -> 2052 | AK60: =AI60+1 -> 2053
G62: =+G12 -> ELEMENTS REPLACE
A64: =+A14 -> 1 | C64: =+C14 -> 1 | E64: =+E14 -> x | G64: =+G14 -> x | I64: =IF(I$59=$M14,FV($U$6,$M14-1,,-$S14,0),0) -> 0 | K64: =IF(K$59=$M14,FV($U$6,$M14-1,,-$S14,0),0) -> 0 | M64: =IF(M$59=$M14,FV($U$6,$M14-1,,-$S14,0),0) -> 0 | O64: =IF(O$59=$M14,FV($U$6,$M14-1,,-$S14,0),0) -> 0 | Q64: =IF(Q$59=$M14,FV($U$6,$M14-1,,-$S14,0),0) -> 0 | S64: =IF(S$59=$M14,FV($U$6,$M14-1,,-$S14,0),0) -> 0 | U64: =IF(U$59=$M14,FV($U$6,$M14-1,,-$S14,0),0) -> 0 | W64: =IF(W$59=$M14,FV($U$6,$M14-1,,-$S14,0),0) -> 0 | Y64: =IF(Y$59=$M14,FV($U$6,$M14-1,,-$S14,0),0) -> 0 | AA64: =IF(AA$59=$M14,FV($U$6,$M14-1,,-$S14,0),0) -> 0 | AC64: =IF(AC$59=$M14,FV($U$6,$M14-1,,-$S14,0),0) -> 0 | AE64: =IF(AE$59=$M14,FV($U$6,$M14-1,,-$S14,0),0) -> 0 | AG64: =IF(AG$59=$M14,FV($U$6,$M14-1,,-$S14,0),0) -> 0 | AI64: =IF(AI$59=$M14,FV($U$6,$M14-1,,-$S14,0),0) -> 0 | AK64: =IF(AK$59=$M14,FV($U$6,$M14-1,,-$S14,0),0) -> 0
A65: =+A15 -> 2 | C65: =+C15 -> 1 | E65: =+E15 -> x | G65: =+G15 -> x | I65: =IF(I$59=$M15,FV($U$6,$M15-1,,-$S15,0),0) -> 0 | K65: =IF(K$59=$M15,FV($U$6,$M15-1,,-$S15,0),0) -> 0 | M65: =IF(M$59=$M15,FV($U$6,$M15-1,,-$S15,0),0) -> 0 | O65: =IF(O$59=$M15,FV($U$6,$M15-1,,-$S15,0),0) -> 0 | Q65: =IF(Q$59=$M15,FV($U$6,$M15-1,,-$S15,0),0) -> 0 | S65: =IF(S$59=$M15,FV($U$6,$M15-1,,-$S15,0),0) -> 0 | U65: =IF(U$59=$M15,FV($U$6,$M15-1,,-$S15,0),0) -> 0 | W65: =IF(W$59=$M15,FV($U$6,$M15-1,,-$S15,0),0) -> 0 | Y65: =IF(Y$59=$M15,FV($U$6,$M15-1,,-$S15,0),0) -> 0 | AA65: =IF(AA$59=$M15,FV($U$6,$M15-1,,-$S15,0),0) -> 0 | AC65: =IF(AC$59=$M15,FV($U$6,$M15-1,,-$S15,0),0) -> 0 | AE65: =IF(AE$59=$M15,FV($U$6,$M15-1,,-$S15,0),0) -> 0 | AG65: =IF(AG$59=$M15,FV($U$6,$M15-1,,-$S15,0),0) -> 0 | AI65: =IF(AI$59=$M15,FV($U$6,$M15-1,,-$S15,0),0) -> 0 | AK65: =IF(AK$59=$M15,FV($U$6,$M15-1,,-$S15,0),0) -> 0
A66: =+A16 -> 3 | C66: =+C16 -> 1 | E66: =+E16 -> x | G66: =+G16 -> x | I66: =IF(I$59=$M16,FV($U$6,$M16-1,,-$S16,0),0) -> 0 | K66: =IF(K$59=$M16,FV($U$6,$M16-1,,-$S16,0),0) -> 0 | M66: =IF(M$59=$M16,FV($U$6,$M16-1,,-$S16,0),0) -> 0 | O66: =IF(O$59=$M16,FV($U$6,$M16-1,,-$S16,0),0) -> 0 | Q66: =IF(Q$59=$M16,FV($U$6,$M16-1,,-$S16,0),0) -> 0 | S66: =IF(S$59=$M16,FV($U$6,$M16-1,,-$S16,0),0) -> 0 | U66: =IF(U$59=$M16,FV($U$6,$M16-1,,-$S16,0),0) -> 0 | W66: =IF(W$59=$M16,FV($U$6,$M16-1,,-$S16,0),0) -> 0 | Y66: =IF(Y$59=$M16,FV($U$6,$M16-1,,-$S16,0),0) -> 0 | AA66: =IF(AA$59=$M16,FV($U$6,$M16-1,,-$S16,0),0) -> 0 | AC66: =IF(AC$59=$M16,FV($U$6,$M16-1,,-$S16,0),0) -> 0 | AE66: =IF(AE$59=$M16,FV($U$6,$M16-1,,-$S16,0),0) -> 0 | AG66: =IF(AG$59=$M16,FV($U$6,$M16-1,,-$S16,0),0) -> 0 | AI66: =IF(AI$59=$M16,FV($U$6,$M16-1,,-$S16,0),0) -> 0 | AK66: =IF(AK$59=$M16,FV($U$6,$M16-1,,-$S16,0),0) -> 0
A67: =+A17 -> 4 | C67: =+C17 -> 1 | E67: =+E17 -> x | G67: =+G17 -> x | I67: =IF(I$59=$M17,FV($U$6,$M17-1,,-$S17,0),0) -> 0 | K67: =IF(K$59=$M17,FV($U$6,$M17-1,,-$S17,0),0) -> 0 | M67: =IF(M$59=$M17,FV($U$6,$M17-1,,-$S17,0),0) -> 0 | O67: =IF(O$59=$M17,FV($U$6,$M17-1,,-$S17,0),0) -> 0 | Q67: =IF(Q$59=$M17,FV($U$6,$M17-1,,-$S17,0),0) -> 0 | S67: =IF(S$59=$M17,FV($U$6,$M17-1,,-$S17,0),0) -> 0 | U67: =IF(U$59=$M17,FV($U$6,$M17-1,,-$S17,0),0) -> 0 | W67: =IF(W$59=$M17,FV($U$6,$M17-1,,-$S17,0),0) -> 0 | Y67: =IF(Y$59=$M17,FV($U$6,$M17-1,,-$S17,0),0) -> 0 | AA67: =IF(AA$59=$M17,FV($U$6,$M17-1,,-$S17,0),0) -> 0 | AC67: =IF(AC$59=$M17,FV($U$6,$M17-1,,-$S17,0),0) -> 0 | AE67: =IF(AE$59=$M17,FV($U$6,$M17-1,,-$S17,0),0) -> 0 | AG67: =IF(AG$59=$M17,FV($U$6,$M17-1,,-$S17,0),0) -> 0 | AI67: =IF(AI$59=$M17,FV($U$6,$M17-1,,-$S17,0),0) -> 0 | AK67: =IF(AK$59=$M17,FV($U$6,$M17-1,,-$S17,0),0) -> 0
A68: =+A18 -> 5 | C68: =+C18 -> 1 | E68: =+E18 -> x | G68: =+G18 -> x | I68: =IF(I$59=$M18,FV($U$6,$M18-1,,-$S18,0),0) -> 0 | K68: =IF(K$59=$M18,FV($U$6,$M18-1,,-$S18,0),0) -> 0 | M68: =IF(M$59=$M18,FV($U$6,$M18-1,,-$S18,0),0) -> 0 | O68: =IF(O$59=$M18,FV($U$6,$M18-1,,-$S18,0),0) -> 0 | Q68: =IF(Q$59=$M18,FV($U$6,$M18-1,,-$S18,0),0) -> 0 | S68: =IF(S$59=$M18,FV($U$6,$M18-1,,-$S18,0),0) -> 0 | U68: =IF(U$59=$M18,FV($U$6,$M18-1,,-$S18,0),0) -> 0 | W68: =IF(W$59=$M18,FV($U$6,$M18-1,,-$S18,0),0) -> 0 | Y68: =IF(Y$59=$M18,FV($U$6,$M18-1,,-$S18,0),0) -> 0 | AA68: =IF(AA$59=$M18,FV($U$6,$M18-1,,-$S18,0),0) -> 0 | AC68: =IF(AC$59=$M18,FV($U$6,$M18-1,,-$S18,0),0) -> 0 | AE68: =IF(AE$59=$M18,FV($U$6,$M18-1,,-$S18,0),0) -> 0 | AG68: =IF(AG$59=$M18,FV($U$6,$M18-1,,-$S18,0),0) -> 0 | AI68: =IF(AI$59=$M18,FV($U$6,$M18-1,,-$S18,0),0) -> 0 | AK68: =IF(AK$59=$M18,FV($U$6,$M18-1,,-$S18,0),0) -> 0
A69: =+A19 -> 6 | C69: =+C19 -> 1 | E69: =+E19 -> x | G69: =+G19 -> x | I69: =IF(I$59=$M19,FV($U$6,$M19-1,,-$S19,0),0) -> 0 | K69: =IF(K$59=$M19,FV($U$6,$M19-1,,-$S19,0),0) -> 0 | M69: =IF(M$59=$M19,FV($U$6,$M19-1,,-$S19,0),0) -> 0 | O69: =IF(O$59=$M19,FV($U$6,$M19-1,,-$S19,0),0) -> 0 | Q69: =IF(Q$59=$M19,FV($U$6,$M19-1,,-$S19,0),0) -> 0 | S69: =IF(S$59=$M19,FV($U$6,$M19-1,,-$S19,0),0) -> 0 | U69: =IF(U$59=$M19,FV($U$6,$M19-1,,-$S19,0),0) -> 0 | W69: =IF(W$59=$M19,FV($U$6,$M19-1,,-$S19,0),0) -> 0 | Y69: =IF(Y$59=$M19,FV($U$6,$M19-1,,-$S19,0),0) -> 0 | AA69: =IF(AA$59=$M19,FV($U$6,$M19-1,,-$S19,0),0) -> 0 | AC69: =IF(AC$59=$M19,FV($U$6,$M19-1,,-$S19,0),0) -> 0 | AE69: =IF(AE$59=$M19,FV($U$6,$M19-1,,-$S19,0),0) -> 0 | AG69: =IF(AG$59=$M19,FV($U$6,$M19-1,,-$S19,0),0) -> 0 | AI69: =IF(AI$59=$M19,FV($U$6,$M19-1,,-$S19,0),0) -> 0 | AK69: =IF(AK$59=$M19,FV($U$6,$M19-1,,-$S19,0),0) -> 0
A70: =+A20 -> 7 | C70: =+C20 -> 1 | E70: =+E20 -> x | G70: =+G20 -> x | I70: =IF(I$59=$M20,FV($U$6,$M20-1,,-$S20,0),0) -> 0 | K70: =IF(K$59=$M20,FV($U$6,$M20-1,,-$S20,0),0) -> 0 | M70: =IF(M$59=$M20,FV($U$6,$M20-1,,-$S20,0),0) -> 0 | O70: =IF(O$59=$M20,FV($U$6,$M20-1,,-$S20,0),0) -> 0 | Q70: =IF(Q$59=$M20,FV($U$6,$M20-1,,-$S20,0),0) -> 0 | S70: =IF(S$59=$M20,FV($U$6,$M20-1,,-$S20,0),0) -> 0 | U70: =IF(U$59=$M20,FV($U$6,$M20-1,,-$S20,0),0) -> 0 | W70: =IF(W$59=$M20,FV($U$6,$M20-1,,-$S20,0),0) -> 0 | Y70: =IF(Y$59=$M20,FV($U$6,$M20-1,,-$S20,0),0) -> 0 | AA70: =IF(AA$59=$M20,FV($U$6,$M20-1,,-$S20,0),0) -> 0 | AC70: =IF(AC$59=$M20,FV($U$6,$M20-1,,-$S20,0),0) -> 0 | AE70: =IF(AE$59=$M20,FV($U$6,$M20-1,,-$S20,0),0) -> 0 | AG70: =IF(AG$59=$M20,FV($U$6,$M20-1,,-$S20,0),0) -> 0 | AI70: =IF(AI$59=$M20,FV($U$6,$M20-1,,-$S20,0),0) -> 0 | AK70: =IF(AK$59=$M20,FV($U$6,$M20-1,,-$S20,0),0) -> 0
A71: =+A21 -> 8 | C71: =+C21 -> 1 | E71: =+E21 -> x | G71: =+G21 -> x | I71: =IF(I$59=$M21,FV($U$6,$M21-1,,-$S21,0),0) -> 0 | K71: =IF(K$59=$M21,FV($U$6,$M21-1,,-$S21,0),0) -> 0 | M71: =IF(M$59=$M21,FV($U$6,$M21-1,,-$S21,0),0) -> 0 | O71: =IF(O$59=$M21,FV($U$6,$M21-1,,-$S21,0),0) -> 0 | Q71: =IF(Q$59=$M21,FV($U$6,$M21-1,,-$S21,0),0) -> 0 | S71: =IF(S$59=$M21,FV($U$6,$M21-1,,-$S21,0),0) -> 0 | U71: =IF(U$59=$M21,FV($U$6,$M21-1,,-$S21,0),0) -> 0 | W71: =IF(W$59=$M21,FV($U$6,$M21-1,,-$S21,0),0) -> 0 | Y71: =IF(Y$59=$M21,FV($U$6,$M21-1,,-$S21,0),0) -> 0 | AA71: =IF(AA$59=$M21,FV($U$6,$M21-1,,-$S21,0),0) -> 0 | AC71: =IF(AC$59=$M21,FV($U$6,$M21-1,,-$S21,0),0) -> 0 | AE71: =IF(AE$59=$M21,FV($U$6,$M21-1,,-$S21,0),0) -> 0 | AG71: =IF(AG$59=$M21,FV($U$6,$M21-1,,-$S21,0),0) -> 0 | AI71: =IF(AI$59=$M21,FV($U$6,$M21-1,,-$S21,0),0) -> 0 | AK71: =IF(AK$59=$M21,FV($U$6,$M21-1,,-$S21,0),0) -> 0
A72: =+A22 -> 9 | C72: =+C22 -> 1 | E72: =+E22 -> x | G72: =+G22 -> x | I72: =IF(I$59=$M22,FV($U$6,$M22-1,,-$S22,0),0) -> 0 | K72: =IF(K$59=$M22,FV($U$6,$M22-1,,-$S22,0),0) -> 0 | M72: =IF(M$59=$M22,FV($U$6,$M22-1,,-$S22,0),0) -> 0 | O72: =IF(O$59=$M22,FV($U$6,$M22-1,,-$S22,0),0) -> 0 | Q72: =IF(Q$59=$M22,FV($U$6,$M22-1,,-$S22,0),0) -> 0 | S72: =IF(S$59=$M22,FV($U$6,$M22-1,,-$S22,0),0) -> 0 | U72: =IF(U$59=$M22,FV($U$6,$M22-1,,-$S22,0),0) -> 0 | W72: =IF(W$59=$M22,FV($U$6,$M22-1,,-$S22,0),0) -> 0 | Y72: =IF(Y$59=$M22,FV($U$6,$M22-1,,-$S22,0),0) -> 0 | AA72: =IF(AA$59=$M22,FV($U$6,$M22-1,,-$S22,0),0) -> 0 | AC72: =IF(AC$59=$M22,FV($U$6,$M22-1,,-$S22,0),0) -> 0 | AE72: =IF(AE$59=$M22,FV($U$6,$M22-1,,-$S22,0),0) -> 0 | AG72: =IF(AG$59=$M22,FV($U$6,$M22-1,,-$S22,0),0) -> 0 | AI72: =IF(AI$59=$M22,FV($U$6,$M22-1,,-$S22,0),0) -> 0 | AK72: =IF(AK$59=$M22,FV($U$6,$M22-1,,-$S22,0),0) -> 0
A73: =+A23 -> 10 | C73: =+C23 -> 1 | E73: =+E23 -> x | G73: =+G23 -> x | I73: =IF(I$59=$M23,FV($U$6,$M23-1,,-$S23,0),0) -> 0 | K73: =IF(K$59=$M23,FV($U$6,$M23-1,,-$S23,0),0) -> 0 | M73: =IF(M$59=$M23,FV($U$6,$M23-1,,-$S23,0),0) -> 0 | O73: =IF(O$59=$M23,FV($U$6,$M23-1,,-$S23,0),0) -> 0 | Q73: =IF(Q$59=$M23,FV($U$6,$M23-1,,-$S23,0),0) -> 0 | S73: =IF(S$59=$M23,FV($U$6,$M23-1,,-$S23,0),0) -> 0 | U73: =IF(U$59=$M23,FV($U$6,$M23-1,,-$S23,0),0) -> 0 | W73: =IF(W$59=$M23,FV($U$6,$M23-1,,-$S23,0),0) -> 0 | Y73: =IF(Y$59=$M23,FV($U$6,$M23-1,,-$S23,0),0) -> 0 | AA73: =IF(AA$59=$M23,FV($U$6,$M23-1,,-$S23,0),0) -> 0 | AC73: =IF(AC$59=$M23,FV($U$6,$M23-1,,-$S23,0),0) -> 0 | AE73: =IF(AE$59=$M23,FV($U$6,$M23-1,,-$S23,0),0) -> 0 | AG73: =IF(AG$59=$M23,FV($U$6,$M23-1,,-$S23,0),0) -> 0 | AI73: =IF(AI$59=$M23,FV($U$6,$M23-1,,-$S23,0),0) -> 0 | AK73: =IF(AK$59=$M23,FV($U$6,$M23-1,,-$S23,0),0) -> 0
A74: =+A24 -> 11 | C74: =+C24 -> 1 | E74: =+E24 -> x | G74: =+G24 -> x | I74: =IF(I$59=$M24,FV($U$6,$M24-1,,-$S24,0),0) -> 0 | K74: =IF(K$59=$M24,FV($U$6,$M24-1,,-$S24,0),0) -> 0 | M74: =IF(M$59=$M24,FV($U$6,$M24-1,,-$S24,0),0) -> 0 | O74: =IF(O$59=$M24,FV($U$6,$M24-1,,-$S24,0),0) -> 0 | Q74: =IF(Q$59=$M24,FV($U$6,$M24-1,,-$S24,0),0) -> 0 | S74: =IF(S$59=$M24,FV($U$6,$M24-1,,-$S24,0),0) -> 0 | U74: =IF(U$59=$M24,FV($U$6,$M24-1,,-$S24,0),0) -> 0 | W74: =IF(W$59=$M24,FV($U$6,$M24-1,,-$S24,0),0) -> 0 | Y74: =IF(Y$59=$M24,FV($U$6,$M24-1,,-$S24,0),0) -> 0 | AA74: =IF(AA$59=$M24,FV($U$6,$M24-1,,-$S24,0),0) -> 0 | AC74: =IF(AC$59=$M24,FV($U$6,$M24-1,,-$S24,0),0) -> 0 | AE74: =IF(AE$59=$M24,FV($U$6,$M24-1,,-$S24,0),0) -> 0 | AG74: =IF(AG$59=$M24,FV($U$6,$M24-1,,-$S24,0),0) -> 0 | AI74: =IF(AI$59=$M24,FV($U$6,$M24-1,,-$S24,0),0) -> 0 | AK74: =IF(AK$59=$M24,FV($U$6,$M24-1,,-$S24,0),0) -> 0
A75: =+A25 -> 12 | C75: =+C25 -> 1 | E75: =+E25 -> x | G75: =+G25 -> x | I75: =IF(I$59=$M25,FV($U$6,$M25-1,,-$S25,0),0) -> 0 | K75: =IF(K$59=$M25,FV($U$6,$M25-1,,-$S25,0),0) -> 0 | M75: =IF(M$59=$M25,FV($U$6,$M25-1,,-$S25,0),0) -> 0 | O75: =IF(O$59=$M25,FV($U$6,$M25-1,,-$S25,0),0) -> 0 | Q75: =IF(Q$59=$M25,FV($U$6,$M25-1,,-$S25,0),0) -> 0 | S75: =IF(S$59=$M25,FV($U$6,$M25-1,,-$S25,0),0) -> 0 | U75: =IF(U$59=$M25,FV($U$6,$M25-1,,-$S25,0),0) -> 0 | W75: =IF(W$59=$M25,FV($U$6,$M25-1,,-$S25,0),0) -> 0 | Y75: =IF(Y$59=$M25,FV($U$6,$M25-1,,-$S25,0),0) -> 0 | AA75: =IF(AA$59=$M25,FV($U$6,$M25-1,,-$S25,0),0) -> 0 | AC75: =IF(AC$59=$M25,FV($U$6,$M25-1,,-$S25,0),0) -> 0 | AE75: =IF(AE$59=$M25,FV($U$6,$M25-1,,-$S25,0),0) -> 0 | AG75: =IF(AG$59=$M25,FV($U$6,$M25-1,,-$S25,0),0) -> 0 | AI75: =IF(AI$59=$M25,FV($U$6,$M25-1,,-$S25,0),0) -> 0 | AK75: =IF(AK$59=$M25,FV($U$6,$M25-1,,-$S25,0),0) -> 0
... A87: =+A37 -> 24 | C87: =+C37 -> 1 | E87: =+E37 -> x | G87: =+G37 -> x | I87: =IF(I$59=$M37,FV($U$6,$M37-1,,-$S37,0),0) -> 0 | K87: =IF(K$59=$M37,FV($U$6,$M37-1,,-$S37,0),0) -> 0 | M87: =IF(M$59=$M37,FV($U$6,$M37-1,,-$S37,0),0) -> 0 | O87: =IF(O$59=$M37,FV($U$6,$M37-1,,-$S37,0),0) -> 0 | Q87: =IF(Q$59=$M37,FV($U$6,$M37-1,,-$S37,0),0) -> 0 | S87: =IF(S$59=$M37,FV($U$6,$M37-1,,-$S37,0),0) -> 0 | U87: =IF(U$59=$M37,FV($U$6,$M37-1,,-$S37,0),0) -> 0 | W87: =IF(W$59=$M37,FV($U$6,$M37-1,,-$S37,0),0) -> 0 | Y87: =IF(Y$59=$M37,FV($U$6,$M37-1,,-$S37,0),0) -> 0 | AA87: =IF(AA$59=$M37,FV($U$6,$M37-1,,-$S37,0),0) -> 0 | AC87: =IF(AC$59=$M37,FV($U$6,$M37-1,,-$S37,0),0) -> 0 | AE87: =IF(AE$59=$M37,FV($U$6,$M37-1,,-$S37,0),0) -> 0 | AG87: =IF(AG$59=$M37,FV($U$6,$M37-1,,-$S37,0),0) -> 0 | AI87: =IF(AI$59=$M37,FV($U$6,$M37-1,,-$S37,0),0) -> 0 | AK87: =IF(AK$59=$M37,FV($U$6,$M37-1,,-$S37,0),0) -> 0
G89: =G39 -> ELEMENTS (PRN)
A90: =+A40 -> 25 | C90: =+C40 -> 1 | E90: =+E40 -> x | G90: =+G40 -> x | I90: =FV($U$6,AY$9,,-$S$40,0) -> 1.5579674 | K90: =FV($U$6,I$59,,-$S$40,0) -> 1.6047064 | M90: =FV($U$6,K$59,,-$S$40,0) -> 1.6528476 | O90: =FV($U$6,M$59,,-$S$40,0) -> 1.7024331 | Q90: =FV($U$6,O$59,,-$S$40,0) -> 1.7535061 | S90: =FV($U$6,Q$59,,-$S$40,0) -> 1.8061112 | U90: =FV($U$6,S$59,,-$S$40,0) -> 1.8602946 | W90: =FV($U$6,U$59,,-$S$40,0) -> 1.9161034 | Y90: =FV($U$6,W$59,,-$S$40,0) -> 1.9735865 | AA90: =FV($U$6,Y$59,,-$S$40,0) -> 2.0327941 | AC90: =FV($U$6,AA$59,,-$S$40,0) -> 2.0937779 | AE90: =FV($U$6,AC$59,,-$S$40,0) -> 2.1565913 | AG90: =FV($U$6,AE$59,,-$S$40,0) -> 2.221289 | AI90: =FV($U$6,AG$59,,-$S$40,0) -> 2.2879277 | AK90: =FV($U$6,AI$59,,-$S$40,0) -> 2.3565655
A91: =+A41 -> 26 | C91: =+C41 -> 1 | E91: =+E41 -> x | G91: =+G41 -> x | I91: =FV($U$6,AY$9,,-$S$41,0) -> 1.5579674 | K91: =FV($U$6,I$59,,-$S$41,0) -> 1.6047064 | M91: =FV($U$6,K$59,,-$S$41,0) -> 1.6528476 | O91: =FV($U$6,M$59,,-$S$41,0) -> 1.7024331 | Q91: =FV($U$6,O$59,,-$S$41,0) -> 1.7535061 | S91: =FV($U$6,Q$59,,-$S$41,0) -> 1.8061112 | U91: =FV($U$6,S$59,,-$S$41,0) -> 1.8602946 | W91: =FV($U$6,U$59,,-$S$41,0) -> 1.9161034 | Y91: =FV($U$6,W$59,,-$S$41,0) -> 1.9735865 | AA91: =FV($U$6,Y$59,,-$S$41,0) -> 2.0327941 | AC91: =FV($U$6,AA$59,,-$S$41,0) -> 2.0937779 | AE91: =FV($U$6,AC$59,,-$S$41,0) -> 2.1565913 | AG91: =FV($U$6,AE$59,,-$S$41,0) -> 2.221289 | AI91: =FV($U$6,AG$59,,-$S$41,0) -> 2.2879277 | AK91: =FV($U$6,AI$59,,-$S$41,0) -> 2.3565655
A92: =+A42 -> 27 | C92: =+C42 -> 1 | E92: =+E42 -> x | G92: =+G42 -> x | I92: =FV($U$6,AY$9,,-$S$42,0) -> 1.5579674 | K92: =FV($U$6,I$59,,-$S$42,0) -> 1.6047064 | M92: =FV($U$6,K$59,,-$S$42,0) -> 1.6528476 | O92: =FV($U$6,M$59,,-$S$42,0) -> 1.7024331 | Q92: =FV($U$6,O$59,,-$S$42,0) -> 1.7535061 | S92: =FV($U$6,Q$59,,-$S$42,0) -> 1.8061112 | U92: =FV($U$6,S$59,,-$S$42,0) -> 1.8602946 | W92: =FV($U$6,U$59,,-$S$42,0) -> 1.9161034 | Y92: =FV($U$6,W$59,,-$S$42,0) -> 1.9735865 | AA92: =FV($U$6,Y$59,,-$S$42,0) -> 2.0327941 | AC92: =FV($U$6,AA$59,,-$S$42,0) -> 2.0937779 | AE92: =FV($U$6,AC$59,,-$S$42,0) -> 2.1565913 | AG92: =FV($U$6,AE$59,,-$S$42,0) -> 2.221289 | AI92: =FV($U$6,AG$59,,-$S$42,0) -> 2.2879277 | AK92: =FV($U$6,AI$59,,-$S$42,0) -> 2.3565655
A93: =+A43 -> 28 | C93: =+C43 -> 1 | E93: =+E43 -> x | G93: =+G43 -> x | I93: =FV($U$6,AY$9,,-$S$43,0) -> 1.5579674 | K93: =FV($U$6,I$59,,-$S$43,0) -> 1.6047064 | M93: =FV($U$6,K$59,,-$S$43,0) -> 1.6528476 | O93: =FV($U$6,M$59,,-$S$43,0) -> 1.7024331 | Q93: =FV($U$6,O$59,,-$S$43,0) -> 1.7535061 | S93: =FV($U$6,Q$59,,-$S$43,0) -> 1.8061112 | U93: =FV($U$6,S$59,,-$S$43,0) -> 1.8602946 | W93: =FV($U$6,U$59,,-$S$43,0) -> 1.9161034 | Y93: =FV($U$6,W$59,,-$S$43,0) -> 1.9735865 | AA93: =FV($U$6,Y$59,,-$S$43,0) -> 2.0327941 | AC93: =FV($U$6,AA$59,,-$S$43,0) -> 2.0937779 | AE93: =FV($U$6,AC$59,,-$S$43,0) -> 2.1565913 | AG93: =FV($U$6,AE$59,,-$S$43,0) -> 2.221289 | AI93: =FV($U$6,AG$59,,-$S$43,0) -> 2.2879277 | AK93: =FV($U$6,AI$59,,-$S$43,0) -> 2.3565655
A94: =+A44 -> 29 | C94: =+C44 -> 1 | E94: =+E44 -> x | G94: =+G44 -> x | I94: =FV($U$6,AY$9,,-$S$44,0) -> 1.5579674 | K94: =FV($U$6,I$59,,-$S$44,0) -> 1.6047064 | M94: =FV($U$6,K$59,,-$S$44,0) -> 1.6528476 | O94: =FV($U$6,M$59,,-$S$44,0) -> 1.7024331 | Q94: =FV($U$6,O$59,,-$S$44,0) -> 1.7535061 | S94: =FV($U$6,Q$59,,-$S$44,0) -> 1.8061112 | U94: =FV($U$6,S$59,,-$S$44,0) -> 1.8602946 | W94: =FV($U$6,U$59,,-$S$44,0) -> 1.9161034 | Y94: =FV($U$6,W$59,,-$S$44,0) -> 1.9735865 | AA94: =FV($U$6,Y$59,,-$S$44,0) -> 2.0327941 | AC94: =FV($U$6,AA$59,,-$S$44,0) -> 2.0937779 | AE94: =FV($U$6,AC$59,,-$S$44,0) -> 2.1565913 | AG94: =FV($U$6,AE$59,,-$S$44,0) -> 2.221289 | AI94: =FV($U$6,AG$59,,-$S$44,0) -> 2.2879277 | AK94: =FV($U$6,AI$59,,-$S$44,0) -> 2.3565655
A95: =+A45 -> 30 | C95: =+C45 -> 1 | E95: =+E45 -> x | G95: =+G45 -> x | I95: =FV($U$6,AY$9,,-$S$45,0) -> 1.5579674 | K95: =FV($U$6,I$59,,-$S$45,0) -> 1.6047064 | M95: =FV($U$6,K$59,,-$S$45,0) -> 1.6528476 | O95: =FV($U$6,M$59,,-$S$45,0) -> 1.7024331 | Q95: =FV($U$6,O$59,,-$S$45,0) -> 1.7535061 | S95: =FV($U$6,Q$59,,-$S$45,0) -> 1.8061112 | U95: =FV($U$6,S$59,,-$S$45,0) -> 1.8602946 | W95: =FV($U$6,U$59,,-$S$45,0) -> 1.9161034 | Y95: =FV($U$6,W$59,,-$S$45,0) -> 1.9735865 | AA95: =FV($U$6,Y$59,,-$S$45,0) -> 2.0327941 | AC95: =FV($U$6,AA$59,,-$S$45,0) -> 2.0937779 | AE95: =FV($U$6,AC$59,,-$S$45,0) -> 2.1565913 | AG95: =FV($U$6,AE$59,,-$S$45,0) -> 2.221289 | AI95: =FV($U$6,AG$59,,-$S$45,0) -> 2.2879277 | AK95: =FV($U$6,AI$59,,-$S$45,0) -> 2.3565655
A96: =+A46 -> 31 | C96: =+C46 -> 1 | E96: =+E46 -> x | G96: =+G46 -> x | I96: =FV($U$6,AY$9,,-$S$46,0) -> 1.5579674 | K96: =FV($U$6,I$59,,-$S$46,0) -> 1.6047064 | M96: =FV($U$6,K$59,,-$S$46,0) -> 1.6528476 | O96: =FV($U$6,M$59,,-$S$46,0) -> 1.7024331 | Q96: =FV($U$6,O$59,,-$S$46,0) -> 1.7535061 | S96: =FV($U$6,Q$59,,-$S$46,0) -> 1.8061112 | U96: =FV($U$6,S$59,,-$S$46,0) -> 1.8602946 | W96: =FV($U$6,U$59,,-$S$46,0) -> 1.9161034 | Y96: =FV($U$6,W$59,,-$S$46,0) -> 1.9735865 | AA96: =FV($U$6,Y$59,,-$S$46,0) -> 2.0327941 | AC96: =FV($U$6,AA$59,,-$S$46,0) -> 2.0937779 | AE96: =FV($U$6,AC$59,,-$S$46,0) -> 2.1565913 | AG96: =FV($U$6,AE$59,,-$S$46,0) -> 2.221289 | AI96: =FV($U$6,AG$59,,-$S$46,0) -> 2.2879277 | AK96: =FV($U$6,AI$59,,-$S$46,0) -> 2.3565655
A97: =+A47 -> 32 | C97: =+C47 -> 1 | E97: =+E47 -> x | G97: =+G47 -> x | I97: =FV($U$6,AY$9,,-$S$47,0) -> 1.5579674 | K97: =FV($U$6,I$59,,-$S$47,0) -> 1.6047064 | M97: =FV($U$6,K$59,,-$S$47,0) -> 1.6528476 | O97: =FV($U$6,M$59,,-$S$47,0) -> 1.7024331 | Q97: =FV($U$6,O$59,,-$S$47,0) -> 1.7535061 | S97: =FV($U$6,Q$59,,-$S$47,0) -> 1.8061112 | U97: =FV($U$6,S$59,,-$S$47,0) -> 1.8602946 | W97: =FV($U$6,U$59,,-$S$47,0) -> 1.9161034 | Y97: =FV($U$6,W$59,,-$S$47,0) -> 1.9735865 | AA97: =FV($U$6,Y$59,,-$S$47,0) -> 2.0327941 | AC97: =FV($U$6,AA$59,,-$S$47,0) -> 2.0937779 | AE97: =FV($U$6,AC$59,,-$S$47,0) -> 2.1565913 | AG97: =FV($U$6,AE$59,,-$S$47,0) -> 2.221289 | AI97: =FV($U$6,AG$59,,-$S$47,0) -> 2.2879277 | AK97: =FV($U$6,AI$59,,-$S$47,0) -> 2.3565655
A98: =+A48 -> 33 | C98: =+C48 -> 1 | E98: =+E48 -> x | G98: =+G48 -> x | I98: =FV($U$6,AY$9,,-$S$48,0) -> 1.5579674 | K98: =FV($U$6,I$59,,-$S$47,0) -> 1.6047064 | M98: =FV($U$6,K$59,,-$S$47,0) -> 1.6528476 | O98: =FV($U$6,M$59,,-$S$47,0) -> 1.7024331 | Q98: =FV($U$6,O$59,,-$S$47,0) -> 1.7535061 | S98: =FV($U$6,Q$59,,-$S$47,0) -> 1.8061112 | U98: =FV($U$6,S$59,,-$S$47,0) -> 1.8602946 | W98: =FV($U$6,U$59,,-$S$47,0) -> 1.9161034 | Y98: =FV($U$6,W$59,,-$S$47,0) -> 1.9735865 | AA98: =FV($U$6,Y$59,,-$S$47,0) -> 2.0327941 | AC98: =FV($U$6,AA$59,,-$S$47,0) -> 2.0937779 | AE98: =FV($U$6,AC$59,,-$S$47,0) -> 2.1565913 | AG98: =FV($U$6,AE$59,,-$S$47,0) -> 2.221289 | AI98: =FV($U$6,AG$59,,-$S$47,0) -> 2.2879277 | AK98: =FV($U$6,AI$59,,-$S$47,0) -> 2.3565655
A99: =+A49 -> 34 | C99: =+C49 -> 1 | E99: =+E49 -> x | G99: =+G49 -> x | I99: =FV($U$6,AY$9,,-$S$49,0) -> 1.5579674 | K99: =FV($U$6,I$59,,-$S$49,0) -> 1.6047064 | M99: =FV($U$6,K$59,,-$S$49,0) -> 1.6528476 | O99: =FV($U$6,M$59,,-$S$49,0) -> 1.7024331 | Q99: =FV($U$6,O$59,,-$S$49,0) -> 1.7535061 | S99: =FV($U$6,Q$59,,-$S$49,0) -> 1.8061112 | U99: =FV($U$6,S$59,,-$S$49,0) -> 1.8602946 | W99: =FV($U$6,U$59,,-$S$49,0) -> 1.9161034 | Y99: =FV($U$6,W$59,,-$S$49,0) -> 1.9735865 | AA99: =FV($U$6,Y$59,,-$S$49,0) -> 2.0327941 | AC99: =FV($U$6,AA$59,,-$S$49,0) -> 2.0937779 | AE99: =FV($U$6,AC$59,,-$S$49,0) -> 2.1565913 | AG99: =FV($U$6,AE$59,,-$S$49,0) -> 2.221289 | AI99: =FV($U$6,AG$59,,-$S$49,0) -> 2.2879277 | AK99: =FV($U$6,AI$59,,-$S$49,0) -> 2.3565655
A100: =+A50 -> 35 | C100: =+C50 -> 1 | E100: =+E50 -> x | G100: =+G50 -> x | I100: =FV($U$6,AY$9,,-$S$50,0) -> 1.5579674 | K100: =FV($U$6,I$59,,-$S$50,0) -> 1.6047064 | M100: =FV($U$6,K$59,,-$S$50,0) -> 1.6528476 | O100: =FV($U$6,M$59,,-$S$50,0) -> 1.7024331 | Q100: =FV($U$6,O$59,,-$S$50,0) -> 1.7535061 | S100: =FV($U$6,Q$59,,-$S$50,0) -> 1.8061112 | U100: =FV($U$6,S$59,,-$S$50,0) -> 1.8602946 | W100: =FV($U$6,U$59,,-$S$50,0) -> 1.9161034 | Y100: =FV($U$6,W$59,,-$S$50,0) -> 1.9735865 | AA100: =FV($U$6,Y$59,,-$S$50,0) -> 2.0327941 | AC100: =FV($U$6,AA$59,,-$S$50,0) -> 2.0937779 | AE100: =FV($U$6,AC$59,,-$S$50,0) -> 2.1565913 | AG100: =FV($U$6,AE$59,,-$S$50,0) -> 2.221289 | AI100: =FV($U$6,AG$59,,-$S$50,0) -> 2.2879277 | AK100: =FV($U$6,AI$59,,-$S$50,0) -> 2.3565655
A101: =+A51 -> 36 | C101: =+C51 -> 1 | E101: =+E51 -> x | G101: =+G51 -> x | I101: =FV($U$6,AY$9,,-$S$51,0) -> 1.5579674 | K101: =FV($U$6,I$59,,-$S$51,0) -> 1.6047064 | M101: =FV($U$6,K$59,,-$S$51,0) -> 1.6528476 | O101: =FV($U$6,M$59,,-$S$51,0) -> 1.7024331 | Q101: =FV($U$6,O$59,,-$S$51,0) -> 1.7535061 | S101: =FV($U$6,Q$59,,-$S$51,0) -> 1.8061112 | U101: =FV($U$6,S$59,,-$S$51,0) -> 1.8602946 | W101: =FV($U$6,U$59,,-$S$51,0) -> 1.9161034 | Y101: =FV($U$6,W$59,,-$S$51,0) -> 1.9735865 | AA101: =FV($U$6,Y$59,,-$S$51,0) -> 2.0327941 | AC101: =FV($U$6,AA$59,,-$S$51,0) -> 2.0937779 | AE101: =FV($U$6,AC$59,,-$S$51,0) -> 2.1565913 | AG101: =FV($U$6,AE$59,,-$S$51,0) -> 2.221289 | AI101: =FV($U$6,AG$59,,-$S$51,0) -> 2.2879277 | AK101: =FV($U$6,AI$59,,-$S$51,0) -> 2.3565655
A102: =+A52 -> 37 | C102: =+C52 -> 1 | E102: =+E52 -> x | G102: =+G52 -> x | I102: =FV($U$6,AY$9,,-$S$52,0) -> 1.5579674 | K102: =FV($U$6,I$59,,-$S$52,0) -> 1.6047064 | M102: =FV($U$6,K$59,,-$S$52,0) -> 1.6528476 | O102: =FV($U$6,M$59,,-$S$52,0) -> 1.7024331 | Q102: =FV($U$6,O$59,,-$S$52,0) -> 1.7535061 | S102: =FV($U$6,Q$59,,-$S$52,0) -> 1.8061112 | U102: =FV($U$6,S$59,,-$S$52,0) -> 1.8602946 | W102: =FV($U$6,U$59,,-$S$52,0) -> 1.9161034 | Y102: =FV($U$6,W$59,,-$S$52,0) -> 1.9735865 | AA102: =FV($U$6,Y$59,,-$S$52,0) -> 2.0327941 | AC102: =FV($U$6,AA$59,,-$S$52,0) -> 2.0937779 | AE102: =FV($U$6,AC$59,,-$S$52,0) -> 2.1565913 | AG102: =FV($U$6,AE$59,,-$S$52,0) -> 2.221289 | AI102: =FV($U$6,AG$59,,-$S$52,0) -> 2.2879277 | AK102: =FV($U$6,AI$59,,-$S$52,0) -> 2.3565655
A103: =+A53 -> 38 | C103: =+C53 -> 1 | E103: =+E53 -> x | G103: =+G53 -> x | I103: =FV($U$6,AY$9,,-$S$53,0) -> 1.5579674 | K103: =FV($U$6,I$59,,-$S$53,0) -> 1.6047064 | M103: =FV($U$6,K$59,,-$S$53,0) -> 1.6528476 | O103: =FV($U$6,M$59,,-$S$53,0) -> 1.7024331 | Q103: =FV($U$6,O$59,,-$S$53,0) -> 1.7535061 | S103: =FV($U$6,Q$59,,-$S$53,0) -> 1.8061112 | U103: =FV($U$6,S$59,,-$S$53,0) -> 1.8602946 | W103: =FV($U$6,U$59,,-$S$53,0) -> 1.9161034 | Y103: =FV($U$6,W$59,,-$S$53,0) -> 1.9735865 | AA103: =FV($U$6,Y$59,,-$S$53,0) -> 2.0327941 | AC103: =FV($U$6,AA$59,,-$S$53,0) -> 2.0937779 | AE103: =FV($U$6,AC$59,,-$S$53,0) -> 2.1565913 | AG103: =FV($U$6,AE$59,,-$S$53,0) -> 2.221289 | AI103: =FV($U$6,AG$59,,-$S$53,0) -> 2.2879277 | AK103: =FV($U$6,AI$59,,-$S$53,0) -> 2.3565655
A104: =+A54 -> 39 | C104: =+C54 -> 1 | E104: =+E54 -> x | G104: =+G54 -> x | I104: =FV($U$6,AY$9,,-$S$54,0) -> 1.5579674 | K104: =FV($U$6,I$59,,-$S$54,0) -> 1.6047064 | M104: =FV($U$6,K$59,,-$S$54,0) -> 1.6528476 | O104: =FV($U$6,M$59,,-$S$54,0) -> 1.7024331 | Q104: =FV($U$6,O$59,,-$S$54,0) -> 1.7535061 | S104: =FV($U$6,Q$59,,-$S$54,0) -> 1.8061112 | U104: =FV($U$6,S$59,,-$S$54,0) -> 1.8602946 | W104: =FV($U$6,U$59,,-$S$54,0) -> 1.9161034 | Y104: =FV($U$6,W$59,,-$S$54,0) -> 1.9735865 | AA104: =FV($U$6,Y$59,,-$S$54,0) -> 2.0327941 | AC104: =FV($U$6,AA$59,,-$S$54,0) -> 2.0937779 | AE104: =FV($U$6,AC$59,,-$S$54,0) -> 2.1565913 | AG104: =FV($U$6,AE$59,,-$S$54,0) -> 2.221289 | AI104: =FV($U$6,AG$59,,-$S$54,0) -> 2.2879277 | AK104: =FV($U$6,AI$59,,-$S$54,0) -> 2.3565655
G107: =+G56 -> Anticipated Expenditures, By Year | I107: =SUM(I64:I106) -> 23.369511 | K107: =SUM(K64:K106) -> 24.070597 | M107: =SUM(M64:M106) -> 24.792714 | O107: =SUM(O64:O106) -> 25.536496 | Q107: =SUM(Q64:Q106) -> 26.302591 | S107: =SUM(S64:S106) -> 27.091669 | U107: =SUM(U64:U106) -> 27.904419 | W107: =SUM(W64:W106) -> 28.741551 | Y107: =SUM(Y64:Y106) -> 29.603798 | AA107: =SUM(AA64:AA106) -> 30.491912 | AC107: =SUM(AC64:AC106) -> 31.406669 | AE107: =SUM(AE64:AE106) -> 32.348869 | AG107: =SUM(AG64:AG106) -> 33.319335 | AI107: =SUM(AI64:AI106) -> 34.318915 | AK107: =SUM(AK64:AK106) -> 35.348483

Sheet Combo 2
G3: Exhibit B
G5: RESERVE EXPENDITURES | U5: Explanatory Notes:
G6: for | T6: 1) | U6: =+'Roofs 1'!V3 -> 0.03 | V6: is the estimated future Inflation Rate for estimating Future Replacement Costs.
G7: =+'Roofs 1'!H5 -> Association | T7: 2) | U7: Fiscal Year is beginning January 1 and ending December 31.
A9: Line Item | C9: Estimated | I9: Estimated Year Last Replaced | K9: Life Analysis, Years | O9: Estimated Year of 1st Replacement | Q9: =+'Roofs 1'!R6 -> 2024 Unit Cost | S9: =+'Roofs 1'!T6 -> 2024 Cost of Replacement | U9: Total Future Cost of Replacement | W9: 1 | Y9: 2 | AA9: 3 | AC9: 4 | AE9: 5 | AG9: 6 | AI9: 7 | AK9: 8 | AM9: 9 | AO9: 10 | AQ9: 11 | AS9: 12 | AU9: 13 | AW9: 14 | AY9: 15
C10: Quantity | E10: Units | G10: Reserve Component Inventory | K10: Useful | M10: Remaining | W10: =+'Roofs 1'!X7 -> 2024 | Y10: =W10+1 -> 2025 | Z10: =X10+1 -> 1 | AA10: =Y10+1 -> 2026 | AB10: =Z10+1 -> 2 | AC10: =AA10+1 -> 2027 | AD10: =AB10+1 -> 3 | AE10: =AC10+1 -> 2028 | AF10: =AD10+1 -> 4 | ... AY10: =AW10+1 -> 2038
G12: ELEMENTS REPLACE | X12: =+'Roofs 1'!Y9 -> 0 | Z12: =+'Roofs 1'!AA9 -> 0
A14: ='Maintain (PRN) 1'!A35+1 -> 63 | C14: 1 | E14: x | G14: x | I14: x | K14: x | M14: 1 | N14: ='Roofs 1'!P4 -> 2023 | O14: =+$W$10-1+M14 -> 2024 | Q14: 1 | S14: =C14*Q14 -> 1 | U14: =SUM(W14:AY14)+SUM(I40:AK40) -> 1 | W14: =IF(W$9=$M14,FV($U$6,$M14-1,,-$S14,0),0) -> 1 | Y14: =IF(Y$9=$M14,FV($U$6,$M14-1,,-$S14,0),0) -> 0 | AA14: =IF(AA$9=$M14,FV($U$6,$M14-1,,-$S14,0),0) -> 0 | AC14: =IF(AC$9=$M14,FV($U$6,$M14-1,,-$S14,0),0) -> 0 | AE14: =IF(AE$9=$M14,FV($U$6,$M14-1,,-$S14,0),0) -> 0 | AG14: =IF(AG$9=$M14,FV($U$6,$M14-1,,-$S14,0),0) -> 0 | AI14: =IF(AI$9=$M14,FV($U$6,$M14-1,,-$S14,0),0) -> 0 | AK14: =IF(AK$9=$M14,FV($U$6,$M14-1,,-$S14,0),0) -> 0 | AM14: =IF(AM$9=$M14,FV($U$6,$M14-1,,-$S14,0),0) -> 0 | AO14: =IF(AO$9=$M14,FV($U$6,$M14-1,,-$S14,0),0) -> 0 | AQ14: =IF(AQ$9=$M14,FV($U$6,$M14-1,,-$S14,0),0) -> 0 | AS14: =IF(AS$9=$M14,FV($U$6,$M14-1,,-$S14,0),0) -> 0 | AU14: =IF(AU$9=$M14,FV($U$6,$M14-1,,-$S14,0),0) -> 0 | AW14: =IF(AW$9=$M14,FV($U$6,$M14-1,,-$S14,0),0) -> 0 | AY14: =IF(AY$9=$M14,FV($U$6,$M14-1,,-$S14,0),0) -> 0
A15: =A14+1 -> 64 | C15: 1 | E15: x | G15: x | I15: x | K15: x | M15: 1 | N15: =N14 -> 2023 | O15: =+$W$10-1+M15 -> 2024 | Q15: 1 | S15: =C15*Q15 -> 1 | U15: =SUM(W15:AY15)+SUM(I41:AK41) -> 1 | W15: =IF(W$9=$M15,FV($U$6,$M15-1,,-$S15,0),0) -> 1 | Y15: =IF(Y$9=$M15,FV($U$6,$M15-1,,-$S15,0),0) -> 0 | AA15: =IF(AA$9=$M15,FV($U$6,$M15-1,,-$S15,0),0) -> 0 | AC15: =IF(AC$9=$M15,FV($U$6,$M15-1,,-$S15,0),0) -> 0 | AE15: =IF(AE$9=$M15,FV($U$6,$M15-1,,-$S15,0),0) -> 0 | AG15: =IF(AG$9=$M15,FV($U$6,$M15-1,,-$S15,0),0) -> 0 | AI15: =IF(AI$9=$M15,FV($U$6,$M15-1,,-$S15,0),0) -> 0 | AK15: =IF(AK$9=$M15,FV($U$6,$M15-1,,-$S15,0),0) -> 0 | AM15: =IF(AM$9=$M15,FV($U$6,$M15-1,,-$S15,0),0) -> 0 | AO15: =IF(AO$9=$M15,FV($U$6,$M15-1,,-$S15,0),0) -> 0 | AQ15: =IF(AQ$9=$M15,FV($U$6,$M15-1,,-$S15,0),0) -> 0 | AS15: =IF(AS$9=$M15,FV($U$6,$M15-1,,-$S15,0),0) -> 0 | AU15: =IF(AU$9=$M15,FV($U$6,$M15-1,,-$S15,0),0) -> 0 | AW15: =IF(AW$9=$M15,FV($U$6,$M15-1,,-$S15,0),0) -> 0 | AY15: =IF(AY$9=$M15,FV($U$6,$M15-1,,-$S15,0),0) -> 0
A16: =A15+1 -> 65 | C16: 1 | E16: x | G16: x | I16: x | K16: x | M16: 1 | N16: =N15 -> 2023 | O16: =+$W$10-1+M16 -> 2024 | Q16: 1 | S16: =C16*Q16 -> 1 | U16: =SUM(W16:AY16)+SUM(I42:AK42) -> 1 | W16: =IF(W$9=$M16,FV($U$6,$M16-1,,-$S16,0),0) -> 1 | Y16: =IF(Y$9=$M16,FV($U$6,$M16-1,,-$S16,0),0) -> 0 | AA16: =IF(AA$9=$M16,FV($U$6,$M16-1,,-$S16,0),0) -> 0 | AC16: =IF(AC$9=$M16,FV($U$6,$M16-1,,-$S16,0),0) -> 0 | AE16: =IF(AE$9=$M16,FV($U$6,$M16-1,,-$S16,0),0) -> 0 | AG16: =IF(AG$9=$M16,FV($U$6,$M16-1,,-$S16,0),0) -> 0 | AI16: =IF(AI$9=$M16,FV($U$6,$M16-1,,-$S16,0),0) -> 0 | AK16: =IF(AK$9=$M16,FV($U$6,$M16-1,,-$S16,0),0) -> 0 | AM16: =IF(AM$9=$M16,FV($U$6,$M16-1,,-$S16,0),0) -> 0 | AO16: =IF(AO$9=$M16,FV($U$6,$M16-1,,-$S16,0),0) -> 0 | AQ16: =IF(AQ$9=$M16,FV($U$6,$M16-1,,-$S16,0),0) -> 0 | AS16: =IF(AS$9=$M16,FV($U$6,$M16-1,,-$S16,0),0) -> 0 | AU16: =IF(AU$9=$M16,FV($U$6,$M16-1,,-$S16,0),0) -> 0 | AW16: =IF(AW$9=$M16,FV($U$6,$M16-1,,-$S16,0),0) -> 0 | AY16: =IF(AY$9=$M16,FV($U$6,$M16-1,,-$S16,0),0) -> 0
A17: =A16+1 -> 66 | C17: 1 | E17: x | G17: x | I17: x | K17: x | M17: 1 | N17: =N16 -> 2023 | O17: =+$W$10-1+M17 -> 2024 | Q17: 1 | S17: =C17*Q17 -> 1 | U17: =SUM(W17:AY17)+SUM(I43:AK43) -> 1 | W17: =IF(W$9=$M17,FV($U$6,$M17-1,,-$S17,0),0) -> 1 | Y17: =IF(Y$9=$M17,FV($U$6,$M17-1,,-$S17,0),0) -> 0 | AA17: =IF(AA$9=$M17,FV($U$6,$M17-1,,-$S17,0),0) -> 0 | AC17: =IF(AC$9=$M17,FV($U$6,$M17-1,,-$S17,0),0) -> 0 | AE17: =IF(AE$9=$M17,FV($U$6,$M17-1,,-$S17,0),0) -> 0 | AG17: =IF(AG$9=$M17,FV($U$6,$M17-1,,-$S17,0),0) -> 0 | AI17: =IF(AI$9=$M17,FV($U$6,$M17-1,,-$S17,0),0) -> 0 | AK17: =IF(AK$9=$M17,FV($U$6,$M17-1,,-$S17,0),0) -> 0 | AM17: =IF(AM$9=$M17,FV($U$6,$M17-1,,-$S17,0),0) -> 0 | AO17: =IF(AO$9=$M17,FV($U$6,$M17-1,,-$S17,0),0) -> 0 | AQ17: =IF(AQ$9=$M17,FV($U$6,$M17-1,,-$S17,0),0) -> 0 | AS17: =IF(AS$9=$M17,FV($U$6,$M17-1,,-$S17,0),0) -> 0 | AU17: =IF(AU$9=$M17,FV($U$6,$M17-1,,-$S17,0),0) -> 0 | AW17: =IF(AW$9=$M17,FV($U$6,$M17-1,,-$S17,0),0) -> 0 | AY17: =IF(AY$9=$M17,FV($U$6,$M17-1,,-$S17,0),0) -> 0
A18: =A17+1 -> 67 | C18: 1 | E18: x | G18: x | I18: x | K18: x | M18: 1 | N18: =N17 -> 2023 | O18: =+$W$10-1+M18 -> 2024 | Q18: 1 | S18: =C18*Q18 -> 1 | U18: =SUM(W18:AY18)+SUM(I44:AK44) -> 1 | W18: =IF(W$9=$M18,FV($U$6,$M18-1,,-$S18,0),0) -> 1 | Y18: =IF(Y$9=$M18,FV($U$6,$M18-1,,-$S18,0),0) -> 0 | AA18: =IF(AA$9=$M18,FV($U$6,$M18-1,,-$S18,0),0) -> 0 | AC18: =IF(AC$9=$M18,FV($U$6,$M18-1,,-$S18,0),0) -> 0 | AE18: =IF(AE$9=$M18,FV($U$6,$M18-1,,-$S18,0),0) -> 0 | AG18: =IF(AG$9=$M18,FV($U$6,$M18-1,,-$S18,0),0) -> 0 | AI18: =IF(AI$9=$M18,FV($U$6,$M18-1,,-$S18,0),0) -> 0 | AK18: =IF(AK$9=$M18,FV($U$6,$M18-1,,-$S18,0),0) -> 0 | AM18: =IF(AM$9=$M18,FV($U$6,$M18-1,,-$S18,0),0) -> 0 | AO18: =IF(AO$9=$M18,FV($U$6,$M18-1,,-$S18,0),0) -> 0 | AQ18: =IF(AQ$9=$M18,FV($U$6,$M18-1,,-$S18,0),0) -> 0 | AS18: =IF(AS$9=$M18,FV($U$6,$M18-1,,-$S18,0),0) -> 0 | AU18: =IF(AU$9=$M18,FV($U$6,$M18-1,,-$S18,0),0) -> 0 | AW18: =IF(AW$9=$M18,FV($U$6,$M18-1,,-$S18,0),0) -> 0 | AY18: =IF(AY$9=$M18,FV($U$6,$M18-1,,-$S18,0),0) -> 0
A19: =A18+1 -> 68 | C19: 1 | E19: x | G19: x | I19: x | K19: x | M19: 1 | N19: =N18 -> 2023 | O19: =+$W$10-1+M19 -> 2024 | Q19: 1 | S19: =C19*Q19 -> 1 | U19: =SUM(W19:AY19)+SUM(I45:AK45) -> 1 | W19: =IF(W$9=$M19,FV($U$6,$M19-1,,-$S19,0),0) -> 1 | Y19: =IF(Y$9=$M19,FV($U$6,$M19-1,,-$S19,0),0) -> 0 | AA19: =IF(AA$9=$M19,FV($U$6,$M19-1,,-$S19,0),0) -> 0 | AC19: =IF(AC$9=$M19,FV($U$6,$M19-1,,-$S19,0),0) -> 0 | AE19: =IF(AE$9=$M19,FV($U$6,$M19-1,,-$S19,0),0) -> 0 | AG19: =IF(AG$9=$M19,FV($U$6,$M19-1,,-$S19,0),0) -> 0 | AI19: =IF(AI$9=$M19,FV($U$6,$M19-1,,-$S19,0),0) -> 0 | AK19: =IF(AK$9=$M19,FV($U$6,$M19-1,,-$S19,0),0) -> 0 | AM19: =IF(AM$9=$M19,FV($U$6,$M19-1,,-$S19,0),0) -> 0 | AO19: =IF(AO$9=$M19,FV($U$6,$M19-1,,-$S19,0),0) -> 0 | AQ19: =IF(AQ$9=$M19,FV($U$6,$M19-1,,-$S19,0),0) -> 0 | AS19: =IF(AS$9=$M19,FV($U$6,$M19-1,,-$S19,0),0) -> 0 | AU19: =IF(AU$9=$M19,FV($U$6,$M19-1,,-$S19,0),0) -> 0 | AW19: =IF(AW$9=$M19,FV($U$6,$M19-1,,-$S19,0),0) -> 0 | AY19: =IF(AY$9=$M19,FV($U$6,$M19-1,,-$S19,0),0) -> 0
A20: =A19+1 -> 69 | C20: 1 | E20: x | G20: x | I20: x | K20: x | M20: 1 | N20: =N19 -> 2023 | O20: =+$W$10-1+M20 -> 2024 | Q20: 1 | S20: =C20*Q20 -> 1 | U20: =SUM(W20:AY20)+SUM(I46:AK46) -> 1 | W20: =IF(W$9=$M20,FV($U$6,$M20-1,,-$S20,0),0) -> 1 | Y20: =IF(Y$9=$M20,FV($U$6,$M20-1,,-$S20,0),0) -> 0 | AA20: =IF(AA$9=$M20,FV($U$6,$M20-1,,-$S20,0),0) -> 0 | AC20: =IF(AC$9=$M20,FV($U$6,$M20-1,,-$S20,0),0) -> 0 | AE20: =IF(AE$9=$M20,FV($U$6,$M20-1,,-$S20,0),0) -> 0 | AG20: =IF(AG$9=$M20,FV($U$6,$M20-1,,-$S20,0),0) -> 0 | AI20: =IF(AI$9=$M20,FV($U$6,$M20-1,,-$S20,0),0) -> 0 | AK20: =IF(AK$9=$M20,FV($U$6,$M20-1,,-$S20,0),0) -> 0 | AM20: =IF(AM$9=$M20,FV($U$6,$M20-1,,-$S20,0),0) -> 0 | AO20: =IF(AO$9=$M20,FV($U$6,$M20-1,,-$S20,0),0) -> 0 | AQ20: =IF(AQ$9=$M20,FV($U$6,$M20-1,,-$S20,0),0) -> 0 | AS20: =IF(AS$9=$M20,FV($U$6,$M20-1,,-$S20,0),0) -> 0 | AU20: =IF(AU$9=$M20,FV($U$6,$M20-1,,-$S20,0),0) -> 0 | AW20: =IF(AW$9=$M20,FV($U$6,$M20-1,,-$S20,0),0) -> 0 | AY20: =IF(AY$9=$M20,FV($U$6,$M20-1,,-$S20,0),0) -> 0
A21: =A20+1 -> 70 | C21: 1 | E21: x | G21: x | I21: x | K21: x | M21: 1 | N21: =N20 -> 2023 | O21: =+$W$10-1+M21 -> 2024 | Q21: 1 | S21: =C21*Q21 -> 1 | U21: =SUM(W21:AY21)+SUM(I47:AK47) -> 1 | W21: =IF(W$9=$M21,FV($U$6,$M21-1,,-$S21,0),0) -> 1 | Y21: =IF(Y$9=$M21,FV($U$6,$M21-1,,-$S21,0),0) -> 0 | AA21: =IF(AA$9=$M21,FV($U$6,$M21-1,,-$S21,0),0) -> 0 | AC21: =IF(AC$9=$M21,FV($U$6,$M21-1,,-$S21,0),0) -> 0 | AE21: =IF(AE$9=$M21,FV($U$6,$M21-1,,-$S21,0),0) -> 0 | AG21: =IF(AG$9=$M21,FV($U$6,$M21-1,,-$S21,0),0) -> 0 | AI21: =IF(AI$9=$M21,FV($U$6,$M21-1,,-$S21,0),0) -> 0 | AK21: =IF(AK$9=$M21,FV($U$6,$M21-1,,-$S21,0),0) -> 0 | AM21: =IF(AM$9=$M21,FV($U$6,$M21-1,,-$S21,0),0) -> 0 | AO21: =IF(AO$9=$M21,FV($U$6,$M21-1,,-$S21,0),0) -> 0 | AQ21: =IF(AQ$9=$M21,FV($U$6,$M21-1,,-$S21,0),0) -> 0 | AS21: =IF(AS$9=$M21,FV($U$6,$M21-1,,-$S21,0),0) -> 0 | AU21: =IF(AU$9=$M21,FV($U$6,$M21-1,,-$S21,0),0) -> 0 | AW21: =IF(AW$9=$M21,FV($U$6,$M21-1,,-$S21,0),0) -> 0 | AY21: =IF(AY$9=$M21,FV($U$6,$M21-1,,-$S21,0),0) -> 0
A22: =A21+1 -> 71 | C22: 1 | E22: x | G22: x | I22: x | K22: x | M22: 1 | N22: =N21 -> 2023 | O22: =+$W$10-1+M22 -> 2024 | Q22: 1 | S22: =C22*Q22 -> 1 | U22: =SUM(W22:AY22)+SUM(I48:AK48) -> 1 | W22: =IF(W$9=$M22,FV($U$6,$M22-1,,-$S22,0),0) -> 1 | Y22: =IF(Y$9=$M22,FV($U$6,$M22-1,,-$S22,0),0) -> 0 | AA22: =IF(AA$9=$M22,FV($U$6,$M22-1,,-$S22,0),0) -> 0 | AC22: =IF(AC$9=$M22,FV($U$6,$M22-1,,-$S22,0),0) -> 0 | AE22: =IF(AE$9=$M22,FV($U$6,$M22-1,,-$S22,0),0) -> 0 | AG22: =IF(AG$9=$M22,FV($U$6,$M22-1,,-$S22,0),0) -> 0 | AI22: =IF(AI$9=$M22,FV($U$6,$M22-1,,-$S22,0),0) -> 0 | AK22: =IF(AK$9=$M22,FV($U$6,$M22-1,,-$S22,0),0) -> 0 | AM22: =IF(AM$9=$M22,FV($U$6,$M22-1,,-$S22,0),0) -> 0 | AO22: =IF(AO$9=$M22,FV($U$6,$M22-1,,-$S22,0),0) -> 0 | AQ22: =IF(AQ$9=$M22,FV($U$6,$M22-1,,-$S22,0),0) -> 0 | AS22: =IF(AS$9=$M22,FV($U$6,$M22-1,,-$S22,0),0) -> 0 | AU22: =IF(AU$9=$M22,FV($U$6,$M22-1,,-$S22,0),0) -> 0 | AW22: =IF(AW$9=$M22,FV($U$6,$M22-1,,-$S22,0),0) -> 0 | AY22: =IF(AY$9=$M22,FV($U$6,$M22-1,,-$S22,0),0) -> 0
G24: ELEMENTS (PRN)
A25: =A22+1 -> 72 | C25: 1 | E25: x | G25: x | I25: x | K25: x | M25: 1 | N25: ='Roofs 1'!P4 -> 2023 | O25: =+$W$10-1+M25 -> 2024 | Q25: 1 | S25: =C25*Q25 -> 1 | U25: =SUM(W25:AY25)+SUM(I51:AK51) -> 47.575416 | W25: =S25 -> 1 | Y25: =FV($U$6,W$9,,-$S25,0) -> 1.03 | AA25: =FV($U$6,Y$9,,-$S25,0) -> 1.0609 | AC25: =FV($U$6,AA$9,,-$S25,0) -> 1.092727 | AE25: =FV($U$6,AC$9,,-$S25,0) -> 1.1255088 | AG25: =FV($U$6,AE$9,,-$S25,0) -> 1.1592741 | AI25: =FV($U$6,AG$9,,-$S25,0) -> 1.1940523 | AK25: =FV($U$6,AI$9,,-$S25,0) -> 1.2298739 | AM25: =FV($U$6,AK$9,,-$S25,0) -> 1.2667701 | AO25: =FV($U$6,AM$9,,-$S25,0) -> 1.3047732 | AQ25: =FV($U$6,AO$9,,-$S25,0) -> 1.3439164 | AS25: =FV($U$6,AQ$9,,-$S25,0) -> 1.3842339 | AU25: =FV($U$6,AS$9,,-$S25,0) -> 1.4257609 | AW25: =FV($U$6,AU$9,,-$S25,0) -> 1.4685337 | AY25: =FV($U$6,AW$9,,-$S25,0) -> 1.5125897
